// converted by version 1.3
// on Mon Jun 22 12:25:38 AEST 2020

.package com/makina/security/OpenFIPS201 {
	.aid 0xA0:0x0:0x0:0x3:0x8:0x0:0x0:0x10:0x0;
	.version 1.0;

	.imports {
		0xA0:0x0:0x0:0x0:0x62:0x1:0x1 1.5;		//javacard/framework
		0xA0:0x0:0x0:0x1:0x51:0x0 1.0;		//org/globalplatform
		0xA0:0x0:0x0:0x0:0x62:0x0:0x1 1.0;		//java/lang
		0xA0:0x0:0x0:0x0:0x62:0x2:0x1 1.5;		//javacardx/crypto
		0xA0:0x0:0x0:0x0:0x62:0x1:0x2 1.5;		//javacard/security
	}

	.applet {
		0xA0:0x0:0x0:0x3:0x8:0x0:0x0:0x10:0x0:0x1:0x0 OpenFIPS201;
	}

	.constantPool {
		// 0
		instanceFieldRef 1.1 CVMPIN/cvm;
		// 1
		instanceFieldRef 2.0[] ChainBuffer/dataPtr;
		// 2
		instanceFieldRef short[] ChainBuffer/context;
		// 3
		instanceFieldRef ChainBuffer OpenFIPS201/chainBuffer;
		// 4
		instanceFieldRef PIV OpenFIPS201/piv;
		// 5
		instanceFieldRef 1.2 OpenFIPS201/secureChannel;
		// 6
		instanceFieldRef byte[] PIV/scratch;
		// 7
		instanceFieldRef byte[] PIV/authenticationContext;
		// 8
		instanceFieldRef ChainBuffer PIV/chainBuffer;
		// 9
		instanceFieldRef PIVSecurityProvider PIV/cspPIV;
		// 10
		instanceFieldRef TLVReader PIV/tlvReader;
		// 11
		instanceFieldRef TLVWriter PIV/tlvWriter;
		// 12
		instanceFieldRef 0.9 PIVSecurityProvider/cardPIN;
		// 13
		instanceFieldRef 0.9 PIVSecurityProvider/cardPUK;
		// 14
		instanceFieldRef byte[] PIVDataObject/content;
		// 15
		instanceFieldRef CVMPIN PIVSecurityProvider/globalPIN;
		// 16
		instanceFieldRef PIVDataObject PIV/firstDataObject;
		// 17
		instanceFieldRef PIVObject PIVObject/nextObject;
		// 18
		instanceFieldRef PIVObject PIVObject/nextObject;
		// 19
		instanceFieldRef byte[] PIVObject/header;
		// 20
		instanceFieldRef boolean[] PIVKeyObject/securityFlags;
		// 21
		instanceFieldRef 4.9 PIVKeyObjectPKI/publicKey;
		// 22
		instanceFieldRef 4.8 PIVKeyObjectPKI/privateKey;
		// 23
		instanceFieldRef 4.16 PIVKeyObjectPKI/keyPair;
		// 24
		instanceFieldRef 4.4 PIVKeyObjectSYM/key;
		// 25
		instanceFieldRef short PIVDataObject/bytesAllocated;
		// 26
		instanceFieldRef 3.1 PIVSecurityProvider/cspAES;
		// 27
		instanceFieldRef 3.1 PIVSecurityProvider/cspRSA;
		// 28
		instanceFieldRef 3.1 PIVSecurityProvider/cspTDEA;
		// 29
		instanceFieldRef 4.14 PIVSecurityProvider/cspRNG;
		// 30
		instanceFieldRef boolean[] PIVSecurityProvider/securityFlags;
		// 31
		instanceFieldRef PIVKeyObject PIVSecurityProvider/firstKey;
		// 32
		instanceFieldRef PIVObject PIVObject/nextObject;
		// 33
		instanceFieldRef 2.0[] TLVReader/dataPtr;
		// 34
		instanceFieldRef short[] TLVReader/context;
		// 35
		instanceFieldRef 2.0[] TLVWriter/dataPtr;
		// 36
		instanceFieldRef short[] TLVWriter/context;
		// 37
		virtualMethodRef PIV/deselect()V;
		// 38
		staticMethodRef 1.3.4()Lorg/globalplatform/SecureChannel;;		// org/globalplatform/GPSystem.getSecureChannel()Lorg/globalplatform/SecureChannel;
			.descriptor	Lorg/globalplatform/SecureChannel;	1.2;

		// 39
		virtualMethodRef 0.10.6()S;		// setIncomingAndReceive()S
		// 40
		virtualMethodRef 0.10.14()Z;		// isISOInterindustryCLA()Z
		// 41
		staticMethodRef 0.10.2()B;		// javacard/framework/APDU.getProtocol()B
		// 42
		virtualMethodRef PIV/updateSecurityStatus(ZZ)V;
		// 43
		virtualMethodRef ChainBuffer/processOutgoing(Ljavacard/framework/APDU;)V;
			.descriptor	Ljavacard/framework/APDU;	0.10;

		// 44
		virtualMethodRef 0.10.16()S;		// getOffsetCdata()S
		// 45
		virtualMethodRef ChainBuffer/processIncomingObject([BSS)V;
		// 46
		virtualMethodRef ChainBuffer/checkIncomingAPDU([BSS)V;
		// 47
		virtualMethodRef PIV/resetPinAlways()V;
		// 48
		staticMethodRef OpenFIPS201/processGP_SECURECHANNEL(Ljavacard/framework/APDU;)V;
			.descriptor	Ljavacard/framework/APDU;	0.10;

		// 49
		staticMethodRef OpenFIPS201/processPIV_SELECT(Ljavacard/framework/APDU;)V;
			.descriptor	Ljavacard/framework/APDU;	0.10;

		// 50
		staticMethodRef OpenFIPS201/processPIV_GET_DATA(Ljavacard/framework/APDU;)V;
			.descriptor	Ljavacard/framework/APDU;	0.10;

		// 51
		staticMethodRef OpenFIPS201/processPIV_VERIFY(Ljavacard/framework/APDU;)V;
			.descriptor	Ljavacard/framework/APDU;	0.10;

		// 52
		staticMethodRef OpenFIPS201/processPIV_CHANGE_REFERENCE_DATA(Ljavacard/framework/APDU;)V;
			.descriptor	Ljavacard/framework/APDU;	0.10;

		// 53
		staticMethodRef OpenFIPS201/processPIV_RESET_RETRY_COUNTER(Ljavacard/framework/APDU;)V;
			.descriptor	Ljavacard/framework/APDU;	0.10;

		// 54
		staticMethodRef OpenFIPS201/processPIV_GENERAL_AUTHENTICATE(Ljavacard/framework/APDU;)V;
			.descriptor	Ljavacard/framework/APDU;	0.10;

		// 55
		staticMethodRef OpenFIPS201/processPIV_PUT_DATA(Ljavacard/framework/APDU;)V;
			.descriptor	Ljavacard/framework/APDU;	0.10;

		// 56
		staticMethodRef OpenFIPS201/processPIV_GENERATE_ASSYMETRIC_KEYPAIR(Ljavacard/framework/APDU;)V;
			.descriptor	Ljavacard/framework/APDU;	0.10;

		// 57
		virtualMethodRef 0.10.8(SS)V;		// setOutgoingAndSend(SS)V
		// 58
		virtualMethodRef 0.3.3()Z;		// selectingApplet()Z
		// 59
		virtualMethodRef PIV/select([BSS)S;
		// 60
		virtualMethodRef PIV/getData([BSS)S;
		// 61
		virtualMethodRef PIV/putDataAdmin([BSS)V;
		// 62
		virtualMethodRef PIV/putData([BSS)V;
		// 63
		virtualMethodRef PIV/verifyGetStatus(B)V;
		// 64
		virtualMethodRef PIV/verifyResetStatus(B)V;
		// 65
		virtualMethodRef PIV/verify(B[BSS)V;
		// 66
		virtualMethodRef PIV/changeReferenceData(B[BSS)V;
		// 67
		virtualMethodRef PIV/changeReferenceDataAdmin(B[BSS)V;
		// 68
		virtualMethodRef PIV/resetRetryCounter(B[BSS)V;
		// 69
		virtualMethodRef PIV/generalAuthenticate([BSS)S;
		// 70
		virtualMethodRef PIV/generateAsymmetricKeyPair([BSS)S;
		// 71
		staticMethodRef 0.8.13(SB)[B;		// javacard/framework/JCSystem.makeTransientByteArray(SB)[B
		// 72
		staticMethodRef 1.3.3(B)Lorg/globalplatform/CVM;;		// org/globalplatform/GPSystem.getCVM(B)Lorg/globalplatform/CVM;
			.descriptor	Lorg/globalplatform/CVM;	1.1;

		// 73
		staticMethodRef 0.8.15(SB)[S;		// javacard/framework/JCSystem.makeTransientShortArray(SB)[S
		// 74
		staticMethodRef 0.9.0(BB)V;		// javacard/framework/OwnerPIN.<init>(BB)V
		// 75
		classRef PIVSecurityProvider;
		// 76
		staticMethodRef PIVSecurityProvider/<init>()V;
		// 77
		staticMethodRef 0.8.0()V;		// javacard/framework/JCSystem.abortTransaction()V
		// 78
		classRef TLVReader;
		// 79
		staticMethodRef TLVReader/<init>()V;
		// 80
		virtualMethodRef ChainBuffer/reset()V;
		// 81
		classRef TLVWriter;
		// 82
		staticMethodRef TLVWriter/<init>()V;
		// 83
		staticMethodRef 0.8.2()V;		// javacard/framework/JCSystem.commitTransaction()V
		// 84
		virtualMethodRef PIVSecurityProvider/generateRandom([BSS)V;
		// 85
		staticMethodRef 0.16.3([BSSB)S;		// javacard/framework/Util.arrayFillNonAtomic([BSSB)S
		// 86
		virtualMethodRef 0.9.8([BSB)V;		// update([BSB)V
		// 87
		virtualMethodRef PIVSecurityProvider/zeroise([BSS)V;
		// 88
		staticMethodRef 0.8.1()V;		// javacard/framework/JCSystem.beginTransaction()V
		// 89
		staticFieldRef byte[] Config/DEFAULT_APT;
		// 90
		virtualMethodRef PIVSecurityProvider/resetSecurityStatus()V;
		// 91
		staticMethodRef PIV/findDataObject(B)Lcom/makina/security/OpenFIPS201/PIVDataObject;;
		// 92
		virtualMethodRef PIVSecurityProvider/checkAccessModeObject(Lcom/makina/security/OpenFIPS201/PIVObject;)Z;
		// 93
		virtualMethodRef PIVDataObject/isInitialised()Z;
		// 94
		virtualMethodRef PIVDataObject/getLength()S;
		// 95
		staticMethodRef 0.16.4([BS)S;		// javacard/framework/Util.getShort([BS)S
		// 96
		virtualMethodRef ChainBuffer/setOutgoing([BSSZ)V;
		// 97
		virtualMethodRef PIVSecurityProvider/checkAccessModeAdmin(Z)Z;
		// 98
		staticMethodRef TLVReader/getLength([BS)S;
		// 99
		staticMethodRef TLVReader/getDataOffset([BS)S;
		// 100
		virtualMethodRef PIVDataObject/allocate(S)V;
		// 101
		virtualMethodRef ChainBuffer/setIncomingObject([BSSZ)V;
		// 102
		classRef 2.2;		// java/lang/Exception
		// 103
		virtualMethodRef PIVSecurityProvider/getIsContactless()Z;
		// 104
		staticMethodRef PIV/verifyPinFormat(B[BSS)Z;
		// 105
		virtualMethodRef 0.9.2()B;		// getTriesRemaining()B
		// 106
		virtualMethodRef 0.9.1([BSB)Z;		// check([BSB)Z
		// 107
		virtualMethodRef PIVSecurityProvider/setPINAlways(Z)V;
		// 108
		virtualMethodRef 0.9.4()Z;		// isValidated()Z
		// 109
		virtualMethodRef 0.9.5()V;		// reset()V
		// 110
		virtualMethodRef PIVSecurityProvider/setIsContactless(Z)V;
		// 111
		virtualMethodRef PIVSecurityProvider/setIsSecureChannel(Z)V;
		// 112
		virtualMethodRef ChainBuffer/processIncomingAPDU([BSS[BS)S;
		// 113
		virtualMethodRef TLVReader/init([BSS)V;
		// 114
		virtualMethodRef PIVSecurityProvider/selectKey(BB)Lcom/makina/security/OpenFIPS201/PIVKeyObject;;
		// 115
		virtualMethodRef PIVObject/isInitialised()Z;
		// 116
		virtualMethodRef TLVReader/find(B)Z;
		// 117
		virtualMethodRef TLVReader/moveInto()Z;
		// 118
		virtualMethodRef TLVReader/getOffset()S;
		// 119
		virtualMethodRef TLVReader/match(B)Z;
		// 120
		virtualMethodRef TLVReader/isNull()Z;
		// 121
		virtualMethodRef TLVReader/moveNext()Z;
		// 122
		virtualMethodRef TLVReader/setOffset(S)V;
		// 123
		virtualMethodRef PIVKeyObject/getBlockLength()S;
		// 124
		staticMethodRef PIV/authenticateReset()V;
		// 125
		virtualMethodRef PIVKeyObject/hasRole(B)Z;
		// 126
		virtualMethodRef TLVReader/getLength()S;
		// 127
		virtualMethodRef TLVReader/getDataOffset()S;
		// 128
		virtualMethodRef PIVSecurityProvider/encrypt(Lcom/makina/security/OpenFIPS201/PIVKeyObject;[BSS[BS)S;
		// 129
		virtualMethodRef TLVWriter/init([BSSS)V;
		// 130
		virtualMethodRef TLVWriter/writeTag(B)S;
		// 131
		virtualMethodRef TLVWriter/writeLength(S)S;
		// 132
		virtualMethodRef TLVWriter/getOffset()S;
		// 133
		virtualMethodRef TLVWriter/setOffset(S)V;
		// 134
		virtualMethodRef TLVWriter/finish()S;
		// 135
		virtualMethodRef PIVKeyObject/resetSecurityStatus()V;
		// 136
		virtualMethodRef PIVObject/getId()B;
		// 137
		virtualMethodRef PIVKeyObject/getMechanism()B;
		// 138
		staticMethodRef 0.16.0([BS[BSS)B;		// javacard/framework/Util.arrayCompare([BS[BSS)B
		// 139
		virtualMethodRef PIVKeyObject/setSecurityStatus()V;
		// 140
		virtualMethodRef PIVSecurityProvider/keyExists(B)Z;
		// 141
		classRef PIVKeyObjectPKI;
		// 142
		virtualMethodRef PIVKeyObjectPKI/generate()V;
		// 143
		virtualMethodRef PIVKeyObject/getKeyLength()S;
		// 144
		virtualMethodRef PIVKeyObject/getKeyLength()S;
		// 145
		virtualMethodRef PIVKeyObjectPKI/getModulus([BS)S;
		// 146
		virtualMethodRef PIVKeyObjectPKI/getPublicExponent([BS)S;
		// 147
		virtualMethodRef TLVReader/toByte()B;
		// 148
		staticMethodRef ChainBuffer/resetAbort()V;
		// 149
		virtualMethodRef PIVObject/getId()B;
		// 150
		staticMethodRef 0.7.1(S)V;		// javacard/framework/ISOException.throwIt(S)V
		// 151
		staticMethodRef PIV/createDataObject(BBB)V;
		// 152
		virtualMethodRef PIVSecurityProvider/createKey(BBBBB)V;
		// 153
		virtualMethodRef TLVReader/getTag()B;
		// 154
		virtualMethodRef PIVKeyObject/updateElement(B[BSS)V;
		// 155
		virtualMethodRef PIVObject/match(B)Z;
		// 156
		staticMethodRef 0.16.2([BS[BSS)S;		// javacard/framework/Util.arrayCopyNonAtomic([BS[BSS)S
		// 157
		classRef PIVDataObject;
		// 158
		staticMethodRef PIVDataObject/<init>(BBB)V;
		// 159
		staticFieldRef byte[] Config/DEFAULT_DISCOVERY;
		// 160
		staticMethodRef 0.16.1([BS[BSS)S;		// javacard/framework/Util.arrayCopy([BS[BSS)S
		// 161
		staticMethodRef ChainBuffer/resetCommit()V;
		// 162
		staticMethodRef PIVObject/<init>(BBB)V;
		// 163
		staticMethodRef 0.8.12(SB)[Z;		// javacard/framework/JCSystem.makeTransientBooleanArray(SB)[Z
		// 164
		classRef PIVKeyObjectSYM;
		// 165
		staticMethodRef PIVKeyObjectSYM/<init>(BBBBB)V;
		// 166
		staticMethodRef PIVKeyObjectPKI/<init>(BBBBB)V;
		// 167
		staticMethodRef PIVKeyObject/<init>(BBBBB)V;
		// 168
		virtualMethodRef 0.10.1()[B;		// getBuffer()[B
		// 169
		virtualMethodRef 0.10.7()S;		// setOutgoing()S
		// 170
		staticMethodRef PIVKeyObjectPKI/allocate()V;
		// 171
		classRef 4.9;		// javacard/security/RSAPublicKey
		// 172
		classRef 4.8;		// javacard/security/RSAPrivateKey
		// 173
		classRef 4.16;		// javacard/security/KeyPair
		// 174
		staticMethodRef 4.16.0(BS)V;		// javacard/security/KeyPair.<init>(BS)V
		// 175
		virtualMethodRef 0.10.9(S)V;		// setOutgoingLength(S)V
		// 176
		virtualMethodRef 4.16.2()Ljavacard/security/PrivateKey;;		// getPrivate()Ljavacard/security/PrivateKey;
			.descriptor	Ljavacard/security/PrivateKey;	4.2;

		// 177
		virtualMethodRef 4.16.3()Ljavacard/security/PublicKey;;		// getPublic()Ljavacard/security/PublicKey;
			.descriptor	Ljavacard/security/PublicKey;	4.3;

		// 178
		virtualMethodRef 4.16.1()V;		// genKeyPair()V
		// 179
		virtualMethodRef 3.1.3(Ljavacard/security/Key;B)V;		// init(Ljavacard/security/Key;B)V
			.descriptor	Ljavacard/security/Key;	4.0;

		// 180
		virtualMethodRef 3.1.1([BSS[BS)S;		// doFinal([BSS[BS)S
		// 181
		virtualMethodRef PIVKeyObject/getKeyLength()S;
		// 182
		virtualMethodRef 0.10.5([BSS)V;		// sendBytesLong([BSS)V
		// 183
		staticMethodRef PIVKeyObjectSYM/allocate()V;
		// 184
		classRef 4.4;		// javacard/security/SecretKey
		// 185
		classRef 4.10;		// javacard/security/DESKey
		// 186
		virtualMethodRef PIVKeyObjectSYM/clear()V;
		// 187
		classRef 4.20;		// javacard/security/AESKey
		// 188
		staticMethodRef 4.13.0(BSZ)Ljavacard/security/Key;;		// javacard/security/KeyBuilder.buildKey(BSZ)Ljavacard/security/Key;
			.descriptor	Ljavacard/security/Key;	4.0;

		// 189
		staticMethodRef 0.3.0()V;		// javacard/framework/Applet.<init>()V
		// 190
		staticMethodRef 0.8.17()Z;		// javacard/framework/JCSystem.isObjectDeletionSupported()Z
		// 191
		staticMethodRef 0.8.18()V;		// javacard/framework/JCSystem.requestObjectDeletion()V
		// 192
		staticMethodRef 3.1.0(BZ)Ljavacardx/crypto/Cipher;;		// javacardx/crypto/Cipher.getInstance(BZ)Ljavacardx/crypto/Cipher;
			.descriptor	Ljavacardx/crypto/Cipher;	3.1;

		// 193
		classRef ChainBuffer;
		// 194
		staticMethodRef ChainBuffer/<init>()V;
		// 195
		classRef 1.1;		// org/globalplatform/CVM
		// 196
		staticMethodRef 4.14.0(B)Ljavacard/security/RandomData;;		// javacard/security/RandomData.getInstance(B)Ljavacard/security/RandomData;
			.descriptor	Ljavacard/security/RandomData;	4.14;

		// 197
		classRef PIV;
		// 198
		staticMethodRef PIV/<init>(Lcom/makina/security/OpenFIPS201/ChainBuffer;)V;
		// 199
		classRef 0.9;		// javacard/framework/OwnerPIN
		// 200
		classRef CVMPIN;
		// 201
		staticMethodRef CVMPIN/<init>(BB)V;
		// 202
		staticMethodRef 2.0.0()V;		// java/lang/Object.<init>()V
		// 203
		classRef OpenFIPS201;
		// 204
		classRef PIVKeyObject;
		// 205
		virtualMethodRef CVMPIN/isValidated()Z;
		// 206
		virtualMethodRef PIVKeyObject/match(BB)Z;
		// 207
		virtualMethodRef PIVObject/match(B)Z;
		// 208
		staticMethodRef PIVKeyObject/create(BBBBB)Lcom/makina/security/OpenFIPS201/PIVKeyObject;;
		// 209
		virtualMethodRef PIVKeyObject/getSecurityStatus()Z;
		// 210
		virtualMethodRef PIVObject/getModeContactless()B;
		// 211
		virtualMethodRef PIVObject/getModeContact()B;
		// 212
		virtualMethodRef 4.14.1([BSS)V;		// generateData([BSS)V
		// 213
		virtualMethodRef PIVKeyObject/encrypt(Ljavacardx/crypto/Cipher;[BSS[BS)S;
			.descriptor	Ljavacardx/crypto/Cipher;	3.1;

		// 214
		staticMethodRef OpenFIPS201/<init>()V;
		// 215
		virtualMethodRef 0.3.2([BSB)V;		// register([BSB)V
		// 216
		virtualMethodRef TLVReader/isInitialized()Z;
		// 217
		virtualMethodRef TLVReader/getTagShort()S;
		// 218
		virtualMethodRef TLVReader/find(S)Z;
		// 219
		staticMethodRef 0.8.14(SB)[Ljava/lang/Object;;		// javacard/framework/JCSystem.makeTransientObjectArray(SB)[Ljava/lang/Object;
			.descriptor	Ljava/lang/Object;	2.0;

		// 220
		classRef 1.2;		// org/globalplatform/SecureChannel
		// 221
		virtualMethodRef TLVWriter/writeTag(S)S;
		// 222
		staticMethodRef 0.16.6([BSS)S;		// javacard/framework/Util.setShort([BSS)S
		// 223
		virtualMethodRef TLVWriter/reset()V;
	}

	.class public final CVMPIN 0 extends 0.9 {		// extends javacard/framework/OwnerPIN

		.fields {
			 1.1 cvm 0;		// Lorg/globalplatform/CVM;
		}

		.publicMethodTable 1 {
			equals(Ljava/lang/Object;)Z;
			check([BSB)Z;
			getTriesRemaining()B;
			getValidatedFlag()Z;
			isValidated()Z;
			reset()V;
			resetAndUnblock()V;
			setValidatedFlag(Z)V;
			update([BSB)V;
		}

		.packageMethodTable 0 {
		}

		.implementedInterfaceInfoTable { 
			.interface 0.1 { 		// javacard/framework/PIN
				1;		// check([BSB)Z
				2;		// getTriesRemaining()B
				4;		// isValidated()Z
				5;		// reset()V
			}

		}

		.method public <init>(BB)V 0 {
			.stack 3;
			.locals 0;

				L0:	aload_0;
					sload_1;
					sload_2;
					invokespecial 74;		// javacard/framework/OwnerPIN.<init>(BB)V
					aload_0;
					bspush 17;
					invokestatic 72;		// org/globalplatform/GPSystem.getCVM(B)Lorg/globalplatform/CVM;
					putfield_a 0;		// reference com/makina/security/OpenFIPS201/CVMPIN.cvm
					return;
		}

		.method public getTriesRemaining()B 2 {
			.stack 1;
			.locals 0;

				L0:	getfield_a_this 0;		// reference com/makina/security/OpenFIPS201/CVMPIN.cvm
					invokeinterface 1 195 4;		// org/globalplatform/CVM
					sreturn;
		}

		.method public check([BSB)Z 1 {
			.stack 6;
			.locals 0;

				L0:	sconst_0;
					getfield_a_this 0;		// reference com/makina/security/OpenFIPS201/CVMPIN.cvm
					aload_1;
					sload_2;
					sload_3;
					sconst_3;
					invokeinterface 5 195 10;		// org/globalplatform/CVM
					if_scmpne L2;
				L1:	sconst_1;
					goto L3;
				L2:	sconst_0;
				L3:	sreturn;
		}

		.method public isValidated()Z 4 {
			.stack 1;
			.locals 0;

				L0:	getfield_a_this 0;		// reference com/makina/security/OpenFIPS201/CVMPIN.cvm
					invokeinterface 1 195 2;		// org/globalplatform/CVM
					sreturn;
		}

		.method public reset()V 5 {
			.stack 1;
			.locals 0;

				L0:	getfield_a_this 0;		// reference com/makina/security/OpenFIPS201/CVMPIN.cvm
					invokeinterface 1 195 6;		// org/globalplatform/CVM
					pop;
					return;
		}

		.method public update([BSB)V 8 {
			.stack 5;
			.locals 0;

				L0:	getfield_a_this 0;		// reference com/makina/security/OpenFIPS201/CVMPIN.cvm
					aload_1;
					sload_2;
					sload_3;
					sconst_3;
					invokeinterface 5 195 5;		// org/globalplatform/CVM
					pop;
					return;
		}

		.method public resetAndUnblock()V 6 {
			.stack 1;
			.locals 0;

				L0:	getfield_a_this 0;		// reference com/makina/security/OpenFIPS201/CVMPIN.cvm
					invokeinterface 1 195 8;		// org/globalplatform/CVM
					pop;
					return;
		}

	}

	.class public final ChainBuffer 1 extends 2.0 {		// extends java/lang/Object

		.fields {
			private 2.0[] dataPtr 0;		// [Ljava/lang/Object;
			private short[] context 1;		// [S
			public static final short STATE_NONE = 0;		// S
			public static final short STATE_OUTGOING = 1;		// S
			public static final short STATE_INCOMING_OBJECT = 2;		// S
			public static final short STATE_INCOMING_APDU = 3;		// S
			private static final short CONTEXT_STATE = 0;		// S
			private static final short CONTEXT_OFFSET = 1;		// S
			private static final short CONTEXT_INITIAL = 2;		// S
			private static final short CONTEXT_LENGTH = 3;		// S
			private static final short CONTEXT_REMAINING = 4;		// S
			private static final short CONTEXT_CLEAR_ON_COMPLETE = 5;		// S
			private static final short CONTEXT_TRANSACTION = 6;		// S
			private static final short CONTEXT_APDU_CLAINS = 8;		// S
			private static final short CONTEXT_APDU_P1P2 = 9;		// S
			private static final short LENGTH_CONTEXT = 10;		// S
			private static final byte CLA_CHAINING = 16;		// B
			private static final byte INS_GET_RESPONSE = -64;		// B
		}

		.publicMethodTable 1 {
			equals(Ljava/lang/Object;)Z;
			reset()V;
			setOutgoing([BSSZ)V;
			setIncomingObject([BSSZ)V;
			checkIncomingAPDU([BSS)V;
			processIncomingAPDU([BSS[BS)S;
			processIncomingObject([BSS)V;
			processOutgoing(Ljavacard/framework/APDU;)V;
		}

		.packageMethodTable 0 {
		}

		.method public <init>()V 0 {
			.stack 3;
			.locals 0;

				L0:	aload_0;
					invokespecial 202;		// java/lang/Object.<init>()V
					aload_0;
					sconst_1;
					sconst_2;
					invokestatic 219;		// javacard/framework/JCSystem.makeTransientObjectArray(SB)[Ljava/lang/Object;
					putfield_a 1;		// reference com/makina/security/OpenFIPS201/ChainBuffer.dataPtr
					aload_0;
					bspush 10;
					sconst_2;
					invokestatic 73;		// javacard/framework/JCSystem.makeTransientShortArray(SB)[S
					putfield_a 2;		// reference com/makina/security/OpenFIPS201/ChainBuffer.context
					return;
		}

		.method private resetAbort()V {
			.stack 3;
			.locals 0;

				L0:	sconst_0;
					getfield_a_this 2;		// reference com/makina/security/OpenFIPS201/ChainBuffer.context
					bspush 6;
					saload;
					if_scmpeq L2;
				L1:	invokestatic 77;		// javacard/framework/JCSystem.abortTransaction()V
				L2:	aload_0;
					invokevirtual 80;		// reset()V
					return;
		}

		.method private resetCommit()V {
			.stack 3;
			.locals 0;

				L0:	sconst_0;
					getfield_a_this 2;		// reference com/makina/security/OpenFIPS201/ChainBuffer.context
					bspush 6;
					saload;
					if_scmpeq L2;
				L1:	invokestatic 83;		// javacard/framework/JCSystem.commitTransaction()V
				L2:	aload_0;
					invokevirtual 80;		// reset()V
					return;
		}

		.method public reset()V 1 {
			.stack 4;
			.locals 0;

				L0:	getfield_a_this 1;		// reference com/makina/security/OpenFIPS201/ChainBuffer.dataPtr
					sconst_0;
					aaload;
					ifnull L3;
				L1:	getfield_a_this 2;		// reference com/makina/security/OpenFIPS201/ChainBuffer.context
					sconst_5;
					saload;
					ifeq L3;
				L2:	getfield_a_this 1;		// reference com/makina/security/OpenFIPS201/ChainBuffer.dataPtr
					sconst_0;
					aaload;
					checkcast 11 0;		// T_BYTE
					checkcast 11 0;		// T_BYTE
					getfield_a_this 2;		// reference com/makina/security/OpenFIPS201/ChainBuffer.context
					sconst_2;
					saload;
					getfield_a_this 2;		// reference com/makina/security/OpenFIPS201/ChainBuffer.context
					sconst_3;
					saload;
					sconst_0;
					invokestatic 85;		// javacard/framework/Util.arrayFillNonAtomic([BSSB)S
					pop;
				L3:	getfield_a_this 1;		// reference com/makina/security/OpenFIPS201/ChainBuffer.dataPtr
					sconst_0;
					aconst_null;
					aastore;
					getfield_a_this 2;		// reference com/makina/security/OpenFIPS201/ChainBuffer.context
					sconst_0;
					sconst_0;
					sastore;
					getfield_a_this 2;		// reference com/makina/security/OpenFIPS201/ChainBuffer.context
					sconst_1;
					sconst_0;
					sastore;
					getfield_a_this 2;		// reference com/makina/security/OpenFIPS201/ChainBuffer.context
					sconst_2;
					sconst_0;
					sastore;
					getfield_a_this 2;		// reference com/makina/security/OpenFIPS201/ChainBuffer.context
					sconst_4;
					sconst_0;
					sastore;
					getfield_a_this 2;		// reference com/makina/security/OpenFIPS201/ChainBuffer.context
					sconst_3;
					sconst_0;
					sastore;
					getfield_a_this 2;		// reference com/makina/security/OpenFIPS201/ChainBuffer.context
					sconst_5;
					sconst_0;
					sastore;
					getfield_a_this 2;		// reference com/makina/security/OpenFIPS201/ChainBuffer.context
					bspush 8;
					sconst_0;
					sastore;
					getfield_a_this 2;		// reference com/makina/security/OpenFIPS201/ChainBuffer.context
					bspush 9;
					sconst_0;
					sastore;
					getfield_a_this 2;		// reference com/makina/security/OpenFIPS201/ChainBuffer.context
					bspush 6;
					sconst_0;
					sastore;
					return;
		}

		.method public setOutgoing([BSSZ)V 2 {
			.stack 3;
			.locals 0;

				L0:	aload_0;
					invokevirtual 80;		// reset()V
					getfield_a_this 1;		// reference com/makina/security/OpenFIPS201/ChainBuffer.dataPtr
					sconst_0;
					aload_1;
					aastore;
					getfield_a_this 2;		// reference com/makina/security/OpenFIPS201/ChainBuffer.context
					sconst_0;
					sconst_1;
					sastore;
					getfield_a_this 2;		// reference com/makina/security/OpenFIPS201/ChainBuffer.context
					sconst_1;
					sload_2;
					sastore;
					getfield_a_this 2;		// reference com/makina/security/OpenFIPS201/ChainBuffer.context
					sconst_2;
					sload_2;
					sastore;
					getfield_a_this 2;		// reference com/makina/security/OpenFIPS201/ChainBuffer.context
					sconst_4;
					sload_3;
					sastore;
					getfield_a_this 2;		// reference com/makina/security/OpenFIPS201/ChainBuffer.context
					sconst_3;
					sload_3;
					sastore;
					getfield_a_this 2;		// reference com/makina/security/OpenFIPS201/ChainBuffer.context
					sconst_5;
					sload 4;
					ifeq L2;
				L1:	sconst_1;
					goto L3;
				L2:	sconst_0;
				L3:	sastore;
					return;
		}

		.method public setIncomingObject([BSSZ)V 3 {
			.stack 3;
			.locals 0;

				L0:	aload_0;
					invokevirtual 80;		// reset()V
					getfield_a_this 1;		// reference com/makina/security/OpenFIPS201/ChainBuffer.dataPtr
					sconst_0;
					aload_1;
					aastore;
					getfield_a_this 2;		// reference com/makina/security/OpenFIPS201/ChainBuffer.context
					sconst_0;
					sconst_2;
					sastore;
					getfield_a_this 2;		// reference com/makina/security/OpenFIPS201/ChainBuffer.context
					sconst_1;
					sload_2;
					sastore;
					getfield_a_this 2;		// reference com/makina/security/OpenFIPS201/ChainBuffer.context
					sconst_4;
					sload_3;
					sastore;
					getfield_a_this 2;		// reference com/makina/security/OpenFIPS201/ChainBuffer.context
					sconst_3;
					sload_3;
					sastore;
					sload 4;
					ifeq L2;
				L1:	invokestatic 88;		// javacard/framework/JCSystem.beginTransaction()V
					getfield_a_this 2;		// reference com/makina/security/OpenFIPS201/ChainBuffer.context
					bspush 6;
					sconst_1;
					sastore;
				L2:	return;
		}

		.method public checkIncomingAPDU([BSS)V 4 {
			.stack 3;
			.locals 1;

				L0:	sspush -4097;
					sstore 4;
				L1:	getfield_a_this 2;		// reference com/makina/security/OpenFIPS201/ChainBuffer.context
					sconst_0;
					saload;
					sconst_3;
					if_scmpeq L3;
				L2:	return;
				L3:	getfield_a_this 2;		// reference com/makina/security/OpenFIPS201/ChainBuffer.context
					bspush 8;
					saload;
					sspush -4097;
					sand;
					aload_1;
					sconst_0;
					invokestatic 95;		// javacard/framework/Util.getShort([BS)S
					if_scmpne L5;
				L4:	getfield_a_this 2;		// reference com/makina/security/OpenFIPS201/ChainBuffer.context
					bspush 9;
					saload;
					aload_1;
					sconst_2;
					invokestatic 95;		// javacard/framework/Util.getShort([BS)S
					if_scmpeq L6;
				L5:	aload_0;
					invokevirtual 80;		// reset()V
					return;
				L6:	return;
		}

		.method public processIncomingAPDU([BSS[BS)S 5 {
			.stack 5;
			.locals 2;

				L0:	getfield_a_this 2;		// reference com/makina/security/OpenFIPS201/ChainBuffer.context
					sconst_0;
					saload;
					ifeq L3;
				L1:	getfield_a_this 2;		// reference com/makina/security/OpenFIPS201/ChainBuffer.context
					sconst_0;
					saload;
					sconst_3;
					if_scmpeq L3;
				L2:	aload_0;
					invokespecial 148;		// com/makina/security/OpenFIPS201/ChainBuffer.resetAbort()V
					sspush 27013;
					invokestatic 150;		// javacard/framework/ISOException.throwIt(S)V
				L3:	aload_1;
					sconst_0;
					baload;
					bspush 16;
					sand;
					ifne L10;
				L4:	getfield_a_this 2;		// reference com/makina/security/OpenFIPS201/ChainBuffer.context
					sconst_0;
					saload;
					ifne L10;
				L5:	aload_1;
					sload_2;
					aload 4;
					sload 5;
					sload_3;
					invokestatic 156;		// javacard/framework/Util.arrayCopyNonAtomic([BS[BSS)S
					pop;
				L6:	goto L9;
				L7:	astore 6;
				L8:	aload_0;
					invokevirtual 80;		// reset()V
					sspush 27268;
					invokestatic 150;		// javacard/framework/ISOException.throwIt(S)V
				L9:	sload_3;
					sreturn;
				L10:	aload_1;
					sconst_0;
					baload;
					bspush 16;
					sand;
					ifeq L18;
				L11:	getfield_a_this 2;		// reference com/makina/security/OpenFIPS201/ChainBuffer.context
					sconst_0;
					saload;
					ifne L18;
				L12:	getfield_a_this 2;		// reference com/makina/security/OpenFIPS201/ChainBuffer.context
					sconst_0;
					sconst_3;
					sastore;
					getfield_a_this 2;		// reference com/makina/security/OpenFIPS201/ChainBuffer.context
					sconst_2;
					sload_2;
					sastore;
					getfield_a_this 2;		// reference com/makina/security/OpenFIPS201/ChainBuffer.context
					bspush 8;
					aload_1;
					sconst_0;
					invokestatic 95;		// javacard/framework/Util.getShort([BS)S
					sastore;
					getfield_a_this 2;		// reference com/makina/security/OpenFIPS201/ChainBuffer.context
					bspush 9;
					aload_1;
					sconst_2;
					invokestatic 95;		// javacard/framework/Util.getShort([BS)S
					sastore;
				L13:	aload_1;
					sload_2;
					aload 4;
					sload 5;
					sload_3;
					invokestatic 156;		// javacard/framework/Util.arrayCopyNonAtomic([BS[BSS)S
					pop;
				L14:	goto L17;
				L15:	astore 6;
				L16:	aload_0;
					invokevirtual 80;		// reset()V
					sspush 27268;
					invokestatic 150;		// javacard/framework/ISOException.throwIt(S)V
				L17:	getfield_a_this 2;		// reference com/makina/security/OpenFIPS201/ChainBuffer.context
					sconst_3;
					sload_3;
					sastore;
					sconst_0;
					sreturn;
				L18:	aload_1;
					sconst_0;
					baload;
					bspush 16;
					sand;
					ifeq L29;
				L19:	getfield_a_this 2;		// reference com/makina/security/OpenFIPS201/ChainBuffer.context
					sconst_0;
					saload;
					sconst_3;
					if_scmpne L29;
				L20:	getfield_a_this 2;		// reference com/makina/security/OpenFIPS201/ChainBuffer.context
					bspush 8;
					saload;
					aload_1;
					sconst_0;
					invokestatic 95;		// javacard/framework/Util.getShort([BS)S
					if_scmpne L22;
				L21:	getfield_a_this 2;		// reference com/makina/security/OpenFIPS201/ChainBuffer.context
					bspush 9;
					saload;
					aload_1;
					sconst_2;
					invokestatic 95;		// javacard/framework/Util.getShort([BS)S
					if_scmpeq L23;
				L22:	aload_0;
					invokevirtual 80;		// reset()V
					sspush 26755;
					invokestatic 150;		// javacard/framework/ISOException.throwIt(S)V
				L23:	sload 5;
					getfield_a_this 2;		// reference com/makina/security/OpenFIPS201/ChainBuffer.context
					sconst_3;
					saload;
					sadd;
					sstore 5;
				L24:	aload_1;
					sload_2;
					aload 4;
					sload 5;
					sload_3;
					invokestatic 156;		// javacard/framework/Util.arrayCopyNonAtomic([BS[BSS)S
					pop;
				L25:	goto L28;
				L26:	astore 6;
				L27:	aload_0;
					invokevirtual 80;		// reset()V
					sspush 26368;
					invokestatic 150;		// javacard/framework/ISOException.throwIt(S)V
				L28:	getfield_a_this 2;		// reference com/makina/security/OpenFIPS201/ChainBuffer.context
					sconst_3;
					dup2;
					saload;
					sload_3;
					sadd;
					sastore;
					sconst_0;
					sreturn;
				L29:	aload_1;
					sconst_0;
					baload;
					bspush 16;
					sand;
					ifne L41;
				L30:	getfield_a_this 2;		// reference com/makina/security/OpenFIPS201/ChainBuffer.context
					sconst_0;
					saload;
					sconst_3;
					if_scmpne L41;
				L31:	sspush -4097;
					sstore 6;
				L32:	getfield_a_this 2;		// reference com/makina/security/OpenFIPS201/ChainBuffer.context
					bspush 8;
					saload;
					sspush -4097;
					sand;
					aload_1;
					sconst_0;
					invokestatic 95;		// javacard/framework/Util.getShort([BS)S
					if_scmpne L34;
				L33:	getfield_a_this 2;		// reference com/makina/security/OpenFIPS201/ChainBuffer.context
					bspush 9;
					saload;
					aload_1;
					sconst_2;
					invokestatic 95;		// javacard/framework/Util.getShort([BS)S
					if_scmpeq L35;
				L34:	aload_0;
					invokevirtual 80;		// reset()V
					sspush 26755;
					invokestatic 150;		// javacard/framework/ISOException.throwIt(S)V
				L35:	sload 5;
					getfield_a_this 2;		// reference com/makina/security/OpenFIPS201/ChainBuffer.context
					sconst_3;
					saload;
					sadd;
					sstore 5;
				L36:	aload_1;
					sload_2;
					aload 4;
					sload 5;
					sload_3;
					invokestatic 156;		// javacard/framework/Util.arrayCopyNonAtomic([BS[BSS)S
					pop;
				L37:	goto L40;
				L38:	astore 7;
				L39:	aload_0;
					invokevirtual 80;		// reset()V
					sspush 26368;
					invokestatic 150;		// javacard/framework/ISOException.throwIt(S)V
				L40:	sload_3;
					getfield_a_this 2;		// reference com/makina/security/OpenFIPS201/ChainBuffer.context
					sconst_3;
					saload;
					sadd;
					sstore_3;
					aload_0;
					invokevirtual 80;		// reset()V
					sload_3;
					sreturn;
				L41:	aload_0;
					invokevirtual 80;		// reset()V
					sspush 28416;
					invokestatic 150;		// javacard/framework/ISOException.throwIt(S)V
					sconst_0;
					sreturn;
			.exceptionTable {
				// start_block end_block handler_block catch_type_index
				L5 L6 L7 102;
				L13 L14 L15 102;
				L24 L25 L26 102;
				L36 L37 L38 102;
			}
		}

		.method public processIncomingObject([BSS)V 6 {
			.stack 5;
			.locals 1;

				L0:	getfield_a_this 2;		// reference com/makina/security/OpenFIPS201/ChainBuffer.context
					sconst_0;
					saload;
					sconst_2;
					if_scmpeq L2;
				L1:	return;
				L2:	sspush -4097;
					sstore 4;
				L3:	getfield_a_this 2;		// reference com/makina/security/OpenFIPS201/ChainBuffer.context
					sconst_3;
					saload;
					getfield_a_this 2;		// reference com/makina/security/OpenFIPS201/ChainBuffer.context
					sconst_4;
					saload;
					if_scmpne L5;
				L4:	getfield_a_this 2;		// reference com/makina/security/OpenFIPS201/ChainBuffer.context
					bspush 8;
					aload_1;
					sconst_0;
					invokestatic 95;		// javacard/framework/Util.getShort([BS)S
					sspush -4097;
					sand;
					sastore;
					getfield_a_this 2;		// reference com/makina/security/OpenFIPS201/ChainBuffer.context
					bspush 9;
					aload_1;
					sconst_2;
					invokestatic 95;		// javacard/framework/Util.getShort([BS)S
					sastore;
					goto L8;
				L5:	getfield_a_this 2;		// reference com/makina/security/OpenFIPS201/ChainBuffer.context
					bspush 8;
					saload;
					aload_1;
					sconst_0;
					invokestatic 95;		// javacard/framework/Util.getShort([BS)S
					sspush -4097;
					sand;
					if_scmpne L7;
				L6:	getfield_a_this 2;		// reference com/makina/security/OpenFIPS201/ChainBuffer.context
					bspush 9;
					saload;
					aload_1;
					sconst_2;
					invokestatic 95;		// javacard/framework/Util.getShort([BS)S
					if_scmpeq L8;
				L7:	aload_0;
					invokespecial 148;		// com/makina/security/OpenFIPS201/ChainBuffer.resetAbort()V
					return;
				L8:	aload_1;
					sconst_0;
					baload;
					bspush 16;
					sand;
					ifeq L17;
				L9:	sload_3;
					ifne L11;
				L10:	return;
				L11:	sload_3;
					getfield_a_this 2;		// reference com/makina/security/OpenFIPS201/ChainBuffer.context
					sconst_4;
					saload;
					if_scmplt L13;
				L12:	aload_0;
					invokespecial 148;		// com/makina/security/OpenFIPS201/ChainBuffer.resetAbort()V
					sspush 26368;
					invokestatic 150;		// javacard/framework/ISOException.throwIt(S)V
				L13:	sconst_0;
					getfield_a_this 2;		// reference com/makina/security/OpenFIPS201/ChainBuffer.context
					bspush 6;
					saload;
					if_scmpeq L15;
				L14:	aload_1;
					sload_2;
					getfield_a_this 1;		// reference com/makina/security/OpenFIPS201/ChainBuffer.dataPtr
					sconst_0;
					aaload;
					checkcast 11 0;		// T_BYTE
					checkcast 11 0;		// T_BYTE
					getfield_a_this 2;		// reference com/makina/security/OpenFIPS201/ChainBuffer.context
					sconst_1;
					saload;
					sload_3;
					invokestatic 160;		// javacard/framework/Util.arrayCopy([BS[BSS)S
					pop;
					goto L16;
				L15:	aload_1;
					sload_2;
					getfield_a_this 1;		// reference com/makina/security/OpenFIPS201/ChainBuffer.dataPtr
					sconst_0;
					aaload;
					checkcast 11 0;		// T_BYTE
					checkcast 11 0;		// T_BYTE
					getfield_a_this 2;		// reference com/makina/security/OpenFIPS201/ChainBuffer.context
					sconst_1;
					saload;
					sload_3;
					invokestatic 156;		// javacard/framework/Util.arrayCopyNonAtomic([BS[BSS)S
					pop;
				L16:	getfield_a_this 2;		// reference com/makina/security/OpenFIPS201/ChainBuffer.context
					sconst_1;
					dup2;
					saload;
					sload_3;
					sadd;
					sastore;
					getfield_a_this 2;		// reference com/makina/security/OpenFIPS201/ChainBuffer.context
					sconst_4;
					dup2;
					saload;
					sload_3;
					ssub;
					sastore;
					sspush -28672;
					invokestatic 150;		// javacard/framework/ISOException.throwIt(S)V
					goto L22;
				L17:	sload_3;
					ifne L19;
				L18:	aload_0;
					invokespecial 148;		// com/makina/security/OpenFIPS201/ChainBuffer.resetAbort()V
					sspush 26368;
					invokestatic 150;		// javacard/framework/ISOException.throwIt(S)V
				L19:	sload_3;
					getfield_a_this 2;		// reference com/makina/security/OpenFIPS201/ChainBuffer.context
					sconst_4;
					saload;
					if_scmpeq L21;
				L20:	aload_0;
					invokespecial 148;		// com/makina/security/OpenFIPS201/ChainBuffer.resetAbort()V
					sspush 26368;
					invokestatic 150;		// javacard/framework/ISOException.throwIt(S)V
				L21:	aload_1;
					sload_2;
					getfield_a_this 1;		// reference com/makina/security/OpenFIPS201/ChainBuffer.dataPtr
					sconst_0;
					aaload;
					checkcast 11 0;		// T_BYTE
					checkcast 11 0;		// T_BYTE
					getfield_a_this 2;		// reference com/makina/security/OpenFIPS201/ChainBuffer.context
					sconst_1;
					saload;
					sload_3;
					invokestatic 160;		// javacard/framework/Util.arrayCopy([BS[BSS)S
					pop;
					aload_0;
					invokespecial 161;		// com/makina/security/OpenFIPS201/ChainBuffer.resetCommit()V
					sspush -28672;
					invokestatic 150;		// javacard/framework/ISOException.throwIt(S)V
				L22:	return;
		}

		.method public processOutgoing(Ljavacard/framework/APDU;)V 7 {
			.stack 4;
			.locals 4;

			.descriptor	Ljavacard/framework/APDU;	0.10;

				L0:	getfield_a_this 2;		// reference com/makina/security/OpenFIPS201/ChainBuffer.context
					sconst_0;
					saload;
					sconst_1;
					if_scmpeq L2;
				L1:	return;
				L2:	aload_1;
					invokevirtual 168;		// getBuffer()[B
					astore_2;
				L3:	aload_2;
					sconst_1;
					baload;
					bspush -64;
					if_scmpeq L6;
				L4:	getfield_a_this 2;		// reference com/makina/security/OpenFIPS201/ChainBuffer.context
					sconst_4;
					saload;
					getfield_a_this 2;		// reference com/makina/security/OpenFIPS201/ChainBuffer.context
					sconst_3;
					saload;
					if_scmpeq L6;
				L5:	aload_0;
					invokevirtual 80;		// reset()V
					return;
				L6:	aload_1;
					invokevirtual 169;		// setOutgoing()S
					sstore_3;
				L7:	sload_3;
					ifne L9;
				L8:	sspush 256;
					sstore_3;
				L9:	getfield_a_this 2;		// reference com/makina/security/OpenFIPS201/ChainBuffer.context
					sconst_4;
					saload;
					sload_3;
					if_scmple L11;
				L10:	sload_3;
					goto L12;
				L11:	getfield_a_this 2;		// reference com/makina/security/OpenFIPS201/ChainBuffer.context
					sconst_4;
					saload;
				L12:	sstore 4;
				L13:	aload_1;
					sload 4;
					invokevirtual 175;		// setOutgoingLength(S)V
					aload_1;
					getfield_a_this 1;		// reference com/makina/security/OpenFIPS201/ChainBuffer.dataPtr
					sconst_0;
					aaload;
					checkcast 11 0;		// T_BYTE
					checkcast 11 0;		// T_BYTE
					getfield_a_this 2;		// reference com/makina/security/OpenFIPS201/ChainBuffer.context
					sconst_1;
					saload;
					sload 4;
					invokevirtual 182;		// sendBytesLong([BSS)V
					getfield_a_this 2;		// reference com/makina/security/OpenFIPS201/ChainBuffer.context
					sconst_4;
					dup2;
					saload;
					sload 4;
					ssub;
					sastore;
					getfield_a_this 2;		// reference com/makina/security/OpenFIPS201/ChainBuffer.context
					sconst_1;
					dup2;
					saload;
					sload 4;
					sadd;
					sastore;
					getfield_a_this 2;		// reference com/makina/security/OpenFIPS201/ChainBuffer.context
					sconst_4;
					saload;
					ifne L15;
				L14:	aload_0;
					invokevirtual 80;		// reset()V
					sspush -28672;
					invokestatic 150;		// javacard/framework/ISOException.throwIt(S)V
					goto L20;
				L15:	getfield_a_this 2;		// reference com/makina/security/OpenFIPS201/ChainBuffer.context
					sconst_4;
					saload;
					sspush 255;
					if_scmple L17;
				L16:	sspush 255;
					goto L18;
				L17:	getfield_a_this 2;		// reference com/makina/security/OpenFIPS201/ChainBuffer.context
					sconst_4;
					saload;
				L18:	sstore 5;
				L19:	sspush 24832;
					sload 5;
					sor;
					invokestatic 150;		// javacard/framework/ISOException.throwIt(S)V
				L20:	return;
		}

	}

	.class public abstract Config 2 extends 2.0 {		// extends java/lang/Object

		.fields {
			public static final boolean FEATURE_PIV_TEST_VECTORS = 0;		// Z
			public static final boolean FEATURE_PIN_CARD_ENABLED = 1;		// Z
			public static final boolean FEATURE_PIN_GLOBAL_ENABLED = 0;		// Z
			public static final boolean FEATURE_PIN_GLOBAL_PREFERRED = 0;		// Z
			public static final boolean FEATURE_PIN_GLOBAL_CHANGE = 0;		// Z
			public static final boolean FEATURE_PIN_INIT_RANDOM = 1;		// Z
			public static final boolean FEATURE_PUK_CHANGE = 1;		// Z
			public static final boolean FEATURE_PUK_INIT_RANDOM = 1;		// Z
			public static final boolean FEATURE_PIN_OVER_CONTACTLESS = 0;		// Z
			public static final boolean FEATURE_PUK_OVER_CONTACTLESS = 0;		// Z
			public static final boolean FEATURE_RESTRICT_SCP_TO_CONTACT = 1;		// Z
			public static final boolean FEATURE_ERROR_ON_EMPTY_DATA_OBJECT = 1;		// Z
			public static final boolean FEATURE_DISCOVERY_OBJECT_DEFAULT = 1;		// Z
			public static final boolean FEATURE_STRICT_APDU_CHAINING = 0;		// Z
			public static final byte PIN_RETRIES = 6;		// B
			public static final byte PIN_RETRIES_INTERMEDIATE = 1;		// B
			public static final byte PUK_RETRIES = 6;		// B
			public static final byte PUK_RETRIES_INTERMEDIATE = 1;		// B
			public static final byte PIN_LENGTH_MIN = 6;		// B
			public static final byte PIN_LENGTH_MAX = 8;		// B
			protected static final byte[] DEFAULT_PIN 0 = {49,50,51,52,53,54,-1,-1};		// [B
			protected static final byte[] DEFAULT_PUK 1 = {49,50,51,52,53,54,55,56};		// [B
			protected static final byte[] TEST_VECTOR_RANDOM 2 = {0,1,2,3,4,5,6,7,8,9,10,11,12,13,14,15,16,17,18,19,20,21,22,23,24,25,26,27,28,29,30,31};		// [B
			protected static final byte[] DEFAULT_DISCOVERY 3 = {126,18,79,11,-96,0,0,3,8,0,0,16,0,1,0,95,47,2,64,16};		// [B
			protected static final byte[] DEFAULT_APT 4 = {97,-127,-119,79,11,-96,0,0,3,8,0,0,16,0,1,0,121,7,79,5,-96,0,0,3,8,80,11,79,112,101,110,70,73,80,83,50,48,49,95,80,73,104,116,116,112,58,47,47,110,118,108,112,117,98,115,46,110,105,115,116,46,103,111,118,47,110,105,115,116,112,117,98,115,47,83,112,101,99,105,97,108,80,117,98,108,105,99,97,116,105,111,110,115,47,78,73,83,84,46,83,80,46,56,48,48,45,55,51,45,52,46,112,100,102,-84,24,-128,1,0,-128,1,3,-128,1,8,-128,1,10,-128,1,12,-128,1,6,-128,1,7,6,1,0};		// [B
		}

		.publicMethodTable 1 {
			equals(Ljava/lang/Object;)Z;
		}

		.packageMethodTable 0 {
		}

		.method public <init>()V 0 {
			.stack 1;
			.locals 0;

				L0:	aload_0;
					invokespecial 202;		// java/lang/Object.<init>()V
					return;
		}

	}

	.class public final OpenFIPS201 3 extends 0.3 {		// extends javacard/framework/Applet

		.fields {
			private PIV piv 0;		// Lcom/makina/security/OpenFIPS201/PIV;
			private ChainBuffer chainBuffer 1;		// Lcom/makina/security/OpenFIPS201/ChainBuffer;
			private 1.2 secureChannel 2;		// Lorg/globalplatform/SecureChannel;
			private static final byte INS_GP_INITIALIZE_UPDATE = 80;		// B
			private static final byte INS_GP_EXTERNAL_AUTHENTICATE = -126;		// B
			private static final byte INS_PIV_SELECT = -92;		// B
			private static final byte INS_PIV_GET_DATA = -53;		// B
			private static final byte INS_PIV_VERIFY = 32;		// B
			private static final byte INS_PIV_CHANGE_REFERENCE_DATA = 36;		// B
			private static final byte INS_PIV_RESET_RETRY_COUNTER = 44;		// B
			private static final byte INS_PIV_GENERAL_AUTHENTICATE = -121;		// B
			private static final byte INS_PIV_PUT_DATA = -37;		// B
			private static final byte INS_PIV_GENERATE_ASSYMETRIC_KEYPAIR = 71;		// B
			private static final byte ZERO_BYTE = 0;		// B
			private static final short ZERO_SHORT = 0;		// S
			private static final short LENGTH_BYTE = 1;		// S
			private static final short LENGTH_SHORT = 2;		// S
		}

		.publicMethodTable 4 {
			equals(Ljava/lang/Object;)Z;
			register()V;
			register([BSB)V;
			selectingApplet()Z;
			deselect()V;
			getShareableInterfaceObject(Ljavacard/framework/AID;B)Ljavacard/framework/Shareable;;
			select()Z;
			process(Ljavacard/framework/APDU;)V;
		}

		.packageMethodTable 0 {
		}

		.method public <init>()V 0 {
			.stack 4;
			.locals 0;

				L0:	aload_0;
					invokespecial 189;		// javacard/framework/Applet.<init>()V
					aload_0;
					new 193;		// com/makina/security/OpenFIPS201/ChainBuffer
					dup;
					invokespecial 194;		// com/makina/security/OpenFIPS201/ChainBuffer.<init>()V
					putfield_a 3;		// reference com/makina/security/OpenFIPS201/OpenFIPS201.chainBuffer
					aload_0;
					new 197;		// com/makina/security/OpenFIPS201/PIV
					dup;
					getfield_a_this 3;		// reference com/makina/security/OpenFIPS201/OpenFIPS201.chainBuffer
					invokespecial 198;		// com/makina/security/OpenFIPS201/PIV.<init>(Lcom/makina/security/OpenFIPS201/ChainBuffer;)V
					putfield_a 4;		// reference com/makina/security/OpenFIPS201/OpenFIPS201.piv
					return;
		}

		.method public static install([BSB)V 1 {
			.stack 5;
			.locals 0;

				L0:	new 203;		// com/makina/security/OpenFIPS201/OpenFIPS201
					dup;
					invokespecial 214;		// com/makina/security/OpenFIPS201/OpenFIPS201.<init>()V
					aload_0;
					sload_1;
					sconst_1;
					sadd;
					aload_0;
					sload_1;
					baload;
					invokevirtual 215;		// register([BSB)V
					return;
		}

		.method public deselect()V 4 {
			.stack 1;
			.locals 0;

				L0:	getfield_a_this 5;		// reference com/makina/security/OpenFIPS201/OpenFIPS201.secureChannel
					ifnull L2;
				L1:	getfield_a_this 5;		// reference com/makina/security/OpenFIPS201/OpenFIPS201.secureChannel
					invokeinterface 1 220 5;		// org/globalplatform/SecureChannel
				L2:	getfield_a_this 4;		// reference com/makina/security/OpenFIPS201/OpenFIPS201.piv
					invokevirtual 37;		// deselect()V
					return;
		}

		.method public process(Ljavacard/framework/APDU;)V 7 {
			.stack 5;
			.locals 6;

			.descriptor	Ljavacard/framework/APDU;	0.10;

				L0:	getfield_a_this 5;		// reference com/makina/security/OpenFIPS201/OpenFIPS201.secureChannel
					ifnonnull L2;
				L1:	aload_0;
					invokestatic 38;		// org/globalplatform/GPSystem.getSecureChannel()Lorg/globalplatform/SecureChannel;
					putfield_a 5;		// reference com/makina/security/OpenFIPS201/OpenFIPS201.secureChannel
				L2:	aload_1;
					invokevirtual 168;		// getBuffer()[B
					astore_2;
				L3:	aload_1;
					invokevirtual 39;		// setIncomingAndReceive()S
					sstore_3;
				L4:	aload_1;
					invokevirtual 40;		// isISOInterindustryCLA()Z
					ifne L8;
				L5:	aload_2;
					sconst_1;
					baload;
					bspush 80;
					if_scmpeq L8;
				L6:	aload_2;
					sconst_1;
					baload;
					bspush -126;
					if_scmpeq L8;
				L7:	sspush 28160;
					invokestatic 150;		// javacard/framework/ISOException.throwIt(S)V
				L8:	bspush -125;
					sstore 4;
				L9:	invokestatic 41;		// javacard/framework/APDU.getProtocol()B
					bspush -16;
					sand;
					sstore 5;
				L10:	sload 5;
					bspush -128;
					if_scmpeq L12;
				L11:	sload 5;
					bspush -112;
					if_scmpne L13;
				L12:	sconst_1;
					goto L14;
				L13:	sconst_0;
				L14:	sstore 6;
				L15:	getfield_a_this 5;		// reference com/makina/security/OpenFIPS201/OpenFIPS201.secureChannel
					invokeinterface 1 220 6;		// org/globalplatform/SecureChannel
					bspush -125;
					sand;
					bspush -125;
					if_scmpne L18;
				L16:	getfield_a_this 5;		// reference com/makina/security/OpenFIPS201/OpenFIPS201.secureChannel
					aload_2;
					sconst_0;
					sconst_5;
					sload_3;
					sadd;
					invokeinterface 4 220 2;		// org/globalplatform/SecureChannel
					sstore_3;
					sinc 3 -5;
					sconst_1;
					sstore 7;
				L17:	goto L19;
				L18:	sconst_0;
					sstore 7;
				L19:	getfield_a_this 4;		// reference com/makina/security/OpenFIPS201/OpenFIPS201.piv
					sload 6;
					sload 7;
					invokevirtual 42;		// updateSecurityStatus(ZZ)V
					getfield_a_this 3;		// reference com/makina/security/OpenFIPS201/OpenFIPS201.chainBuffer
					aload_1;
					invokevirtual 43;		// processOutgoing(Ljavacard/framework/APDU;)V
					getfield_a_this 3;		// reference com/makina/security/OpenFIPS201/OpenFIPS201.chainBuffer
					aload_2;
					aload_1;
					invokevirtual 44;		// getOffsetCdata()S
					sload_3;
					invokevirtual 45;		// processIncomingObject([BSS)V
					getfield_a_this 3;		// reference com/makina/security/OpenFIPS201/OpenFIPS201.chainBuffer
					aload_2;
					aload_1;
					invokevirtual 44;		// getOffsetCdata()S
					sload_3;
					invokevirtual 46;		// checkIncomingAPDU([BSS)V
					aload_2;
					sconst_1;
					baload;
					bspush -121;
					if_scmpeq L21;
				L20:	getfield_a_this 4;		// reference com/makina/security/OpenFIPS201/OpenFIPS201.piv
					invokevirtual 47;		// resetPinAlways()V
				L21:	aload_2;
					sconst_1;
					baload;
					slookupswitch L36 10 -126 L25 -121 L33 -92 L28 -53 L29 -37 L34 32 L30 36 L31 44 L32 71 L35 80 L22;
				L22:	sload 6;
					ifeq L24;
				L23:	sspush 27010;
					invokestatic 150;		// javacard/framework/ISOException.throwIt(S)V
				L24:	getfield_a_this 5;		// reference com/makina/security/OpenFIPS201/OpenFIPS201.secureChannel
					invokeinterface 1 220 5;		// org/globalplatform/SecureChannel
					aload_0;
					aload_1;
					invokespecial 48;		// com/makina/security/OpenFIPS201/OpenFIPS201.processGP_SECURECHANNEL(Ljavacard/framework/APDU;)V
					goto L37;
				L25:	sload 6;
					ifeq L27;
				L26:	sspush 27010;
					invokestatic 150;		// javacard/framework/ISOException.throwIt(S)V
				L27:	aload_0;
					aload_1;
					invokespecial 48;		// com/makina/security/OpenFIPS201/OpenFIPS201.processGP_SECURECHANNEL(Ljavacard/framework/APDU;)V
					goto L37;
				L28:	aload_0;
					aload_1;
					invokespecial 49;		// com/makina/security/OpenFIPS201/OpenFIPS201.processPIV_SELECT(Ljavacard/framework/APDU;)V
					goto L37;
				L29:	aload_0;
					aload_1;
					invokespecial 50;		// com/makina/security/OpenFIPS201/OpenFIPS201.processPIV_GET_DATA(Ljavacard/framework/APDU;)V
					goto L37;
				L30:	aload_0;
					aload_1;
					invokespecial 51;		// com/makina/security/OpenFIPS201/OpenFIPS201.processPIV_VERIFY(Ljavacard/framework/APDU;)V
					goto L37;
				L31:	aload_0;
					aload_1;
					invokespecial 52;		// com/makina/security/OpenFIPS201/OpenFIPS201.processPIV_CHANGE_REFERENCE_DATA(Ljavacard/framework/APDU;)V
					goto L37;
				L32:	aload_0;
					aload_1;
					invokespecial 53;		// com/makina/security/OpenFIPS201/OpenFIPS201.processPIV_RESET_RETRY_COUNTER(Ljavacard/framework/APDU;)V
					goto L37;
				L33:	aload_0;
					aload_1;
					invokespecial 54;		// com/makina/security/OpenFIPS201/OpenFIPS201.processPIV_GENERAL_AUTHENTICATE(Ljavacard/framework/APDU;)V
					goto L37;
				L34:	aload_0;
					aload_1;
					invokespecial 55;		// com/makina/security/OpenFIPS201/OpenFIPS201.processPIV_PUT_DATA(Ljavacard/framework/APDU;)V
					goto L37;
				L35:	aload_0;
					aload_1;
					invokespecial 56;		// com/makina/security/OpenFIPS201/OpenFIPS201.processPIV_GENERATE_ASSYMETRIC_KEYPAIR(Ljavacard/framework/APDU;)V
					goto L37;
				L36:	sspush 27904;
					invokestatic 150;		// javacard/framework/ISOException.throwIt(S)V
				L37:	return;
		}

		.method private processGP_SECURECHANNEL(Ljavacard/framework/APDU;)V {
			.stack 3;
			.locals 1;

			.descriptor	Ljavacard/framework/APDU;	0.10;

				L0:	getfield_a_this 5;		// reference com/makina/security/OpenFIPS201/OpenFIPS201.secureChannel
					aload_1;
					invokeinterface 2 220 0;		// org/globalplatform/SecureChannel
					sstore_2;
				L1:	aload_1;
					sconst_5;
					sload_2;
					invokevirtual 57;		// setOutgoingAndSend(SS)V
					return;
		}

		.method private processPIV_SELECT(Ljavacard/framework/APDU;)V {
			.stack 4;
			.locals 2;

			.descriptor	Ljavacard/framework/APDU;	0.10;

				L0:	aload_1;
					invokevirtual 168;		// getBuffer()[B
					astore_2;
				L1:	aload_2;
					sconst_4;
					baload;
					sspush 255;
					sand;
					sstore_3;
				L2:	aload_0;
					invokevirtual 58;		// selectingApplet()Z
					ifne L4;
				L3:	sspush 27266;
					invokestatic 150;		// javacard/framework/ISOException.throwIt(S)V
				L4:	getfield_a_this 4;		// reference com/makina/security/OpenFIPS201/OpenFIPS201.piv
					aload_2;
					sconst_5;
					sload_3;
					invokevirtual 59;		// select([BSS)S
					sstore_3;
					aload_1;
					sconst_5;
					sload_3;
					invokevirtual 57;		// setOutgoingAndSend(SS)V
					return;
		}

		.method private processPIV_GET_DATA(Ljavacard/framework/APDU;)V {
			.stack 4;
			.locals 4;

			.descriptor	Ljavacard/framework/APDU;	0.10;

				L0:	bspush 63;
					sstore_2;
				L1:	sconst_m1;
					sstore_3;
				L2:	aload_1;
					invokevirtual 168;		// getBuffer()[B
					astore 4;
				L3:	aload 4;
					sconst_4;
					baload;
					sspush 255;
					sand;
					sstore 5;
				L4:	aload 4;
					sconst_2;
					baload;
					bspush 63;
					if_scmpeq L6;
				L5:	sspush 27270;
					invokestatic 150;		// javacard/framework/ISOException.throwIt(S)V
				L6:	aload 4;
					sconst_3;
					baload;
					sconst_m1;
					if_scmpeq L8;
				L7:	sspush 27270;
					invokestatic 150;		// javacard/framework/ISOException.throwIt(S)V
				L8:	getfield_a_this 4;		// reference com/makina/security/OpenFIPS201/OpenFIPS201.piv
					aload 4;
					sconst_5;
					sload 5;
					invokevirtual 60;		// getData([BSS)S
					pop;
					getfield_a_this 3;		// reference com/makina/security/OpenFIPS201/OpenFIPS201.chainBuffer
					aload_1;
					invokevirtual 43;		// processOutgoing(Ljavacard/framework/APDU;)V
					return;
		}

		.method private processPIV_PUT_DATA(Ljavacard/framework/APDU;)V {
			.stack 4;
			.locals 6;

			.descriptor	Ljavacard/framework/APDU;	0.10;

				L0:	bspush 63;
					sstore_2;
				L1:	sconst_m1;
					sstore_3;
				L2:	sconst_0;
					sstore 4;
				L3:	aload_1;
					invokevirtual 168;		// getBuffer()[B
					astore 5;
				L4:	aload 5;
					sconst_4;
					baload;
					sspush 255;
					sand;
					sstore 6;
				L5:	aload 5;
					sconst_2;
					baload;
					bspush 63;
					if_scmpeq L7;
				L6:	sspush 27270;
					invokestatic 150;		// javacard/framework/ISOException.throwIt(S)V
				L7:	sconst_0;
					sstore 7;
				L8:	aload 5;
					sconst_3;
					baload;
					ifne L10;
				L9:	sconst_1;
					sstore 7;
					goto L12;
				L10:	aload 5;
					sconst_3;
					baload;
					sconst_m1;
					if_scmpeq L12;
				L11:	sspush 27270;
					invokestatic 150;		// javacard/framework/ISOException.throwIt(S)V
				L12:	sload 7;
					ifeq L14;
				L13:	getfield_a_this 4;		// reference com/makina/security/OpenFIPS201/OpenFIPS201.piv
					aload 5;
					sconst_5;
					sload 6;
					invokevirtual 61;		// putDataAdmin([BSS)V
					goto L15;
				L14:	getfield_a_this 4;		// reference com/makina/security/OpenFIPS201/OpenFIPS201.piv
					aload 5;
					sconst_5;
					sload 6;
					invokevirtual 62;		// putData([BSS)V
				L15:	return;
		}

		.method private processPIV_VERIFY(Ljavacard/framework/APDU;)V {
			.stack 5;
			.locals 6;

			.descriptor	Ljavacard/framework/APDU;	0.10;

				L0:	sconst_0;
					sstore_2;
				L1:	sconst_m1;
					sstore_3;
				L2:	sconst_m1;
					sstore 4;
				L3:	bspush 8;
					sstore 5;
				L4:	aload_1;
					invokevirtual 168;		// getBuffer()[B
					astore 6;
				L5:	aload 6;
					sconst_4;
					baload;
					sspush 255;
					sand;
					sstore 7;
				L6:	aload 6;
					sconst_2;
					baload;
					ifne L9;
				L7:	sload 7;
					ifne L9;
				L8:	getfield_a_this 4;		// reference com/makina/security/OpenFIPS201/OpenFIPS201.piv
					aload 6;
					sconst_3;
					baload;
					invokevirtual 63;		// verifyGetStatus(B)V
					return;
				L9:	aload 6;
					sconst_2;
					baload;
					sconst_m1;
					if_scmpne L12;
				L10:	sload 7;
					ifne L12;
				L11:	getfield_a_this 4;		// reference com/makina/security/OpenFIPS201/OpenFIPS201.piv
					aload 6;
					sconst_3;
					baload;
					invokevirtual 64;		// verifyResetStatus(B)V
					return;
				L12:	aload 6;
					sconst_2;
					baload;
					ifne L15;
				L13:	sload 7;
					ifeq L15;
				L14:	getfield_a_this 4;		// reference com/makina/security/OpenFIPS201/OpenFIPS201.piv
					aload 6;
					sconst_3;
					baload;
					aload 6;
					sconst_5;
					sload 7;
					invokevirtual 65;		// verify(B[BSS)V
					return;
				L15:	sspush 27270;
					invokestatic 150;		// javacard/framework/ISOException.throwIt(S)V
					return;
		}

		.method private processPIV_CHANGE_REFERENCE_DATA(Ljavacard/framework/APDU;)V {
			.stack 5;
			.locals 6;

			.descriptor	Ljavacard/framework/APDU;	0.10;

				L0:	sconst_0;
					sstore_2;
				L1:	sconst_m1;
					sstore_3;
				L2:	bspush 16;
					sstore 4;
				L3:	aload_1;
					invokevirtual 168;		// getBuffer()[B
					astore 5;
				L4:	aload 5;
					sconst_4;
					baload;
					sspush 255;
					sand;
					sstore 6;
				L5:	aload 5;
					sconst_3;
					baload;
					ifeq L8;
				L6:	aload 5;
					sconst_3;
					baload;
					bspush -128;
					if_scmpeq L8;
				L7:	aload 5;
					sconst_3;
					baload;
					bspush -127;
					if_scmpne L9;
				L8:	sconst_1;
					goto L10;
				L9:	sconst_0;
				L10:	sstore 7;
				L11:	sload 7;
					ifeq L14;
				L12:	aload 5;
					sconst_2;
					baload;
					sconst_m1;
					if_scmpne L14;
				L13:	sconst_0;
					sstore 7;
				L14:	sload 7;
					ifeq L17;
				L15:	aload 5;
					sconst_2;
					baload;
					ifeq L17;
				L16:	sspush 27270;
					invokestatic 150;		// javacard/framework/ISOException.throwIt(S)V
				L17:	sload 7;
					ifeq L20;
				L18:	sload 6;
					bspush 16;
					if_scmpeq L20;
				L19:	sspush 27264;
					invokestatic 150;		// javacard/framework/ISOException.throwIt(S)V
				L20:	sload 7;
					ifeq L22;
				L21:	getfield_a_this 4;		// reference com/makina/security/OpenFIPS201/OpenFIPS201.piv
					aload 5;
					sconst_3;
					baload;
					aload 5;
					sconst_5;
					sload 6;
					invokevirtual 66;		// changeReferenceData(B[BSS)V
					goto L23;
				L22:	getfield_a_this 4;		// reference com/makina/security/OpenFIPS201/OpenFIPS201.piv
					aload 5;
					sconst_3;
					baload;
					aload 5;
					sconst_5;
					sload 6;
					invokevirtual 67;		// changeReferenceDataAdmin(B[BSS)V
				L23:	return;
		}

		.method private processPIV_RESET_RETRY_COUNTER(Ljavacard/framework/APDU;)V {
			.stack 5;
			.locals 4;

			.descriptor	Ljavacard/framework/APDU;	0.10;

				L0:	sconst_0;
					sstore_2;
				L1:	bspush 16;
					sstore_3;
				L2:	aload_1;
					invokevirtual 168;		// getBuffer()[B
					astore 4;
				L3:	aload 4;
					sconst_4;
					baload;
					sspush 255;
					sand;
					sstore 5;
				L4:	aload 4;
					sconst_2;
					baload;
					ifeq L6;
				L5:	sspush 27270;
					invokestatic 150;		// javacard/framework/ISOException.throwIt(S)V
				L6:	sload 5;
					bspush 16;
					if_scmpeq L8;
				L7:	sspush 27264;
					invokestatic 150;		// javacard/framework/ISOException.throwIt(S)V
				L8:	getfield_a_this 4;		// reference com/makina/security/OpenFIPS201/OpenFIPS201.piv
					aload 4;
					sconst_3;
					baload;
					aload 4;
					sconst_5;
					sload 5;
					invokevirtual 68;		// resetRetryCounter(B[BSS)V
					return;
		}

		.method private processPIV_GENERAL_AUTHENTICATE(Ljavacard/framework/APDU;)V {
			.stack 4;
			.locals 2;

			.descriptor	Ljavacard/framework/APDU;	0.10;

				L0:	aload_1;
					invokevirtual 168;		// getBuffer()[B
					astore_2;
				L1:	aload_2;
					sconst_4;
					baload;
					sspush 255;
					sand;
					sstore_3;
				L2:	getfield_a_this 4;		// reference com/makina/security/OpenFIPS201/OpenFIPS201.piv
					aload_2;
					sconst_5;
					sload_3;
					invokevirtual 69;		// generalAuthenticate([BSS)S
					sstore_3;
					sload_3;
					ifeq L4;
				L3:	getfield_a_this 3;		// reference com/makina/security/OpenFIPS201/OpenFIPS201.chainBuffer
					aload_1;
					invokevirtual 43;		// processOutgoing(Ljavacard/framework/APDU;)V
				L4:	return;
		}

		.method private processPIV_GENERATE_ASSYMETRIC_KEYPAIR(Ljavacard/framework/APDU;)V {
			.stack 4;
			.locals 3;

			.descriptor	Ljavacard/framework/APDU;	0.10;

				L0:	sconst_0;
					sstore_2;
				L1:	aload_1;
					invokevirtual 168;		// getBuffer()[B
					astore_3;
				L2:	aload_3;
					sconst_4;
					baload;
					sspush 255;
					sand;
					sstore 4;
				L3:	aload_3;
					sconst_2;
					baload;
					ifeq L5;
				L4:	sspush 27270;
					invokestatic 150;		// javacard/framework/ISOException.throwIt(S)V
				L5:	getfield_a_this 4;		// reference com/makina/security/OpenFIPS201/OpenFIPS201.piv
					aload_3;
					sconst_5;
					sload 4;
					invokevirtual 70;		// generateAsymmetricKeyPair([BSS)S
					pop;
					getfield_a_this 3;		// reference com/makina/security/OpenFIPS201/OpenFIPS201.chainBuffer
					aload_1;
					invokevirtual 43;		// processOutgoing(Ljavacard/framework/APDU;)V
					return;
		}

	}

	.class public final PIV 4 extends 2.0 {		// extends java/lang/Object

		.fields {
			private PIVDataObject firstDataObject 0;		// Lcom/makina/security/OpenFIPS201/PIVDataObject;
			private ChainBuffer chainBuffer 1;		// Lcom/makina/security/OpenFIPS201/ChainBuffer;
			 TLVReader tlvReader 2;		// Lcom/makina/security/OpenFIPS201/TLVReader;
			 TLVWriter tlvWriter 3;		// Lcom/makina/security/OpenFIPS201/TLVWriter;
			private PIVSecurityProvider cspPIV 4;		// Lcom/makina/security/OpenFIPS201/PIVSecurityProvider;
			private byte[] scratch 5;		// [B
			private byte[] authenticationContext 6;		// [B
			public static final short LENGTH_SCRATCH = 284;		// S
			public static final byte ID_KEY_GLOBAL_PIN = 0;		// B
			public static final byte ID_KEY_PIN = -128;		// B
			public static final byte ID_KEY_PUK = -127;		// B
			public static final byte ID_ALG_DEFAULT = 0;		// B
			public static final byte ID_ALG_TDEA_3KEY = 3;		// B
			public static final byte ID_ALG_RSA_1024 = 6;		// B
			public static final byte ID_ALG_RSA_2048 = 7;		// B
			public static final byte ID_ALG_AES_128 = 8;		// B
			public static final byte ID_ALG_AES_192 = 10;		// B
			public static final byte ID_ALG_AES_256 = 12;		// B
			public static final short SW_RETRIES_REMAINING = 25536;		// S
			public static final short SW_REFERENCE_NOT_FOUND = 27272;		// S
			public static final short SW_OPERATION_BLOCKED = 27011;		// S
			private static final short OFFSET_AUTH_STATE = 0;		// S
			private static final short OFFSET_AUTH_ID = 1;		// S
			private static final short OFFSET_AUTH_MECHANISM = 2;		// S
			private static final short OFFSET_AUTH_CHALLENGE = 3;		// S
			private static final short LENGTH_CHALLENGE = 16;		// S
			private static final short LENGTH_AUTH_STATE = 21;		// S
			private static final short AUTH_STATE_NONE = 0;		// S
			private static final short AUTH_STATE_EXTERNAL = 1;		// S
			private static final short AUTH_STATE_MUTUAL = 2;		// S
		}

		.publicMethodTable 1 {
			equals(Ljava/lang/Object;)Z;
			select([BSS)S;
			deselect()V;
			getData([BSS)S;
			putData([BSS)V;
			verify(B[BSS)V;
			verifyGetStatus(B)V;
			verifyResetStatus(B)V;
			changeReferenceData(B[BSS)V;
			resetRetryCounter(B[BSS)V;
			updateSecurityStatus(ZZ)V;
			resetPinAlways()V;
			generalAuthenticate([BSS)S;
			generateAsymmetricKeyPair([BSS)S;
			putDataAdmin([BSS)V;
			changeReferenceDataAdmin(B[BSS)V;
		}

		.packageMethodTable 0 {
		}

		.method public <init>(Lcom/makina/security/OpenFIPS201/ChainBuffer;)V 0 {
			.stack 4;
			.locals 0;

				L0:	aload_0;
					invokespecial 202;		// java/lang/Object.<init>()V
					aload_0;
					sspush 284;
					sconst_2;
					invokestatic 71;		// javacard/framework/JCSystem.makeTransientByteArray(SB)[B
					putfield_a 6;		// reference com/makina/security/OpenFIPS201/PIV.scratch
					aload_0;
					bspush 21;
					sconst_2;
					invokestatic 71;		// javacard/framework/JCSystem.makeTransientByteArray(SB)[B
					putfield_a 7;		// reference com/makina/security/OpenFIPS201/PIV.authenticationContext
					aload_0;
					aload_1;
					putfield_a 8;		// reference com/makina/security/OpenFIPS201/PIV.chainBuffer
					aload_1;
					invokevirtual 80;		// reset()V
					aload_0;
					new 75;		// com/makina/security/OpenFIPS201/PIVSecurityProvider
					dup;
					invokespecial 76;		// com/makina/security/OpenFIPS201/PIVSecurityProvider.<init>()V
					putfield_a 9;		// reference com/makina/security/OpenFIPS201/PIV.cspPIV
					aload_0;
					new 78;		// com/makina/security/OpenFIPS201/TLVReader
					dup;
					invokespecial 79;		// com/makina/security/OpenFIPS201/TLVReader.<init>()V
					putfield_a 10;		// reference com/makina/security/OpenFIPS201/PIV.tlvReader
					aload_0;
					new 81;		// com/makina/security/OpenFIPS201/TLVWriter
					dup;
					invokespecial 82;		// com/makina/security/OpenFIPS201/TLVWriter.<init>()V
					putfield_a 11;		// reference com/makina/security/OpenFIPS201/PIV.tlvWriter
					getfield_a_this 9;		// reference com/makina/security/OpenFIPS201/PIV.cspPIV
					getfield_a_this 6;		// reference com/makina/security/OpenFIPS201/PIV.scratch
					sconst_0;
					bspush 8;
					invokevirtual 84;		// generateRandom([BSS)V
					getfield_a_this 9;		// reference com/makina/security/OpenFIPS201/PIV.cspPIV
					getfield_a 12;		// reference com/makina/security/OpenFIPS201/PIVSecurityProvider.cardPIN
					getfield_a_this 6;		// reference com/makina/security/OpenFIPS201/PIV.scratch
					sconst_0;
					bspush 8;
					invokevirtual 86;		// update([BSB)V
					getfield_a_this 9;		// reference com/makina/security/OpenFIPS201/PIV.cspPIV
					getfield_a_this 6;		// reference com/makina/security/OpenFIPS201/PIV.scratch
					sconst_0;
					bspush 8;
					invokevirtual 87;		// zeroise([BSS)V
					getfield_a_this 9;		// reference com/makina/security/OpenFIPS201/PIV.cspPIV
					getfield_a_this 6;		// reference com/makina/security/OpenFIPS201/PIV.scratch
					sconst_0;
					bspush 8;
					invokevirtual 84;		// generateRandom([BSS)V
					getfield_a_this 9;		// reference com/makina/security/OpenFIPS201/PIV.cspPIV
					getfield_a 13;		// reference com/makina/security/OpenFIPS201/PIVSecurityProvider.cardPUK
					getfield_a_this 6;		// reference com/makina/security/OpenFIPS201/PIV.scratch
					sconst_0;
					bspush 8;
					invokevirtual 86;		// update([BSB)V
					getfield_a_this 9;		// reference com/makina/security/OpenFIPS201/PIV.cspPIV
					getfield_a_this 6;		// reference com/makina/security/OpenFIPS201/PIV.scratch
					sconst_0;
					bspush 8;
					invokevirtual 87;		// zeroise([BSS)V
					return;
		}

		.method public select([BSS)S 1 {
			.stack 5;
			.locals 0;

				L0:	getstatic_a 89;		// reference com/makina/security/OpenFIPS201/Config.DEFAULT_APT
					sconst_0;
					aload_1;
					sload_2;
					getstatic_a 89;		// reference com/makina/security/OpenFIPS201/Config.DEFAULT_APT
					arraylength;
					invokestatic 156;		// javacard/framework/Util.arrayCopyNonAtomic([BS[BSS)S
					pop;
					getstatic_a 89;		// reference com/makina/security/OpenFIPS201/Config.DEFAULT_APT
					arraylength;
					sreturn;
		}

		.method public deselect()V 2 {
			.stack 1;
			.locals 0;

				L0:	getfield_a_this 9;		// reference com/makina/security/OpenFIPS201/PIV.cspPIV
					invokevirtual 90;		// resetSecurityStatus()V
					return;
		}

		.method public getData([BSS)S 3 {
			.stack 5;
			.locals 11;

				L0:	bspush 92;
					sstore 4;
				L1:	bspush 126;
					sstore 5;
				L2:	bspush 127;
					sstore 6;
				L3:	bspush 97;
					sstore 7;
				L4:	bspush 95;
					sstore 8;
				L5:	bspush -63;
					sstore 9;
				L6:	sconst_1;
					sstore 10;
				L7:	sconst_2;
					sstore 11;
				L8:	sconst_3;
					sstore 12;
				L9:	aload_1;
					sload_2;
					sinc 2 1;
					baload;
					bspush 92;
					if_scmpeq L11;
				L10:	sspush 27264;
					invokestatic 150;		// javacard/framework/ISOException.throwIt(S)V
				L11:	sconst_0;
					sstore 13;
				L12:	aload_1;
					sload_2;
					baload;
					stableswitch L26 1 3 L13 L16 L21;
				L13:	sinc 2 1;
					aload_1;
					sload_2;
					baload;
					bspush 126;
					if_scmpeq L15;
				L14:	sspush 27272;
					invokestatic 150;		// javacard/framework/ISOException.throwIt(S)V
				L15:	bspush 126;
					sstore 13;
					goto L27;
				L16:	sinc 2 1;
					aload_1;
					sload_2;
					baload;
					bspush 127;
					if_scmpeq L18;
				L17:	sspush 27272;
					invokestatic 150;		// javacard/framework/ISOException.throwIt(S)V
				L18:	sinc 2 1;
					aload_1;
					sload_2;
					baload;
					bspush 97;
					if_scmpeq L20;
				L19:	sspush 27272;
					invokestatic 150;		// javacard/framework/ISOException.throwIt(S)V
				L20:	bspush 97;
					sstore 13;
					goto L27;
				L21:	sinc 2 1;
					aload_1;
					sload_2;
					baload;
					bspush 95;
					if_scmpeq L23;
				L22:	sspush 27272;
					invokestatic 150;		// javacard/framework/ISOException.throwIt(S)V
				L23:	sinc 2 1;
					aload_1;
					sload_2;
					baload;
					bspush -63;
					if_scmpeq L25;
				L24:	sspush 27272;
					invokestatic 150;		// javacard/framework/ISOException.throwIt(S)V
				L25:	sinc 2 1;
					aload_1;
					sload_2;
					baload;
					sstore 13;
					goto L27;
				L26:	sspush 27264;
					invokestatic 150;		// javacard/framework/ISOException.throwIt(S)V
				L27:	aload_0;
					sload 13;
					invokespecial 91;		// com/makina/security/OpenFIPS201/PIV.findDataObject(B)Lcom/makina/security/OpenFIPS201/PIVDataObject;
					astore 14;
				L28:	aload 14;
					ifnonnull L30;
				L29:	sspush 27266;
					invokestatic 150;		// javacard/framework/ISOException.throwIt(S)V
				L30:	getfield_a_this 9;		// reference com/makina/security/OpenFIPS201/PIV.cspPIV
					aload 14;
					invokevirtual 92;		// checkAccessModeObject(Lcom/makina/security/OpenFIPS201/PIVObject;)Z
					ifne L32;
				L31:	sspush 27010;
					invokestatic 150;		// javacard/framework/ISOException.throwIt(S)V
				L32:	aload 14;
					invokevirtual 93;		// isInitialised()Z
					ifne L34;
				L33:	sspush 27266;
					invokestatic 150;		// javacard/framework/ISOException.throwIt(S)V
				L34:	aload 14;
					invokevirtual 94;		// getLength()S
					sstore_3;
					getfield_a_this 8;		// reference com/makina/security/OpenFIPS201/PIV.chainBuffer
					aload 14;
					getfield_a 14;		// reference com/makina/security/OpenFIPS201/PIVDataObject.content
					sconst_0;
					sload_3;
					sconst_0;
					invokevirtual 96;		// setOutgoing([BSSZ)V
					sload_3;
					sreturn;
		}

		.method public putData([BSS)V 4 {
			.stack 5;
			.locals 14;

				L0:	bspush 92;
					sstore 4;
				L1:	bspush 83;
					sstore 5;
				L2:	bspush 126;
					sstore 6;
				L3:	bspush 127;
					sstore 7;
				L4:	bspush 97;
					sstore 8;
				L5:	bspush 95;
					sstore 9;
				L6:	bspush -63;
					sstore 10;
				L7:	sconst_1;
					sstore 11;
				L8:	sconst_2;
					sstore 12;
				L9:	sconst_3;
					sstore 13;
				L10:	sload_2;
					sstore 14;
				L11:	getfield_a_this 9;		// reference com/makina/security/OpenFIPS201/PIV.cspPIV
					sconst_0;
					invokevirtual 97;		// checkAccessModeAdmin(Z)Z
					ifne L13;
				L12:	sspush 27010;
					invokestatic 150;		// javacard/framework/ISOException.throwIt(S)V
				L13:	aload_1;
					sload_2;
					sinc 2 1;
					baload;
					bspush 92;
					if_scmpeq L15;
				L14:	sspush 27272;
					invokestatic 150;		// javacard/framework/ISOException.throwIt(S)V
				L15:	sconst_0;
					sstore 15;
				L16:	aload_1;
					sload_2;
					baload;
					stableswitch L30 1 3 L17 L20 L25;
				L17:	sinc 2 1;
					aload_1;
					sload_2;
					baload;
					bspush 126;
					if_scmpeq L19;
				L18:	sspush 27272;
					invokestatic 150;		// javacard/framework/ISOException.throwIt(S)V
				L19:	bspush 126;
					sstore 15;
					goto L31;
				L20:	sinc 2 1;
					aload_1;
					sload_2;
					baload;
					bspush 127;
					if_scmpeq L22;
				L21:	sspush 27272;
					invokestatic 150;		// javacard/framework/ISOException.throwIt(S)V
				L22:	sinc 2 1;
					aload_1;
					sload_2;
					baload;
					bspush 97;
					if_scmpeq L24;
				L23:	sspush 27272;
					invokestatic 150;		// javacard/framework/ISOException.throwIt(S)V
				L24:	bspush 97;
					sstore 15;
					goto L31;
				L25:	sinc 2 1;
					aload_1;
					sload_2;
					baload;
					bspush 95;
					if_scmpeq L27;
				L26:	sspush 27272;
					invokestatic 150;		// javacard/framework/ISOException.throwIt(S)V
				L27:	sinc 2 1;
					aload_1;
					sload_2;
					baload;
					bspush -63;
					if_scmpeq L29;
				L28:	sspush 27272;
					invokestatic 150;		// javacard/framework/ISOException.throwIt(S)V
				L29:	sinc 2 1;
					aload_1;
					sload_2;
					baload;
					sstore 15;
					goto L31;
				L30:	sspush 27264;
					invokestatic 150;		// javacard/framework/ISOException.throwIt(S)V
				L31:	sinc 2 1;
					aload_1;
					sload_2;
					baload;
					bspush 83;
					if_scmpeq L33;
				L32:	sspush 27264;
					invokestatic 150;		// javacard/framework/ISOException.throwIt(S)V
				L33:	aload_0;
					sload 15;
					invokespecial 91;		// com/makina/security/OpenFIPS201/PIV.findDataObject(B)Lcom/makina/security/OpenFIPS201/PIVDataObject;
					astore 16;
				L34:	aload 16;
					ifnonnull L36;
				L35:	sspush 27266;
					invokestatic 150;		// javacard/framework/ISOException.throwIt(S)V
				L36:	aload_1;
					sload_2;
					invokestatic 98;		// com/makina/security/OpenFIPS201/TLVReader.getLength([BS)S
					sstore 17;
				L37:	sload 17;
					aload_1;
					sload_2;
					invokestatic 99;		// com/makina/security/OpenFIPS201/TLVReader.getDataOffset([BS)S
					sload_2;
					ssub;
					sadd;
					sstore 17;
					aload 16;
					sload 17;
					invokevirtual 100;		// allocate(S)V
					sload_3;
					sload_2;
					sload 14;
					ssub;
					ssub;
					sstore_3;
					getfield_a_this 8;		// reference com/makina/security/OpenFIPS201/PIV.chainBuffer
					aload 16;
					getfield_a 14;		// reference com/makina/security/OpenFIPS201/PIVDataObject.content
					sconst_0;
					sload 17;
					sconst_0;
					invokevirtual 101;		// setIncomingObject([BSSZ)V
					getfield_a_this 8;		// reference com/makina/security/OpenFIPS201/PIV.chainBuffer
					aload_1;
					sload_2;
					sload_3;
					invokevirtual 45;		// processIncomingObject([BSS)V
					return;
		}

		.method public verify(B[BSS)V 5 {
			.stack 5;
			.locals 1;

				L0:	aconst_null;
					astore 5;
				L1:	sload_1;
					slookupswitch L4 2 -128 L3 0 L2;
				L2:	sspush 27272;
					invokestatic 150;		// javacard/framework/ISOException.throwIt(S)V
					getfield_a_this 9;		// reference com/makina/security/OpenFIPS201/PIV.cspPIV
					getfield_a 15;		// reference com/makina/security/OpenFIPS201/PIVSecurityProvider.globalPIN
					astore 5;
					goto L5;
				L3:	getfield_a_this 9;		// reference com/makina/security/OpenFIPS201/PIV.cspPIV
					getfield_a 12;		// reference com/makina/security/OpenFIPS201/PIVSecurityProvider.cardPIN
					astore 5;
					goto L5;
				L4:	sspush 27272;
					invokestatic 150;		// javacard/framework/ISOException.throwIt(S)V
				L5:	getfield_a_this 9;		// reference com/makina/security/OpenFIPS201/PIV.cspPIV
					invokevirtual 103;		// getIsContactless()Z
					ifeq L7;
				L6:	sspush 27010;
					invokestatic 150;		// javacard/framework/ISOException.throwIt(S)V
				L7:	aload_0;
					sload_1;
					aload_2;
					sload_3;
					sload 4;
					invokespecial 104;		// com/makina/security/OpenFIPS201/PIV.verifyPinFormat(B[BSS)Z
					ifne L9;
				L8:	sspush 27264;
					invokestatic 150;		// javacard/framework/ISOException.throwIt(S)V
				L9:	aload 5;
					invokevirtual 105;		// getTriesRemaining()B
					ifne L11;
				L10:	sspush 27011;
					invokestatic 150;		// javacard/framework/ISOException.throwIt(S)V
				L11:	aload 5;
					invokevirtual 105;		// getTriesRemaining()B
					sconst_1;
					if_scmpgt L14;
				L12:	getfield_a_this 9;		// reference com/makina/security/OpenFIPS201/PIV.cspPIV
					invokevirtual 103;		// getIsContactless()Z
					ifeq L14;
				L13:	sspush 27011;
					invokestatic 150;		// javacard/framework/ISOException.throwIt(S)V
				L14:	aload 5;
					aload_2;
					sload_3;
					sload 4;
					s2b;
					invokevirtual 106;		// check([BSB)Z
					ifne L18;
				L15:	aload 5;
					invokevirtual 105;		// getTriesRemaining()B
					ifne L17;
				L16:	sspush 27011;
					invokestatic 150;		// javacard/framework/ISOException.throwIt(S)V
				L17:	sspush 25536;
					aload 5;
					invokevirtual 105;		// getTriesRemaining()B
					sor;
					invokestatic 150;		// javacard/framework/ISOException.throwIt(S)V
				L18:	getfield_a_this 9;		// reference com/makina/security/OpenFIPS201/PIV.cspPIV
					sconst_1;
					invokevirtual 107;		// setPINAlways(Z)V
					return;
		}

		.method public verifyGetStatus(B)V 6 {
			.stack 2;
			.locals 1;

				L0:	aconst_null;
					astore_2;
				L1:	sload_1;
					slookupswitch L4 2 -128 L3 0 L2;
				L2:	sspush 27272;
					invokestatic 150;		// javacard/framework/ISOException.throwIt(S)V
					getfield_a_this 9;		// reference com/makina/security/OpenFIPS201/PIV.cspPIV
					getfield_a 15;		// reference com/makina/security/OpenFIPS201/PIVSecurityProvider.globalPIN
					astore_2;
					goto L5;
				L3:	getfield_a_this 9;		// reference com/makina/security/OpenFIPS201/PIV.cspPIV
					getfield_a 12;		// reference com/makina/security/OpenFIPS201/PIVSecurityProvider.cardPIN
					astore_2;
					goto L5;
				L4:	sspush 27272;
					invokestatic 150;		// javacard/framework/ISOException.throwIt(S)V
				L5:	aload_2;
					invokevirtual 105;		// getTriesRemaining()B
					ifne L7;
				L6:	sspush 27011;
					invokestatic 150;		// javacard/framework/ISOException.throwIt(S)V
				L7:	aload_2;
					invokevirtual 108;		// isValidated()Z
					ifne L9;
				L8:	sspush 25536;
					aload_2;
					invokevirtual 105;		// getTriesRemaining()B
					sor;
					invokestatic 150;		// javacard/framework/ISOException.throwIt(S)V
				L9:	return;
		}

		.method public verifyResetStatus(B)V 7 {
			.stack 2;
			.locals 1;

				L0:	aconst_null;
					astore_2;
				L1:	sload_1;
					slookupswitch L4 2 -128 L3 0 L2;
				L2:	sspush 27272;
					invokestatic 150;		// javacard/framework/ISOException.throwIt(S)V
					getfield_a_this 9;		// reference com/makina/security/OpenFIPS201/PIV.cspPIV
					getfield_a 15;		// reference com/makina/security/OpenFIPS201/PIVSecurityProvider.globalPIN
					astore_2;
					goto L5;
				L3:	getfield_a_this 9;		// reference com/makina/security/OpenFIPS201/PIV.cspPIV
					getfield_a 12;		// reference com/makina/security/OpenFIPS201/PIVSecurityProvider.cardPIN
					astore_2;
					goto L5;
				L4:	sspush 27272;
					invokestatic 150;		// javacard/framework/ISOException.throwIt(S)V
				L5:	aload_2;
					invokevirtual 109;		// reset()V
					getfield_a_this 9;		// reference com/makina/security/OpenFIPS201/PIV.cspPIV
					sconst_0;
					invokevirtual 107;		// setPINAlways(Z)V
					return;
		}

		.method public changeReferenceData(B[BSS)V 8 {
			.stack 5;
			.locals 2;

				L0:	aconst_null;
					astore 5;
				L1:	sconst_0;
					sstore 6;
				L2:	sload_1;
					slookupswitch L12 3 -128 L6 -127 L9 0 L3;
				L3:	sspush 27272;
					invokestatic 150;		// javacard/framework/ISOException.throwIt(S)V
					sspush 27272;
					invokestatic 150;		// javacard/framework/ISOException.throwIt(S)V
					getfield_a_this 9;		// reference com/makina/security/OpenFIPS201/PIV.cspPIV
					invokevirtual 103;		// getIsContactless()Z
					ifeq L5;
				L4:	sspush 27010;
					invokestatic 150;		// javacard/framework/ISOException.throwIt(S)V
				L5:	getfield_a_this 9;		// reference com/makina/security/OpenFIPS201/PIV.cspPIV
					getfield_a 15;		// reference com/makina/security/OpenFIPS201/PIVSecurityProvider.globalPIN
					astore 5;
					sconst_1;
					sstore 6;
					goto L13;
				L6:	getfield_a_this 9;		// reference com/makina/security/OpenFIPS201/PIV.cspPIV
					invokevirtual 103;		// getIsContactless()Z
					ifeq L8;
				L7:	sspush 27010;
					invokestatic 150;		// javacard/framework/ISOException.throwIt(S)V
				L8:	getfield_a_this 9;		// reference com/makina/security/OpenFIPS201/PIV.cspPIV
					getfield_a 12;		// reference com/makina/security/OpenFIPS201/PIVSecurityProvider.cardPIN
					astore 5;
					sconst_1;
					sstore 6;
					goto L13;
				L9:	getfield_a_this 9;		// reference com/makina/security/OpenFIPS201/PIV.cspPIV
					invokevirtual 103;		// getIsContactless()Z
					ifeq L11;
				L10:	sspush 27010;
					invokestatic 150;		// javacard/framework/ISOException.throwIt(S)V
				L11:	getfield_a_this 9;		// reference com/makina/security/OpenFIPS201/PIV.cspPIV
					getfield_a 13;		// reference com/makina/security/OpenFIPS201/PIVSecurityProvider.cardPUK
					astore 5;
					sconst_1;
					sstore 6;
					goto L13;
				L12:	sspush 27272;
					invokestatic 150;		// javacard/framework/ISOException.throwIt(S)V
				L13:	aload 5;
					invokevirtual 105;		// getTriesRemaining()B
					ifne L15;
				L14:	sspush 27011;
					invokestatic 150;		// javacard/framework/ISOException.throwIt(S)V
				L15:	aload 5;
					invokevirtual 105;		// getTriesRemaining()B
					sload 6;
					if_scmpgt L17;
				L16:	sspush 27011;
					invokestatic 150;		// javacard/framework/ISOException.throwIt(S)V
				L17:	aload_0;
					sload_1;
					aload_2;
					sload_3;
					bspush 8;
					invokespecial 104;		// com/makina/security/OpenFIPS201/PIV.verifyPinFormat(B[BSS)Z
					ifne L19;
				L18:	sspush 27264;
					invokestatic 150;		// javacard/framework/ISOException.throwIt(S)V
				L19:	aload 5;
					aload_2;
					sload_3;
					bspush 8;
					invokevirtual 106;		// check([BSB)Z
					ifne L21;
				L20:	sspush 25536;
					aload 5;
					invokevirtual 105;		// getTriesRemaining()B
					sor;
					invokestatic 150;		// javacard/framework/ISOException.throwIt(S)V
				L21:	sinc 3 8;
					aload_0;
					sload_1;
					aload_2;
					sload_3;
					bspush 8;
					invokespecial 104;		// com/makina/security/OpenFIPS201/PIV.verifyPinFormat(B[BSS)Z
					ifne L23;
				L22:	sspush 27264;
					invokestatic 150;		// javacard/framework/ISOException.throwIt(S)V
				L23:	aload 5;
					aload_2;
					sload_3;
					bspush 8;
					invokevirtual 86;		// update([BSB)V
					aload 5;
					aload_2;
					sload_3;
					bspush 8;
					invokevirtual 106;		// check([BSB)Z
					pop;
					getfield_a_this 9;		// reference com/makina/security/OpenFIPS201/PIV.cspPIV
					sconst_1;
					invokevirtual 107;		// setPINAlways(Z)V
					return;
		}

		.method public resetRetryCounter(B[BSS)V 9 {
			.stack 5;
			.locals 0;

				L0:	getfield_a_this 9;		// reference com/makina/security/OpenFIPS201/PIV.cspPIV
					invokevirtual 103;		// getIsContactless()Z
					ifeq L2;
				L1:	sspush 27010;
					invokestatic 150;		// javacard/framework/ISOException.throwIt(S)V
				L2:	getfield_a_this 9;		// reference com/makina/security/OpenFIPS201/PIV.cspPIV
					invokevirtual 103;		// getIsContactless()Z
					ifeq L4;
				L3:	sspush 27010;
					invokestatic 150;		// javacard/framework/ISOException.throwIt(S)V
				L4:	sload_1;
					bspush -128;
					if_scmpeq L6;
				L5:	sspush 27272;
					invokestatic 150;		// javacard/framework/ISOException.throwIt(S)V
				L6:	getfield_a_this 9;		// reference com/makina/security/OpenFIPS201/PIV.cspPIV
					getfield_a 13;		// reference com/makina/security/OpenFIPS201/PIVSecurityProvider.cardPUK
					invokevirtual 105;		// getTriesRemaining()B
					ifne L8;
				L7:	sspush 27011;
					invokestatic 150;		// javacard/framework/ISOException.throwIt(S)V
				L8:	aload_0;
					sload_1;
					aload_2;
					sload_3;
					bspush 8;
					sadd;
					bspush 8;
					invokespecial 104;		// com/makina/security/OpenFIPS201/PIV.verifyPinFormat(B[BSS)Z
					ifne L10;
				L9:	sspush 27264;
					invokestatic 150;		// javacard/framework/ISOException.throwIt(S)V
				L10:	getfield_a_this 9;		// reference com/makina/security/OpenFIPS201/PIV.cspPIV
					getfield_a 13;		// reference com/makina/security/OpenFIPS201/PIVSecurityProvider.cardPUK
					aload_2;
					sload_3;
					bspush 8;
					invokevirtual 106;		// check([BSB)Z
					ifne L14;
				L11:	getfield_a_this 9;		// reference com/makina/security/OpenFIPS201/PIV.cspPIV
					getfield_a 12;		// reference com/makina/security/OpenFIPS201/PIVSecurityProvider.cardPIN
					invokevirtual 109;		// reset()V
					getfield_a_this 9;		// reference com/makina/security/OpenFIPS201/PIV.cspPIV
					getfield_a 13;		// reference com/makina/security/OpenFIPS201/PIVSecurityProvider.cardPUK
					invokevirtual 105;		// getTriesRemaining()B
					ifne L13;
				L12:	sspush 27011;
					invokestatic 150;		// javacard/framework/ISOException.throwIt(S)V
					goto L14;
				L13:	sspush 25536;
					getfield_a_this 9;		// reference com/makina/security/OpenFIPS201/PIV.cspPIV
					getfield_a 13;		// reference com/makina/security/OpenFIPS201/PIVSecurityProvider.cardPUK
					invokevirtual 105;		// getTriesRemaining()B
					sor;
					invokestatic 150;		// javacard/framework/ISOException.throwIt(S)V
				L14:	getfield_a_this 9;		// reference com/makina/security/OpenFIPS201/PIV.cspPIV
					getfield_a 12;		// reference com/makina/security/OpenFIPS201/PIVSecurityProvider.cardPIN
					aload_2;
					sload_3;
					bspush 8;
					sadd;
					bspush 8;
					invokevirtual 86;		// update([BSB)V
					return;
		}

		.method public updateSecurityStatus(ZZ)V 10 {
			.stack 2;
			.locals 0;

				L0:	getfield_a_this 9;		// reference com/makina/security/OpenFIPS201/PIV.cspPIV
					sload_1;
					invokevirtual 110;		// setIsContactless(Z)V
					getfield_a_this 9;		// reference com/makina/security/OpenFIPS201/PIV.cspPIV
					sload_2;
					invokevirtual 111;		// setIsSecureChannel(Z)V
					return;
		}

		.method public resetPinAlways()V 11 {
			.stack 2;
			.locals 0;

				L0:	getfield_a_this 9;		// reference com/makina/security/OpenFIPS201/PIV.cspPIV
					sconst_0;
					invokevirtual 107;		// setPINAlways(Z)V
					return;
		}

		.method private authenticateReset()V {
			.stack 4;
			.locals 0;

				L0:	getfield_a_this 7;		// reference com/makina/security/OpenFIPS201/PIV.authenticationContext
					sconst_0;
					sconst_0;
					bastore;
					getfield_a_this 7;		// reference com/makina/security/OpenFIPS201/PIV.authenticationContext
					sconst_1;
					sconst_0;
					bastore;
					getfield_a_this 7;		// reference com/makina/security/OpenFIPS201/PIV.authenticationContext
					sconst_2;
					sconst_0;
					bastore;
					getfield_a_this 7;		// reference com/makina/security/OpenFIPS201/PIV.authenticationContext
					sconst_3;
					bspush 16;
					sconst_0;
					invokestatic 85;		// javacard/framework/Util.arrayFillNonAtomic([BSSB)S
					pop;
					return;
		}

		.method public generalAuthenticate([BSS)S 12 {
			.stack 8;
			.locals 11;

				L0:	bspush 124;
					sstore 4;
				L1:	bspush -128;
					sstore 5;
				L2:	bspush -127;
					sstore 6;
				L3:	bspush -126;
					sstore 7;
				L4:	getfield_a_this 8;		// reference com/makina/security/OpenFIPS201/PIV.chainBuffer
					aload_1;
					sload_2;
					sload_3;
					getfield_a_this 6;		// reference com/makina/security/OpenFIPS201/PIV.scratch
					sconst_0;
					invokevirtual 112;		// processIncomingAPDU([BSS[BS)S
					sstore_3;
					sload_3;
					ifne L6;
				L5:	sload_3;
					sreturn;
				L6:	getfield_a_this 10;		// reference com/makina/security/OpenFIPS201/PIV.tlvReader
					getfield_a_this 6;		// reference com/makina/security/OpenFIPS201/PIV.scratch
					sconst_0;
					sload_3;
					invokevirtual 113;		// init([BSS)V
					getfield_a_this 9;		// reference com/makina/security/OpenFIPS201/PIV.cspPIV
					aload_1;
					sconst_3;
					baload;
					aload_1;
					sconst_2;
					baload;
					invokevirtual 114;		// selectKey(BB)Lcom/makina/security/OpenFIPS201/PIVKeyObject;
					astore 8;
				L7:	aload 8;
					ifnonnull L9;
				L8:	getfield_a_this 9;		// reference com/makina/security/OpenFIPS201/PIV.cspPIV
					sconst_0;
					invokevirtual 107;		// setPINAlways(Z)V
					getfield_a_this 9;		// reference com/makina/security/OpenFIPS201/PIV.cspPIV
					getfield_a_this 6;		// reference com/makina/security/OpenFIPS201/PIV.scratch
					sconst_0;
					sspush 284;
					invokevirtual 87;		// zeroise([BSS)V
					sspush 27270;
					invokestatic 150;		// javacard/framework/ISOException.throwIt(S)V
				L9:	getfield_a_this 9;		// reference com/makina/security/OpenFIPS201/PIV.cspPIV
					aload 8;
					invokevirtual 92;		// checkAccessModeObject(Lcom/makina/security/OpenFIPS201/PIVObject;)Z
					ifne L11;
				L10:	getfield_a_this 9;		// reference com/makina/security/OpenFIPS201/PIV.cspPIV
					getfield_a_this 6;		// reference com/makina/security/OpenFIPS201/PIV.scratch
					sconst_0;
					sspush 284;
					invokevirtual 87;		// zeroise([BSS)V
					sspush 27010;
					invokestatic 150;		// javacard/framework/ISOException.throwIt(S)V
				L11:	aload 8;
					invokevirtual 115;		// isInitialised()Z
					ifne L13;
				L12:	getfield_a_this 9;		// reference com/makina/security/OpenFIPS201/PIV.cspPIV
					getfield_a_this 6;		// reference com/makina/security/OpenFIPS201/PIV.scratch
					sconst_0;
					sspush 284;
					invokevirtual 87;		// zeroise([BSS)V
					sspush 27270;
					invokestatic 150;		// javacard/framework/ISOException.throwIt(S)V
				L13:	getfield_a_this 10;		// reference com/makina/security/OpenFIPS201/PIV.tlvReader
					bspush 124;
					invokevirtual 116;		// find(B)Z
					ifne L15;
				L14:	getfield_a_this 9;		// reference com/makina/security/OpenFIPS201/PIV.cspPIV
					getfield_a_this 6;		// reference com/makina/security/OpenFIPS201/PIV.scratch
					sconst_0;
					sspush 284;
					invokevirtual 87;		// zeroise([BSS)V
					sspush 27012;
					invokestatic 150;		// javacard/framework/ISOException.throwIt(S)V
				L15:	getfield_a_this 10;		// reference com/makina/security/OpenFIPS201/PIV.tlvReader
					invokevirtual 117;		// moveInto()Z
					pop;
					sconst_0;
					sstore 9;
				L16:	sconst_0;
					sstore 10;
				L17:	sconst_0;
					sstore 11;
				L18:	sconst_0;
					sstore 12;
				L19:	sconst_0;
					sstore 13;
				L20:	sconst_0;
					sstore 14;
				L21:	getfield_a_this 10;		// reference com/makina/security/OpenFIPS201/PIV.tlvReader
					invokevirtual 118;		// getOffset()S
					sstore_2;
				L22:	getfield_a_this 10;		// reference com/makina/security/OpenFIPS201/PIV.tlvReader
					bspush -127;
					invokevirtual 119;		// match(B)Z
					ifeq L24;
				L23:	getfield_a_this 10;		// reference com/makina/security/OpenFIPS201/PIV.tlvReader
					invokevirtual 118;		// getOffset()S
					sstore 9;
					getfield_a_this 10;		// reference com/makina/security/OpenFIPS201/PIV.tlvReader
					invokevirtual 120;		// isNull()Z
					sstore 12;
					goto L28;
				L24:	getfield_a_this 10;		// reference com/makina/security/OpenFIPS201/PIV.tlvReader
					bspush -126;
					invokevirtual 119;		// match(B)Z
					ifeq L26;
				L25:	getfield_a_this 10;		// reference com/makina/security/OpenFIPS201/PIV.tlvReader
					invokevirtual 118;		// getOffset()S
					sstore 11;
					getfield_a_this 10;		// reference com/makina/security/OpenFIPS201/PIV.tlvReader
					invokevirtual 120;		// isNull()Z
					sstore 14;
					goto L28;
				L26:	getfield_a_this 10;		// reference com/makina/security/OpenFIPS201/PIV.tlvReader
					bspush -128;
					invokevirtual 119;		// match(B)Z
					ifeq L28;
				L27:	getfield_a_this 10;		// reference com/makina/security/OpenFIPS201/PIV.tlvReader
					invokevirtual 118;		// getOffset()S
					sstore 10;
					getfield_a_this 10;		// reference com/makina/security/OpenFIPS201/PIV.tlvReader
					invokevirtual 120;		// isNull()Z
					sstore 13;
				L28:	getfield_a_this 10;		// reference com/makina/security/OpenFIPS201/PIV.tlvReader
					invokevirtual 121;		// moveNext()Z
					ifne L22;
				L29:	getfield_a_this 10;		// reference com/makina/security/OpenFIPS201/PIV.tlvReader
					sload_2;
					invokevirtual 122;		// setOffset(S)V
					aload 8;
					invokevirtual 123;		// getBlockLength()S
					sstore_3;
					sload 9;
					ifeq_w L38;
				L30:	sload 12;
					ifne_w L38;
				L31:	sload 11;
					ifeq_w L38;
				L32:	sload 14;
					ifeq_w L38;
				L33:	aload_0;
					invokespecial 124;		// com/makina/security/OpenFIPS201/PIV.authenticateReset()V
					aload 8;
					sconst_4;
					invokevirtual 125;		// hasRole(B)Z
					ifne L35;
				L34:	getfield_a_this 9;		// reference com/makina/security/OpenFIPS201/PIV.cspPIV
					getfield_a_this 6;		// reference com/makina/security/OpenFIPS201/PIV.scratch
					sconst_0;
					sspush 284;
					invokevirtual 87;		// zeroise([BSS)V
					sspush 27010;
					invokestatic 150;		// javacard/framework/ISOException.throwIt(S)V
				L35:	getfield_a_this 10;		// reference com/makina/security/OpenFIPS201/PIV.tlvReader
					sload 9;
					invokevirtual 122;		// setOffset(S)V
					getfield_a_this 10;		// reference com/makina/security/OpenFIPS201/PIV.tlvReader
					invokevirtual 126;		// getLength()S
					sload_3;
					if_scmpeq L37;
				L36:	getfield_a_this 9;		// reference com/makina/security/OpenFIPS201/PIV.cspPIV
					getfield_a_this 6;		// reference com/makina/security/OpenFIPS201/PIV.scratch
					sconst_0;
					sspush 284;
					invokevirtual 87;		// zeroise([BSS)V
					sspush 27264;
					invokestatic 150;		// javacard/framework/ISOException.throwIt(S)V
				L37:	getfield_a_this 9;		// reference com/makina/security/OpenFIPS201/PIV.cspPIV
					aload 8;
					getfield_a_this 6;		// reference com/makina/security/OpenFIPS201/PIV.scratch
					getfield_a_this 10;		// reference com/makina/security/OpenFIPS201/PIV.tlvReader
					invokevirtual 127;		// getDataOffset()S
					sload_3;
					aload_1;
					sconst_0;
					invokevirtual 128;		// encrypt(Lcom/makina/security/OpenFIPS201/PIVKeyObject;[BSS[BS)S
					sstore_3;
					getfield_a_this 9;		// reference com/makina/security/OpenFIPS201/PIV.cspPIV
					getfield_a_this 6;		// reference com/makina/security/OpenFIPS201/PIV.scratch
					sconst_0;
					sspush 284;
					invokevirtual 87;		// zeroise([BSS)V
					getfield_a_this 11;		// reference com/makina/security/OpenFIPS201/PIV.tlvWriter
					getfield_a_this 6;		// reference com/makina/security/OpenFIPS201/PIV.scratch
					sconst_0;
					sload_3;
					bspush 124;
					invokevirtual 129;		// init([BSSS)V
					getfield_a_this 11;		// reference com/makina/security/OpenFIPS201/PIV.tlvWriter
					bspush -126;
					invokevirtual 130;		// writeTag(B)S
					pop;
					getfield_a_this 11;		// reference com/makina/security/OpenFIPS201/PIV.tlvWriter
					sload_3;
					invokevirtual 131;		// writeLength(S)S
					pop;
					aload_1;
					sconst_0;
					getfield_a_this 6;		// reference com/makina/security/OpenFIPS201/PIV.scratch
					getfield_a_this 11;		// reference com/makina/security/OpenFIPS201/PIV.tlvWriter
					invokevirtual 132;		// getOffset()S
					sload_3;
					invokestatic 156;		// javacard/framework/Util.arrayCopyNonAtomic([BS[BSS)S
					sstore_2;
					getfield_a_this 11;		// reference com/makina/security/OpenFIPS201/PIV.tlvWriter
					sload_2;
					invokevirtual 133;		// setOffset(S)V
					getfield_a_this 11;		// reference com/makina/security/OpenFIPS201/PIV.tlvWriter
					invokevirtual 134;		// finish()S
					sstore_3;
					getfield_a_this 8;		// reference com/makina/security/OpenFIPS201/PIV.chainBuffer
					getfield_a_this 6;		// reference com/makina/security/OpenFIPS201/PIV.scratch
					sconst_0;
					sload_3;
					sconst_1;
					invokevirtual 96;		// setOutgoing([BSSZ)V
					sload_3;
					sreturn;
				L38:	sload 9;
					ifeq_w L43;
				L39:	sload 12;
					ifeq_w L43;
				L40:	aload_0;
					invokespecial 124;		// com/makina/security/OpenFIPS201/PIV.authenticateReset()V
					aload 8;
					invokevirtual 135;		// resetSecurityStatus()V
					aload 8;
					sconst_2;
					invokevirtual 125;		// hasRole(B)Z
					ifne L42;
				L41:	aload_0;
					invokespecial 124;		// com/makina/security/OpenFIPS201/PIV.authenticateReset()V
					getfield_a_this 9;		// reference com/makina/security/OpenFIPS201/PIV.cspPIV
					getfield_a_this 6;		// reference com/makina/security/OpenFIPS201/PIV.scratch
					sconst_0;
					sspush 284;
					invokevirtual 87;		// zeroise([BSS)V
					sspush 27010;
					invokestatic 150;		// javacard/framework/ISOException.throwIt(S)V
				L42:	getfield_a_this 11;		// reference com/makina/security/OpenFIPS201/PIV.tlvWriter
					getfield_a_this 6;		// reference com/makina/security/OpenFIPS201/PIV.scratch
					sconst_0;
					sload_3;
					bspush 124;
					invokevirtual 129;		// init([BSSS)V
					getfield_a_this 11;		// reference com/makina/security/OpenFIPS201/PIV.tlvWriter
					bspush -127;
					invokevirtual 130;		// writeTag(B)S
					pop;
					getfield_a_this 11;		// reference com/makina/security/OpenFIPS201/PIV.tlvWriter
					sload_3;
					invokevirtual 131;		// writeLength(S)S
					pop;
					getfield_a_this 11;		// reference com/makina/security/OpenFIPS201/PIV.tlvWriter
					invokevirtual 132;		// getOffset()S
					sstore_2;
					getfield_a_this 9;		// reference com/makina/security/OpenFIPS201/PIV.cspPIV
					getfield_a_this 6;		// reference com/makina/security/OpenFIPS201/PIV.scratch
					sload_2;
					sload_3;
					invokevirtual 84;		// generateRandom([BSS)V
					sload_2;
					getfield_a_this 9;		// reference com/makina/security/OpenFIPS201/PIV.cspPIV
					aload 8;
					getfield_a_this 6;		// reference com/makina/security/OpenFIPS201/PIV.scratch
					sload_2;
					sload_3;
					getfield_a_this 7;		// reference com/makina/security/OpenFIPS201/PIV.authenticationContext
					sconst_3;
					invokevirtual 128;		// encrypt(Lcom/makina/security/OpenFIPS201/PIVKeyObject;[BSS[BS)S
					sadd;
					sstore_2;
					getfield_a_this 11;		// reference com/makina/security/OpenFIPS201/PIV.tlvWriter
					sload_2;
					invokevirtual 133;		// setOffset(S)V
					getfield_a_this 11;		// reference com/makina/security/OpenFIPS201/PIV.tlvWriter
					invokevirtual 134;		// finish()S
					sstore_3;
					getfield_a_this 7;		// reference com/makina/security/OpenFIPS201/PIV.authenticationContext
					sconst_0;
					sconst_1;
					bastore;
					getfield_a_this 7;		// reference com/makina/security/OpenFIPS201/PIV.authenticationContext
					sconst_1;
					aload 8;
					invokevirtual 136;		// getId()B
					bastore;
					getfield_a_this 7;		// reference com/makina/security/OpenFIPS201/PIV.authenticationContext
					sconst_2;
					aload 8;
					invokevirtual 137;		// getMechanism()B
					bastore;
					getfield_a_this 8;		// reference com/makina/security/OpenFIPS201/PIV.chainBuffer
					getfield_a_this 6;		// reference com/makina/security/OpenFIPS201/PIV.scratch
					sconst_0;
					sload_3;
					sconst_1;
					invokevirtual 96;		// setOutgoing([BSSZ)V
					sload_3;
					sreturn;
				L43:	sload 11;
					ifeq_w L55;
				L44:	sload 14;
					ifne_w L55;
				L45:	getfield_a_this 7;		// reference com/makina/security/OpenFIPS201/PIV.authenticationContext
					sconst_0;
					baload;
					sconst_1;
					if_scmpeq L47;
				L46:	aload_0;
					invokespecial 124;		// com/makina/security/OpenFIPS201/PIV.authenticateReset()V
					getfield_a_this 9;		// reference com/makina/security/OpenFIPS201/PIV.cspPIV
					getfield_a_this 6;		// reference com/makina/security/OpenFIPS201/PIV.scratch
					sconst_0;
					sspush 284;
					invokevirtual 87;		// zeroise([BSS)V
					sspush 27010;
					invokestatic 150;		// javacard/framework/ISOException.throwIt(S)V
				L47:	getfield_a_this 7;		// reference com/makina/security/OpenFIPS201/PIV.authenticationContext
					sconst_1;
					baload;
					aload 8;
					invokevirtual 136;		// getId()B
					if_scmpne L49;
				L48:	getfield_a_this 7;		// reference com/makina/security/OpenFIPS201/PIV.authenticationContext
					sconst_2;
					baload;
					aload 8;
					invokevirtual 137;		// getMechanism()B
					if_scmpeq L50;
				L49:	aload_0;
					invokespecial 124;		// com/makina/security/OpenFIPS201/PIV.authenticateReset()V
					getfield_a_this 9;		// reference com/makina/security/OpenFIPS201/PIV.cspPIV
					getfield_a_this 6;		// reference com/makina/security/OpenFIPS201/PIV.scratch
					sconst_0;
					sspush 284;
					invokevirtual 87;		// zeroise([BSS)V
					sspush 27010;
					invokestatic 150;		// javacard/framework/ISOException.throwIt(S)V
				L50:	getfield_a_this 10;		// reference com/makina/security/OpenFIPS201/PIV.tlvReader
					sload 11;
					invokevirtual 122;		// setOffset(S)V
					sload_3;
					getfield_a_this 10;		// reference com/makina/security/OpenFIPS201/PIV.tlvReader
					invokevirtual 126;		// getLength()S
					if_scmpeq L52;
				L51:	aload_0;
					invokespecial 124;		// com/makina/security/OpenFIPS201/PIV.authenticateReset()V
					getfield_a_this 9;		// reference com/makina/security/OpenFIPS201/PIV.cspPIV
					getfield_a_this 6;		// reference com/makina/security/OpenFIPS201/PIV.scratch
					sconst_0;
					sspush 284;
					invokevirtual 87;		// zeroise([BSS)V
					sspush 27010;
					invokestatic 150;		// javacard/framework/ISOException.throwIt(S)V
				L52:	getfield_a_this 6;		// reference com/makina/security/OpenFIPS201/PIV.scratch
					getfield_a_this 10;		// reference com/makina/security/OpenFIPS201/PIV.tlvReader
					invokevirtual 127;		// getDataOffset()S
					getfield_a_this 7;		// reference com/makina/security/OpenFIPS201/PIV.authenticationContext
					sconst_3;
					sload_3;
					invokestatic 138;		// javacard/framework/Util.arrayCompare([BS[BSS)B
					ifeq L54;
				L53:	aload_0;
					invokespecial 124;		// com/makina/security/OpenFIPS201/PIV.authenticateReset()V
					getfield_a_this 9;		// reference com/makina/security/OpenFIPS201/PIV.cspPIV
					getfield_a_this 6;		// reference com/makina/security/OpenFIPS201/PIV.scratch
					sconst_0;
					sspush 284;
					invokevirtual 87;		// zeroise([BSS)V
					sspush 27010;
					invokestatic 150;		// javacard/framework/ISOException.throwIt(S)V
				L54:	aload 8;
					invokevirtual 139;		// setSecurityStatus()V
					aload_0;
					invokespecial 124;		// com/makina/security/OpenFIPS201/PIV.authenticateReset()V
					getfield_a_this 9;		// reference com/makina/security/OpenFIPS201/PIV.cspPIV
					getfield_a_this 6;		// reference com/makina/security/OpenFIPS201/PIV.scratch
					sconst_0;
					sspush 284;
					invokevirtual 87;		// zeroise([BSS)V
					sconst_0;
					sreturn;
				L55:	sload 10;
					ifeq_w L60;
				L56:	sload 13;
					ifeq_w L60;
				L57:	aload_0;
					invokespecial 124;		// com/makina/security/OpenFIPS201/PIV.authenticateReset()V
					aload 8;
					invokevirtual 135;		// resetSecurityStatus()V
					aload 8;
					sconst_2;
					invokevirtual 125;		// hasRole(B)Z
					ifne L59;
				L58:	aload_0;
					invokespecial 124;		// com/makina/security/OpenFIPS201/PIV.authenticateReset()V
					getfield_a_this 9;		// reference com/makina/security/OpenFIPS201/PIV.cspPIV
					getfield_a_this 6;		// reference com/makina/security/OpenFIPS201/PIV.scratch
					sconst_0;
					sspush 284;
					invokevirtual 87;		// zeroise([BSS)V
					sspush 27010;
					invokestatic 150;		// javacard/framework/ISOException.throwIt(S)V
				L59:	getfield_a_this 9;		// reference com/makina/security/OpenFIPS201/PIV.cspPIV
					getfield_a_this 7;		// reference com/makina/security/OpenFIPS201/PIV.authenticationContext
					sconst_3;
					sload_3;
					invokevirtual 84;		// generateRandom([BSS)V
					getfield_a_this 11;		// reference com/makina/security/OpenFIPS201/PIV.tlvWriter
					getfield_a_this 6;		// reference com/makina/security/OpenFIPS201/PIV.scratch
					sconst_0;
					sload_3;
					bspush 124;
					invokevirtual 129;		// init([BSSS)V
					getfield_a_this 11;		// reference com/makina/security/OpenFIPS201/PIV.tlvWriter
					bspush -128;
					invokevirtual 130;		// writeTag(B)S
					pop;
					getfield_a_this 11;		// reference com/makina/security/OpenFIPS201/PIV.tlvWriter
					sload_3;
					invokevirtual 131;		// writeLength(S)S
					pop;
					getfield_a_this 11;		// reference com/makina/security/OpenFIPS201/PIV.tlvWriter
					invokevirtual 132;		// getOffset()S
					sstore_2;
					sload_2;
					getfield_a_this 9;		// reference com/makina/security/OpenFIPS201/PIV.cspPIV
					aload 8;
					getfield_a_this 7;		// reference com/makina/security/OpenFIPS201/PIV.authenticationContext
					sconst_3;
					sload_3;
					getfield_a_this 6;		// reference com/makina/security/OpenFIPS201/PIV.scratch
					sload_2;
					invokevirtual 128;		// encrypt(Lcom/makina/security/OpenFIPS201/PIVKeyObject;[BSS[BS)S
					sadd;
					sstore_2;
					getfield_a_this 11;		// reference com/makina/security/OpenFIPS201/PIV.tlvWriter
					sload_2;
					invokevirtual 133;		// setOffset(S)V
					getfield_a_this 11;		// reference com/makina/security/OpenFIPS201/PIV.tlvWriter
					invokevirtual 134;		// finish()S
					sstore_3;
					getfield_a_this 7;		// reference com/makina/security/OpenFIPS201/PIV.authenticationContext
					sconst_0;
					sconst_2;
					bastore;
					getfield_a_this 7;		// reference com/makina/security/OpenFIPS201/PIV.authenticationContext
					sconst_1;
					aload 8;
					invokevirtual 136;		// getId()B
					bastore;
					getfield_a_this 7;		// reference com/makina/security/OpenFIPS201/PIV.authenticationContext
					sconst_2;
					aload 8;
					invokevirtual 137;		// getMechanism()B
					bastore;
					getfield_a_this 8;		// reference com/makina/security/OpenFIPS201/PIV.chainBuffer
					getfield_a_this 6;		// reference com/makina/security/OpenFIPS201/PIV.scratch
					sconst_0;
					sload_3;
					sconst_1;
					invokevirtual 96;		// setOutgoing([BSSZ)V
					sload_3;
					sreturn;
				L60:	sload 10;
					ifeq_w L76;
				L61:	sload 13;
					ifne_w L76;
				L62:	sload 9;
					ifeq_w L76;
				L63:	sload 12;
					ifne_w L76;
				L64:	getfield_a_this 7;		// reference com/makina/security/OpenFIPS201/PIV.authenticationContext
					sconst_0;
					baload;
					sconst_2;
					if_scmpeq L66;
				L65:	aload_0;
					invokespecial 124;		// com/makina/security/OpenFIPS201/PIV.authenticateReset()V
					getfield_a_this 9;		// reference com/makina/security/OpenFIPS201/PIV.cspPIV
					getfield_a_this 6;		// reference com/makina/security/OpenFIPS201/PIV.scratch
					sconst_0;
					sspush 284;
					invokevirtual 87;		// zeroise([BSS)V
					sspush 27010;
					invokestatic 150;		// javacard/framework/ISOException.throwIt(S)V
				L66:	getfield_a_this 7;		// reference com/makina/security/OpenFIPS201/PIV.authenticationContext
					sconst_1;
					baload;
					aload 8;
					invokevirtual 136;		// getId()B
					if_scmpne L68;
				L67:	getfield_a_this 7;		// reference com/makina/security/OpenFIPS201/PIV.authenticationContext
					sconst_2;
					baload;
					aload 8;
					invokevirtual 137;		// getMechanism()B
					if_scmpeq L69;
				L68:	aload_0;
					invokespecial 124;		// com/makina/security/OpenFIPS201/PIV.authenticateReset()V
					getfield_a_this 9;		// reference com/makina/security/OpenFIPS201/PIV.cspPIV
					getfield_a_this 6;		// reference com/makina/security/OpenFIPS201/PIV.scratch
					sconst_0;
					sspush 284;
					invokevirtual 87;		// zeroise([BSS)V
					sspush 27010;
					invokestatic 150;		// javacard/framework/ISOException.throwIt(S)V
				L69:	getfield_a_this 10;		// reference com/makina/security/OpenFIPS201/PIV.tlvReader
					sload 10;
					invokevirtual 122;		// setOffset(S)V
					sload_3;
					getfield_a_this 10;		// reference com/makina/security/OpenFIPS201/PIV.tlvReader
					invokevirtual 126;		// getLength()S
					if_scmpeq L71;
				L70:	aload_0;
					invokespecial 124;		// com/makina/security/OpenFIPS201/PIV.authenticateReset()V
					getfield_a_this 9;		// reference com/makina/security/OpenFIPS201/PIV.cspPIV
					getfield_a_this 6;		// reference com/makina/security/OpenFIPS201/PIV.scratch
					sconst_0;
					sspush 284;
					invokevirtual 87;		// zeroise([BSS)V
					sspush 27010;
					invokestatic 150;		// javacard/framework/ISOException.throwIt(S)V
				L71:	getfield_a_this 6;		// reference com/makina/security/OpenFIPS201/PIV.scratch
					getfield_a_this 10;		// reference com/makina/security/OpenFIPS201/PIV.tlvReader
					invokevirtual 127;		// getDataOffset()S
					getfield_a_this 7;		// reference com/makina/security/OpenFIPS201/PIV.authenticationContext
					sconst_3;
					sload_3;
					invokestatic 138;		// javacard/framework/Util.arrayCompare([BS[BSS)B
					ifeq L73;
				L72:	aload_0;
					invokespecial 124;		// com/makina/security/OpenFIPS201/PIV.authenticateReset()V
					getfield_a_this 9;		// reference com/makina/security/OpenFIPS201/PIV.cspPIV
					getfield_a_this 6;		// reference com/makina/security/OpenFIPS201/PIV.scratch
					sconst_0;
					sspush 284;
					invokevirtual 87;		// zeroise([BSS)V
					sspush 27010;
					invokestatic 150;		// javacard/framework/ISOException.throwIt(S)V
				L73:	getfield_a_this 10;		// reference com/makina/security/OpenFIPS201/PIV.tlvReader
					sload 9;
					invokevirtual 122;		// setOffset(S)V
					getfield_a_this 10;		// reference com/makina/security/OpenFIPS201/PIV.tlvReader
					invokevirtual 126;		// getLength()S
					sstore_3;
					aload 8;
					invokevirtual 123;		// getBlockLength()S
					sload_3;
					if_scmpeq L75;
				L74:	aload_0;
					invokespecial 124;		// com/makina/security/OpenFIPS201/PIV.authenticateReset()V
					getfield_a_this 9;		// reference com/makina/security/OpenFIPS201/PIV.cspPIV
					getfield_a_this 6;		// reference com/makina/security/OpenFIPS201/PIV.scratch
					sconst_0;
					sspush 284;
					invokevirtual 87;		// zeroise([BSS)V
					sspush 26368;
					invokestatic 150;		// javacard/framework/ISOException.throwIt(S)V
				L75:	getfield_a_this 9;		// reference com/makina/security/OpenFIPS201/PIV.cspPIV
					aload 8;
					getfield_a_this 6;		// reference com/makina/security/OpenFIPS201/PIV.scratch
					getfield_a_this 10;		// reference com/makina/security/OpenFIPS201/PIV.tlvReader
					invokevirtual 127;		// getDataOffset()S
					sload_3;
					aload_1;
					sconst_0;
					invokevirtual 128;		// encrypt(Lcom/makina/security/OpenFIPS201/PIVKeyObject;[BSS[BS)S
					sstore_3;
					getfield_a_this 11;		// reference com/makina/security/OpenFIPS201/PIV.tlvWriter
					getfield_a_this 6;		// reference com/makina/security/OpenFIPS201/PIV.scratch
					sconst_0;
					sload_3;
					bspush 124;
					invokevirtual 129;		// init([BSSS)V
					getfield_a_this 11;		// reference com/makina/security/OpenFIPS201/PIV.tlvWriter
					bspush -126;
					invokevirtual 130;		// writeTag(B)S
					pop;
					getfield_a_this 11;		// reference com/makina/security/OpenFIPS201/PIV.tlvWriter
					sload_3;
					invokevirtual 131;		// writeLength(S)S
					pop;
					aload_1;
					sconst_0;
					getfield_a_this 6;		// reference com/makina/security/OpenFIPS201/PIV.scratch
					getfield_a_this 11;		// reference com/makina/security/OpenFIPS201/PIV.tlvWriter
					invokevirtual 132;		// getOffset()S
					sload_3;
					invokestatic 156;		// javacard/framework/Util.arrayCopyNonAtomic([BS[BSS)S
					sstore_2;
					getfield_a_this 11;		// reference com/makina/security/OpenFIPS201/PIV.tlvWriter
					sload_2;
					invokevirtual 133;		// setOffset(S)V
					getfield_a_this 11;		// reference com/makina/security/OpenFIPS201/PIV.tlvWriter
					invokevirtual 134;		// finish()S
					sstore_3;
					aload 8;
					invokevirtual 139;		// setSecurityStatus()V
					aload_0;
					invokespecial 124;		// com/makina/security/OpenFIPS201/PIV.authenticateReset()V
					getfield_a_this 8;		// reference com/makina/security/OpenFIPS201/PIV.chainBuffer
					getfield_a_this 6;		// reference com/makina/security/OpenFIPS201/PIV.scratch
					sconst_0;
					sload_3;
					sconst_1;
					invokevirtual 96;		// setOutgoing([BSSZ)V
					sload_3;
					sreturn;
				L76:	aload_0;
					invokespecial 124;		// com/makina/security/OpenFIPS201/PIV.authenticateReset()V
					getfield_a_this 9;		// reference com/makina/security/OpenFIPS201/PIV.cspPIV
					getfield_a_this 6;		// reference com/makina/security/OpenFIPS201/PIV.scratch
					sconst_0;
					sspush 284;
					invokevirtual 87;		// zeroise([BSS)V
					sspush 27264;
					invokestatic 150;		// javacard/framework/ISOException.throwIt(S)V
					sconst_0;
					sreturn;
		}

		.method public generateAsymmetricKeyPair([BSS)S 13 {
			.stack 5;
			.locals 8;

				L0:	bspush -84;
					sstore 4;
				L1:	bspush -128;
					sstore 5;
				L2:	bspush -127;
					sstore 6;
				L3:	sspush 32585;
					sstore 7;
				L4:	bspush -127;
					sstore 8;
				L5:	bspush -126;
					sstore 9;
				L6:	getfield_a_this 9;		// reference com/makina/security/OpenFIPS201/PIV.cspPIV
					sconst_0;
					invokevirtual 97;		// checkAccessModeAdmin(Z)Z
					ifne L8;
				L7:	sspush 27010;
					invokestatic 150;		// javacard/framework/ISOException.throwIt(S)V
				L8:	aload_1;
					sload_2;
					sinc 2 1;
					baload;
					bspush -84;
					if_scmpeq L10;
				L9:	sspush 27264;
					invokestatic 150;		// javacard/framework/ISOException.throwIt(S)V
				L10:	sinc 2 1;
					aload_1;
					sload_2;
					sinc 2 1;
					baload;
					bspush -128;
					if_scmpeq L12;
				L11:	sspush 27264;
					invokestatic 150;		// javacard/framework/ISOException.throwIt(S)V
				L12:	aload_1;
					sload_2;
					sinc 2 1;
					baload;
					sconst_1;
					if_scmpeq L14;
				L13:	sspush 27264;
					invokestatic 150;		// javacard/framework/ISOException.throwIt(S)V
				L14:	getfield_a_this 9;		// reference com/makina/security/OpenFIPS201/PIV.cspPIV
					aload_1;
					sconst_3;
					baload;
					aload_1;
					sload_2;
					baload;
					invokevirtual 114;		// selectKey(BB)Lcom/makina/security/OpenFIPS201/PIVKeyObject;
					astore 10;
				L15:	aload 10;
					ifnonnull L19;
				L16:	getfield_a_this 9;		// reference com/makina/security/OpenFIPS201/PIV.cspPIV
					aload_1;
					sconst_3;
					baload;
					invokevirtual 140;		// keyExists(B)Z
					ifne L18;
				L17:	sspush 27270;
					invokestatic 150;		// javacard/framework/ISOException.throwIt(S)V
					goto L19;
				L18:	sspush 27264;
					invokestatic 150;		// javacard/framework/ISOException.throwIt(S)V
				L19:	aload 10;
					instanceof 0 141;		// T_CLASSORINTERFACE com/makina/security/OpenFIPS201/PIVKeyObjectPKI
					ifne L21;
				L20:	sspush 27270;
					invokestatic 150;		// javacard/framework/ISOException.throwIt(S)V
				L21:	aload 10;
					checkcast 0 141;		// T_CLASSORINTERFACE com/makina/security/OpenFIPS201/PIVKeyObjectPKI
					astore 11;
				L22:	aload 11;
					invokevirtual 142;		// generate()V
					getfield_a_this 11;		// reference com/makina/security/OpenFIPS201/PIV.tlvWriter
					getfield_a_this 6;		// reference com/makina/security/OpenFIPS201/PIV.scratch
					sconst_0;
					aload 10;
					invokevirtual 143;		// getKeyLength()S
					sspush 32585;
					invokevirtual 129;		// init([BSSS)V
					getfield_a_this 11;		// reference com/makina/security/OpenFIPS201/PIV.tlvWriter
					bspush -127;
					invokevirtual 130;		// writeTag(B)S
					pop;
					getfield_a_this 11;		// reference com/makina/security/OpenFIPS201/PIV.tlvWriter
					aload 11;
					invokevirtual 144;		// getKeyLength()S
					invokevirtual 131;		// writeLength(S)S
					pop;
					getfield_a_this 11;		// reference com/makina/security/OpenFIPS201/PIV.tlvWriter
					invokevirtual 132;		// getOffset()S
					sstore_2;
					sload_2;
					aload 11;
					getfield_a_this 6;		// reference com/makina/security/OpenFIPS201/PIV.scratch
					sload_2;
					invokevirtual 145;		// getModulus([BS)S
					sadd;
					sstore_2;
					getfield_a_this 11;		// reference com/makina/security/OpenFIPS201/PIV.tlvWriter
					sload_2;
					invokevirtual 133;		// setOffset(S)V
					getfield_a_this 11;		// reference com/makina/security/OpenFIPS201/PIV.tlvWriter
					bspush -126;
					invokevirtual 130;		// writeTag(B)S
					pop;
					getfield_a_this 11;		// reference com/makina/security/OpenFIPS201/PIV.tlvWriter
					sconst_3;
					invokevirtual 131;		// writeLength(S)S
					pop;
					getfield_a_this 11;		// reference com/makina/security/OpenFIPS201/PIV.tlvWriter
					invokevirtual 132;		// getOffset()S
					sstore_2;
					sload_2;
					aload 11;
					getfield_a_this 6;		// reference com/makina/security/OpenFIPS201/PIV.scratch
					sload_2;
					invokevirtual 146;		// getPublicExponent([BS)S
					sadd;
					sstore_2;
					getfield_a_this 11;		// reference com/makina/security/OpenFIPS201/PIV.tlvWriter
					sload_2;
					invokevirtual 133;		// setOffset(S)V
					getfield_a_this 11;		// reference com/makina/security/OpenFIPS201/PIV.tlvWriter
					invokevirtual 134;		// finish()S
					sstore_3;
					getfield_a_this 8;		// reference com/makina/security/OpenFIPS201/PIV.chainBuffer
					getfield_a_this 6;		// reference com/makina/security/OpenFIPS201/PIV.scratch
					sconst_0;
					sload_3;
					sconst_1;
					invokevirtual 96;		// setOutgoing([BSSZ)V
					sload_3;
					sreturn;
		}

		.method private verifyPinFormat(B[BSS)Z {
			.stack 2;
			.locals 3;

				L0:	sconst_m1;
					sstore 5;
				L1:	sload 4;
					bspush 8;
					if_scmpeq L3;
				L2:	sconst_0;
					sreturn;
				L3:	sload_1;
					bspush -127;
					if_scmpne L5;
				L4:	sconst_1;
					sreturn;
				L5:	sconst_0;
					sstore 6;
				L6:	sload 6;
					bspush 8;
					if_scmpge L25;
				L7:	sconst_0;
					sstore 7;
				L8:	sload 6;
					bspush 6;
					if_scmpge L12;
				L9:	aload_2;
					sload_3;
					baload;
					bspush 48;
					if_scmplt L11;
				L10:	aload_2;
					sload_3;
					baload;
					bspush 57;
					if_scmple L16;
				L11:	sconst_0;
					sreturn;
				L12:	aload_2;
					sload_3;
					baload;
					bspush 48;
					if_scmplt L14;
				L13:	aload_2;
					sload_3;
					baload;
					bspush 57;
					if_scmple L16;
				L14:	aload_2;
					sload_3;
					baload;
					sconst_m1;
					if_scmpeq L16;
				L15:	sconst_0;
					sreturn;
				L16:	sload 7;
					ifeq L19;
				L17:	aload_2;
					sload_3;
					baload;
					sconst_m1;
					if_scmpeq L19;
				L18:	sconst_0;
					sreturn;
				L19:	aload_2;
					sload_3;
					baload;
					sconst_m1;
					if_scmpne L23;
				L20:	sload 6;
					bspush 6;
					if_scmpge L22;
				L21:	sconst_0;
					sreturn;
				L22:	sconst_1;
					sstore 7;
				L23:	sinc 3 1;
				L24:	sinc 6 1;
					goto L6;
				L25:	sconst_1;
					sreturn;
		}

		.method public putDataAdmin([BSS)V 14 {
			.stack 6;
			.locals 16;

				L0:	bspush 48;
					sstore 4;
				L1:	bspush -118;
					sstore 5;
				L2:	bspush -117;
					sstore 6;
				L3:	bspush -116;
					sstore 7;
				L4:	bspush -115;
					sstore 8;
				L5:	bspush -114;
					sstore 9;
				L6:	bspush -113;
					sstore 10;
				L7:	sconst_1;
					sstore 11;
				L8:	sconst_2;
					sstore 12;
				L9:	getfield_a_this 9;		// reference com/makina/security/OpenFIPS201/PIV.cspPIV
					sconst_1;
					invokevirtual 97;		// checkAccessModeAdmin(Z)Z
					ifne L11;
				L10:	sspush 27010;
					invokestatic 150;		// javacard/framework/ISOException.throwIt(S)V
				L11:	getfield_a_this 8;		// reference com/makina/security/OpenFIPS201/PIV.chainBuffer
					aload_1;
					sload_2;
					sload_3;
					getfield_a_this 6;		// reference com/makina/security/OpenFIPS201/PIV.scratch
					sconst_0;
					invokevirtual 112;		// processIncomingAPDU([BSS[BS)S
					sstore_3;
					sload_3;
					ifne L13;
				L12:	return;
				L13:	getfield_a_this 10;		// reference com/makina/security/OpenFIPS201/PIV.tlvReader
					getfield_a_this 6;		// reference com/makina/security/OpenFIPS201/PIV.scratch
					sconst_0;
					sload_3;
					invokevirtual 113;		// init([BSS)V
					getfield_a_this 10;		// reference com/makina/security/OpenFIPS201/PIV.tlvReader
					bspush 48;
					invokevirtual 119;		// match(B)Z
					ifne L15;
				L14:	sspush 27264;
					invokestatic 150;		// javacard/framework/ISOException.throwIt(S)V
				L15:	getfield_a_this 10;		// reference com/makina/security/OpenFIPS201/PIV.tlvReader
					invokevirtual 126;		// getLength()S
					sload_3;
					if_scmple L17;
				L16:	sspush 27264;
					invokestatic 150;		// javacard/framework/ISOException.throwIt(S)V
				L17:	getfield_a_this 10;		// reference com/makina/security/OpenFIPS201/PIV.tlvReader
					invokevirtual 117;		// moveInto()Z
					pop;
					getfield_a_this 10;		// reference com/makina/security/OpenFIPS201/PIV.tlvReader
					bspush -118;
					invokevirtual 119;		// match(B)Z
					ifne L19;
				L18:	sspush 27264;
					invokestatic 150;		// javacard/framework/ISOException.throwIt(S)V
				L19:	getfield_a_this 10;		// reference com/makina/security/OpenFIPS201/PIV.tlvReader
					invokevirtual 147;		// toByte()B
					sstore 13;
				L20:	sload 13;
					sconst_1;
					if_scmpeq L23;
				L21:	sload 13;
					sconst_2;
					if_scmpeq L23;
				L22:	sspush 27264;
					invokestatic 150;		// javacard/framework/ISOException.throwIt(S)V
				L23:	getfield_a_this 10;		// reference com/makina/security/OpenFIPS201/PIV.tlvReader
					invokevirtual 121;		// moveNext()Z
					pop;
					getfield_a_this 10;		// reference com/makina/security/OpenFIPS201/PIV.tlvReader
					bspush -117;
					invokevirtual 119;		// match(B)Z
					ifne L25;
				L24:	sspush 27264;
					invokestatic 150;		// javacard/framework/ISOException.throwIt(S)V
				L25:	getfield_a_this 10;		// reference com/makina/security/OpenFIPS201/PIV.tlvReader
					invokevirtual 126;		// getLength()S
					sconst_1;
					if_scmpeq L27;
				L26:	sspush 26368;
					invokestatic 150;		// javacard/framework/ISOException.throwIt(S)V
				L27:	getfield_a_this 10;		// reference com/makina/security/OpenFIPS201/PIV.tlvReader
					invokevirtual 147;		// toByte()B
					sstore 14;
				L28:	getfield_a_this 10;		// reference com/makina/security/OpenFIPS201/PIV.tlvReader
					invokevirtual 121;		// moveNext()Z
					pop;
					getfield_a_this 10;		// reference com/makina/security/OpenFIPS201/PIV.tlvReader
					bspush -116;
					invokevirtual 119;		// match(B)Z
					ifne L30;
				L29:	sspush 27264;
					invokestatic 150;		// javacard/framework/ISOException.throwIt(S)V
				L30:	getfield_a_this 10;		// reference com/makina/security/OpenFIPS201/PIV.tlvReader
					invokevirtual 126;		// getLength()S
					sconst_1;
					if_scmpeq L32;
				L31:	sspush 26368;
					invokestatic 150;		// javacard/framework/ISOException.throwIt(S)V
				L32:	getfield_a_this 10;		// reference com/makina/security/OpenFIPS201/PIV.tlvReader
					invokevirtual 147;		// toByte()B
					sstore 15;
				L33:	getfield_a_this 10;		// reference com/makina/security/OpenFIPS201/PIV.tlvReader
					invokevirtual 121;		// moveNext()Z
					pop;
					getfield_a_this 10;		// reference com/makina/security/OpenFIPS201/PIV.tlvReader
					bspush -115;
					invokevirtual 119;		// match(B)Z
					ifne L35;
				L34:	sspush 27264;
					invokestatic 150;		// javacard/framework/ISOException.throwIt(S)V
				L35:	getfield_a_this 10;		// reference com/makina/security/OpenFIPS201/PIV.tlvReader
					invokevirtual 126;		// getLength()S
					sconst_1;
					if_scmpeq L37;
				L36:	sspush 26368;
					invokestatic 150;		// javacard/framework/ISOException.throwIt(S)V
				L37:	getfield_a_this 10;		// reference com/makina/security/OpenFIPS201/PIV.tlvReader
					invokevirtual 147;		// toByte()B
					sstore 16;
				L38:	sconst_0;
					sstore 17;
				L39:	sconst_0;
					sstore 18;
				L40:	getfield_a_this 10;		// reference com/makina/security/OpenFIPS201/PIV.tlvReader
					invokevirtual 121;		// moveNext()Z
					pop;
					sconst_2;
					sload 13;
					if_scmpne L51;
				L41:	getfield_a_this 10;		// reference com/makina/security/OpenFIPS201/PIV.tlvReader
					bspush -114;
					invokevirtual 119;		// match(B)Z
					ifne L43;
				L42:	sspush 27264;
					invokestatic 150;		// javacard/framework/ISOException.throwIt(S)V
				L43:	getfield_a_this 10;		// reference com/makina/security/OpenFIPS201/PIV.tlvReader
					invokevirtual 126;		// getLength()S
					sconst_1;
					if_scmpeq L45;
				L44:	sspush 26368;
					invokestatic 150;		// javacard/framework/ISOException.throwIt(S)V
				L45:	getfield_a_this 10;		// reference com/makina/security/OpenFIPS201/PIV.tlvReader
					invokevirtual 147;		// toByte()B
					sstore 17;
					getfield_a_this 10;		// reference com/makina/security/OpenFIPS201/PIV.tlvReader
					invokevirtual 121;		// moveNext()Z
					pop;
					getfield_a_this 10;		// reference com/makina/security/OpenFIPS201/PIV.tlvReader
					bspush -113;
					invokevirtual 119;		// match(B)Z
					ifne L47;
				L46:	sspush 27264;
					invokestatic 150;		// javacard/framework/ISOException.throwIt(S)V
				L47:	getfield_a_this 10;		// reference com/makina/security/OpenFIPS201/PIV.tlvReader
					invokevirtual 126;		// getLength()S
					sconst_1;
					if_scmpeq L49;
				L48:	sspush 26368;
					invokestatic 150;		// javacard/framework/ISOException.throwIt(S)V
				L49:	getfield_a_this 10;		// reference com/makina/security/OpenFIPS201/PIV.tlvReader
					invokevirtual 147;		// toByte()B
					sstore 18;
					getfield_a_this 9;		// reference com/makina/security/OpenFIPS201/PIV.cspPIV
					sload 14;
					sload 17;
					invokevirtual 114;		// selectKey(BB)Lcom/makina/security/OpenFIPS201/PIVKeyObject;
					ifnull L56;
				L50:	sspush 27268;
					invokestatic 150;		// javacard/framework/ISOException.throwIt(S)V
					goto L56;
				L51:	getfield_a_this 16;		// reference com/makina/security/OpenFIPS201/PIV.firstDataObject
					astore 19;
				L52:	aload 19;
					ifnull L56;
				L53:	aload 19;
					invokevirtual 149;		// getId()B
					sload 14;
					if_scmpne L55;
				L54:	sspush 27268;
					invokestatic 150;		// javacard/framework/ISOException.throwIt(S)V
				L55:	aload 19;
					getfield_a 17;		// reference com/makina/security/OpenFIPS201/PIVObject.nextObject
					astore 19;
					goto L52;
				L56:	sload 13;
					sconst_1;
					if_scmpne L58;
				L57:	aload_0;
					sload 14;
					sload 15;
					sload 16;
					invokespecial 151;		// com/makina/security/OpenFIPS201/PIV.createDataObject(BBB)V
					goto L59;
				L58:	getfield_a_this 9;		// reference com/makina/security/OpenFIPS201/PIV.cspPIV
					sload 14;
					sload 15;
					sload 16;
					sload 17;
					sload 18;
					invokevirtual 152;		// createKey(BBBBB)V
				L59:	return;
		}

		.method public changeReferenceDataAdmin(B[BSS)V 15 {
			.stack 6;
			.locals 6;

				L0:	bspush 48;
					sstore 5;
				L1:	bspush -128;
					sstore 6;
				L2:	bspush -127;
					sstore 7;
				L3:	bspush -126;
					sstore 8;
				L4:	bspush -125;
					sstore 9;
				L5:	getfield_a_this 9;		// reference com/makina/security/OpenFIPS201/PIV.cspPIV
					sconst_1;
					invokevirtual 97;		// checkAccessModeAdmin(Z)Z
					ifne L7;
				L6:	sspush 27010;
					invokestatic 150;		// javacard/framework/ISOException.throwIt(S)V
				L7:	getfield_a_this 8;		// reference com/makina/security/OpenFIPS201/PIV.chainBuffer
					aload_2;
					sload_3;
					sload 4;
					getfield_a_this 6;		// reference com/makina/security/OpenFIPS201/PIV.scratch
					sconst_0;
					invokevirtual 112;		// processIncomingAPDU([BSS[BS)S
					sstore 4;
					sload 4;
					ifne L9;
				L8:	return;
				L9:	aload_2;
					sconst_3;
					baload;
					bspush -128;
					if_scmpne L13;
				L10:	aload_0;
					bspush -128;
					getfield_a_this 6;		// reference com/makina/security/OpenFIPS201/PIV.scratch
					sconst_0;
					sload 4;
					invokespecial 104;		// com/makina/security/OpenFIPS201/PIV.verifyPinFormat(B[BSS)Z
					ifne L12;
				L11:	sspush 27264;
					invokestatic 150;		// javacard/framework/ISOException.throwIt(S)V
				L12:	getfield_a_this 9;		// reference com/makina/security/OpenFIPS201/PIV.cspPIV
					getfield_a 12;		// reference com/makina/security/OpenFIPS201/PIVSecurityProvider.cardPIN
					getfield_a_this 6;		// reference com/makina/security/OpenFIPS201/PIV.scratch
					sconst_0;
					sload 4;
					s2b;
					invokevirtual 86;		// update([BSB)V
					return;
				L13:	aload_2;
					sconst_3;
					baload;
					bspush -127;
					if_scmpne L17;
				L14:	aload_0;
					bspush -127;
					getfield_a_this 6;		// reference com/makina/security/OpenFIPS201/PIV.scratch
					sconst_0;
					sload 4;
					invokespecial 104;		// com/makina/security/OpenFIPS201/PIV.verifyPinFormat(B[BSS)Z
					ifne L16;
				L15:	sspush 27264;
					invokestatic 150;		// javacard/framework/ISOException.throwIt(S)V
				L16:	getfield_a_this 9;		// reference com/makina/security/OpenFIPS201/PIV.cspPIV
					getfield_a 13;		// reference com/makina/security/OpenFIPS201/PIVSecurityProvider.cardPUK
					getfield_a_this 6;		// reference com/makina/security/OpenFIPS201/PIV.scratch
					sconst_0;
					sload 4;
					s2b;
					invokevirtual 86;		// update([BSB)V
					return;
				L17:	getfield_a_this 9;		// reference com/makina/security/OpenFIPS201/PIV.cspPIV
					aload_2;
					sconst_3;
					baload;
					aload_2;
					sconst_2;
					baload;
					invokevirtual 114;		// selectKey(BB)Lcom/makina/security/OpenFIPS201/PIVKeyObject;
					astore 10;
				L18:	aload 10;
					ifnonnull L20;
				L19:	sspush 27272;
					invokestatic 150;		// javacard/framework/ISOException.throwIt(S)V
				L20:	aload 10;
					bspush 8;
					invokevirtual 125;		// hasRole(B)Z
					ifeq L22;
				L21:	sspush 27010;
					invokestatic 150;		// javacard/framework/ISOException.throwIt(S)V
				L22:	getfield_a_this 10;		// reference com/makina/security/OpenFIPS201/PIV.tlvReader
					getfield_a_this 6;		// reference com/makina/security/OpenFIPS201/PIV.scratch
					sconst_0;
					sload 4;
					invokevirtual 113;		// init([BSS)V
					getfield_a_this 10;		// reference com/makina/security/OpenFIPS201/PIV.tlvReader
					bspush 48;
					invokevirtual 119;		// match(B)Z
					ifne L24;
				L23:	sspush 27264;
					invokestatic 150;		// javacard/framework/ISOException.throwIt(S)V
				L24:	getfield_a_this 10;		// reference com/makina/security/OpenFIPS201/PIV.tlvReader
					invokevirtual 126;		// getLength()S
					sload 4;
					if_scmple L26;
				L25:	sspush 27264;
					invokestatic 150;		// javacard/framework/ISOException.throwIt(S)V
				L26:	getfield_a_this 10;		// reference com/makina/security/OpenFIPS201/PIV.tlvReader
					invokevirtual 117;		// moveInto()Z
					pop;
					aload 10;
					getfield_a_this 10;		// reference com/makina/security/OpenFIPS201/PIV.tlvReader
					invokevirtual 153;		// getTag()B
					getfield_a_this 6;		// reference com/makina/security/OpenFIPS201/PIV.scratch
					getfield_a_this 10;		// reference com/makina/security/OpenFIPS201/PIV.tlvReader
					invokevirtual 127;		// getDataOffset()S
					getfield_a_this 10;		// reference com/makina/security/OpenFIPS201/PIV.tlvReader
					invokevirtual 126;		// getLength()S
					invokevirtual 154;		// updateElement(B[BSS)V
					return;
		}

		.method private findDataObject(B)Lcom/makina/security/OpenFIPS201/PIVDataObject; {
			.stack 2;
			.locals 1;

				L0:	getfield_a_this 16;		// reference com/makina/security/OpenFIPS201/PIV.firstDataObject
					astore_2;
				L1:	aload_2;
					ifnull L5;
				L2:	aload_2;
					sload_1;
					invokevirtual 155;		// match(B)Z
					ifeq L4;
				L3:	aload_2;
					areturn;
				L4:	aload_2;
					getfield_a 18;		// reference com/makina/security/OpenFIPS201/PIVObject.nextObject
					checkcast 0 157;		// T_CLASSORINTERFACE com/makina/security/OpenFIPS201/PIVDataObject
					astore_2;
					goto L1;
				L5:	aconst_null;
					areturn;
		}

		.method private createDataObject(BBB)V {
			.stack 5;
			.locals 3;

				L0:	bspush 126;
					sstore 4;
				L1:	new 157;		// com/makina/security/OpenFIPS201/PIVDataObject
					dup;
					sload_1;
					sload_2;
					sload_3;
					invokespecial 158;		// com/makina/security/OpenFIPS201/PIVDataObject.<init>(BBB)V
					astore 5;
				L2:	getfield_a_this 16;		// reference com/makina/security/OpenFIPS201/PIV.firstDataObject
					ifnonnull L4;
				L3:	aload_0;
					aload 5;
					putfield_a 16;		// reference com/makina/security/OpenFIPS201/PIV.firstDataObject
					return;
				L4:	getfield_a_this 16;		// reference com/makina/security/OpenFIPS201/PIV.firstDataObject
					astore 6;
				L5:	aload 6;
					getfield_a 17;		// reference com/makina/security/OpenFIPS201/PIVObject.nextObject
					ifnull L7;
				L6:	aload 6;
					getfield_a 17;		// reference com/makina/security/OpenFIPS201/PIVObject.nextObject
					astore 6;
					goto L5;
				L7:	aload 6;
					aload 5;
					putfield_a 17;		// reference com/makina/security/OpenFIPS201/PIVObject.nextObject
					bspush 126;
					sload_1;
					if_scmpne L9;
				L8:	aload 5;
					getstatic_a 159;		// reference com/makina/security/OpenFIPS201/Config.DEFAULT_DISCOVERY
					arraylength;
					invokevirtual 100;		// allocate(S)V
					getstatic_a 159;		// reference com/makina/security/OpenFIPS201/Config.DEFAULT_DISCOVERY
					sconst_0;
					aload 5;
					getfield_a 14;		// reference com/makina/security/OpenFIPS201/PIVDataObject.content
					sconst_0;
					getstatic_a 159;		// reference com/makina/security/OpenFIPS201/Config.DEFAULT_DISCOVERY
					arraylength;
					invokestatic 156;		// javacard/framework/Util.arrayCopyNonAtomic([BS[BSS)S
					pop;
				L9:	return;
		}

	}

	.class public abstract PIVObject 5 extends 2.0 {		// extends java/lang/Object

		.fields {
			protected byte[] header 0;		// [B
			public PIVObject nextObject 1;		// Lcom/makina/security/OpenFIPS201/PIVObject;
			public static final byte ACCESS_MODE_NEVER = 0;		// B
			public static final byte ACCESS_MODE_PIN = 1;		// B
			public static final byte ACCESS_MODE_PIN_ALWAYS = 2;		// B
			public static final byte ACCESS_MODE_ALWAYS = 127;		// B
			protected static final short HEADER_ID = 0;		// S
			protected static final short HEADER_MODE_CONTACT = 1;		// S
			protected static final short HEADER_MODE_CONTACTLESS = 2;		// S
			protected static final short LENGTH_HEADER = 8;		// S
		}

		.publicMethodTable 1 {
			equals(Ljava/lang/Object;)Z;
			match(B)Z;
			getId()B;
			getModeContact()B;
			getModeContactless()B;
			isInitialised()Z;
			clear()V;
		}

		.packageMethodTable 0 {
		}

		.method protected <init>(BBB)V 0 {
			.stack 3;
			.locals 0;

				L0:	aload_0;
					invokespecial 202;		// java/lang/Object.<init>()V
					aload_0;
					bspush 8;
					newarray 11;
					putfield_a 19;		// reference com/makina/security/OpenFIPS201/PIVObject.header
					getfield_a_this 19;		// reference com/makina/security/OpenFIPS201/PIVObject.header
					sconst_0;
					sload_1;
					bastore;
					getfield_a_this 19;		// reference com/makina/security/OpenFIPS201/PIVObject.header
					sconst_1;
					sload_2;
					bastore;
					getfield_a_this 19;		// reference com/makina/security/OpenFIPS201/PIVObject.header
					sconst_2;
					sload_3;
					bastore;
					return;
		}

		.method public match(B)Z 1 {
			.stack 2;
			.locals 0;

				L0:	getfield_a_this 19;		// reference com/makina/security/OpenFIPS201/PIVObject.header
					sconst_0;
					baload;
					sload_1;
					if_scmpne L2;
				L1:	sconst_1;
					goto L3;
				L2:	sconst_0;
				L3:	sreturn;
		}

		.method public getId()B 2 {
			.stack 2;
			.locals 0;

				L0:	getfield_a_this 19;		// reference com/makina/security/OpenFIPS201/PIVObject.header
					sconst_0;
					baload;
					sreturn;
		}

		.method public getModeContact()B 3 {
			.stack 2;
			.locals 0;

				L0:	getfield_a_this 19;		// reference com/makina/security/OpenFIPS201/PIVObject.header
					sconst_1;
					baload;
					sreturn;
		}

		.method public getModeContactless()B 4 {
			.stack 2;
			.locals 0;

				L0:	getfield_a_this 19;		// reference com/makina/security/OpenFIPS201/PIVObject.header
					sconst_2;
					baload;
					sreturn;
		}

		.method public abstract isInitialised()Z 5 {
		}

		.method public abstract clear()V 6 {
		}

	}

	.class public abstract PIVKeyObject 6 extends PIVObject {

		.fields {
			private boolean[] securityFlags 0;		// [Z
			protected static final short HEADER_MECHANISM = 3;		// S
			protected static final short HEADER_ROLE = 4;		// S
			public static final byte ROLE_NONE = 0;		// B
			public static final byte ROLE_ADMIN = 1;		// B
			public static final byte ROLE_AUTH_EXTERNAL = 2;		// B
			public static final byte ROLE_AUTH_INTERNAL = 4;		// B
			public static final byte ROLE_GENERATE_ONLY = 8;		// B
			private static final short FLAGS_AUTHENTICATED = 0;		// S
			private static final short LENGTH_FLAGS = 1;		// S
		}

		.publicMethodTable 7 {
			equals(Ljava/lang/Object;)Z;
			match(B)Z;
			getId()B;
			getModeContact()B;
			getModeContactless()B;
			isInitialised()Z;
			clear()V;
			getMechanism()B;
			getRoles()B;
			hasRole(B)Z;
			resetSecurityStatus()V;
			setSecurityStatus()V;
			getSecurityStatus()Z;
			match(BB)Z;
			getBlockLength()S;
			getKeyLength()S;
			isAsymmetric()Z;
			updateElement(B[BSS)V;
			encrypt(Ljavacardx/crypto/Cipher;[BSS[BS)S;
			decrypt(Ljavacardx/crypto/Cipher;[BSS[BS)S;
		}

		.packageMethodTable 0 {
		}

		.method public final getMechanism()B 7 {
			.stack 2;
			.locals 0;

				L0:	getfield_a_this 19;		// reference com/makina/security/OpenFIPS201/PIVObject.header
					sconst_3;
					baload;
					sreturn;
		}

		.method public final getRoles()B 8 {
			.stack 2;
			.locals 0;

				L0:	getfield_a_this 19;		// reference com/makina/security/OpenFIPS201/PIVObject.header
					sconst_4;
					baload;
					sreturn;
		}

		.method public final hasRole(B)Z 9 {
			.stack 2;
			.locals 0;

				L0:	getfield_a_this 19;		// reference com/makina/security/OpenFIPS201/PIVObject.header
					sconst_4;
					baload;
					sload_1;
					sand;
					sload_1;
					if_scmpne L2;
				L1:	sconst_1;
					goto L3;
				L2:	sconst_0;
				L3:	sreturn;
		}

		.method public final resetSecurityStatus()V 10 {
			.stack 3;
			.locals 0;

				L0:	getfield_a_this 20;		// reference com/makina/security/OpenFIPS201/PIVKeyObject.securityFlags
					sconst_0;
					sconst_0;
					bastore;
					return;
		}

		.method public final setSecurityStatus()V 11 {
			.stack 3;
			.locals 0;

				L0:	getfield_a_this 20;		// reference com/makina/security/OpenFIPS201/PIVKeyObject.securityFlags
					sconst_0;
					sconst_1;
					bastore;
					return;
		}

		.method public final getSecurityStatus()Z 12 {
			.stack 2;
			.locals 0;

				L0:	getfield_a_this 20;		// reference com/makina/security/OpenFIPS201/PIVKeyObject.securityFlags
					sconst_0;
					baload;
					sconst_1;
					if_scmpne L2;
				L1:	sconst_1;
					goto L3;
				L2:	sconst_0;
				L3:	sreturn;
		}

		.method protected <init>(BBBBB)V 0 {
			.stack 4;
			.locals 0;

				L0:	aload_0;
					sload_1;
					sload_2;
					sload_3;
					invokespecial 162;		// com/makina/security/OpenFIPS201/PIVObject.<init>(BBB)V
					getfield_a_this 19;		// reference com/makina/security/OpenFIPS201/PIVObject.header
					sconst_3;
					sload 4;
					bastore;
					getfield_a_this 19;		// reference com/makina/security/OpenFIPS201/PIVObject.header
					sconst_4;
					sload 5;
					bastore;
					aload_0;
					sconst_1;
					sconst_2;
					invokestatic 163;		// javacard/framework/JCSystem.makeTransientBooleanArray(SB)[Z
					putfield_a 20;		// reference com/makina/security/OpenFIPS201/PIVKeyObject.securityFlags
					aload_0;
					invokevirtual 135;		// resetSecurityStatus()V
					return;
		}

		.method public static create(BBBBB)Lcom/makina/security/OpenFIPS201/PIVKeyObject; 1 {
			.stack 7;
			.locals 1;

				L0:	sload_3;
					stableswitch L5 0 12 L1 L5 L5 L1 L5 L5 L3 L3 L1 L5 L1 L5 L1;
				L1:	new 164;		// com/makina/security/OpenFIPS201/PIVKeyObjectSYM
					dup;
					sload_0;
					sload_1;
					sload_2;
					sload_3;
					sload 4;
					invokespecial 165;		// com/makina/security/OpenFIPS201/PIVKeyObjectSYM.<init>(BBBBB)V
					astore 5;
				L2:	aload 5;
					areturn;
				L3:	new 141;		// com/makina/security/OpenFIPS201/PIVKeyObjectPKI
					dup;
					sload_0;
					sload_1;
					sload_2;
					sload_3;
					sload 4;
					invokespecial 166;		// com/makina/security/OpenFIPS201/PIVKeyObjectPKI.<init>(BBBBB)V
					astore 5;
				L4:	aload 5;
					areturn;
				L5:	sspush 27265;
					invokestatic 150;		// javacard/framework/ISOException.throwIt(S)V
					aconst_null;
					areturn;
		}

		.method public match(BB)Z 13 {
			.stack 2;
			.locals 0;

				L0:	getfield_a_this 19;		// reference com/makina/security/OpenFIPS201/PIVObject.header
					sconst_0;
					baload;
					sload_1;
					if_scmpne L3;
				L1:	getfield_a_this 19;		// reference com/makina/security/OpenFIPS201/PIVObject.header
					sconst_3;
					baload;
					sload_2;
					if_scmpne L3;
				L2:	sconst_1;
					goto L4;
				L3:	sconst_0;
				L4:	sreturn;
		}

		.method public getBlockLength()S 14 {
			.stack 2;
			.locals 0;

				L0:	getfield_a_this 19;		// reference com/makina/security/OpenFIPS201/PIVObject.header
					sconst_3;
					baload;
					stableswitch L5 0 12 L1 L5 L5 L1 L5 L5 L3 L4 L2 L5 L2 L5 L2;
				L1:	bspush 8;
					sreturn;
				L2:	bspush 16;
					sreturn;
				L3:	sspush 128;
					sreturn;
				L4:	sspush 256;
					sreturn;
				L5:	sspush 27012;
					invokestatic 150;		// javacard/framework/ISOException.throwIt(S)V
					sconst_0;
					sreturn;
		}

		.method public getKeyLength()S 15 {
			.stack 2;
			.locals 0;

				L0:	getfield_a_this 19;		// reference com/makina/security/OpenFIPS201/PIVObject.header
					sconst_3;
					baload;
					stableswitch L7 0 12 L1 L7 L7 L1 L7 L7 L5 L6 L2 L7 L3 L7 L4;
				L1:	bspush 24;
					sreturn;
				L2:	bspush 16;
					sreturn;
				L3:	bspush 24;
					sreturn;
				L4:	bspush 32;
					sreturn;
				L5:	sspush 128;
					sreturn;
				L6:	sspush 256;
					sreturn;
				L7:	sspush 27012;
					invokestatic 150;		// javacard/framework/ISOException.throwIt(S)V
					sconst_0;
					sreturn;
		}

		.method public isAsymmetric()Z 16 {
			.stack 2;
			.locals 0;

				L0:	getfield_a_this 19;		// reference com/makina/security/OpenFIPS201/PIVObject.header
					sconst_3;
					baload;
					stableswitch L3 0 12 L1 L3 L3 L1 L3 L3 L2 L2 L1 L3 L1 L3 L1;
				L1:	sconst_0;
					sreturn;
				L2:	sconst_1;
					sreturn;
				L3:	sspush 27012;
					invokestatic 150;		// javacard/framework/ISOException.throwIt(S)V
					sconst_0;
					sreturn;
		}

		.method public abstract updateElement(B[BSS)V 17 {
		}

		.method public abstract encrypt(Ljavacardx/crypto/Cipher;[BSS[BS)S 18 {
			.descriptor	Ljavacardx/crypto/Cipher;	3.1;

		}

		.method public abstract decrypt(Ljavacardx/crypto/Cipher;[BSS[BS)S 19 {
			.descriptor	Ljavacardx/crypto/Cipher;	3.1;

		}

	}

	.class public final PIVKeyObjectPKI 7 extends PIVKeyObject {

		.fields {
			private 4.8 privateKey 0;		// Ljavacard/security/RSAPrivateKey;
			private 4.9 publicKey 1;		// Ljavacard/security/RSAPublicKey;
			private 4.16 keyPair 2;		// Ljavacard/security/KeyPair;
			public static final byte ELEMENT_RSA_N = -127;		// B
			public static final byte ELEMENT_RSA_E = -126;		// B
			public static final byte ELEMENT_RSA_D = -125;		// B
			public static final byte ELEMENT_RSA_P = -124;		// B
			public static final byte ELEMENT_RSA_Q = -123;		// B
			public static final byte ELEMENT_RSA_DP = -122;		// B
			public static final byte ELEMENT_RSA_DQ = -121;		// B
			public static final byte ELEMENT_RSA_PQ = -120;		// B
			public static final byte ELEMENT_RSA_CLEAR = -1;		// B
		}

		.publicMethodTable 5 {
			equals(Ljava/lang/Object;)Z;
			match(B)Z;
			getId()B;
			getModeContact()B;
			getModeContactless()B;
			isInitialised()Z;
			clear()V;
			getMechanism()B;
			getRoles()B;
			hasRole(B)Z;
			resetSecurityStatus()V;
			setSecurityStatus()V;
			getSecurityStatus()Z;
			match(BB)Z;
			getBlockLength()S;
			getKeyLength()S;
			isAsymmetric()Z;
			updateElement(B[BSS)V;
			encrypt(Ljavacardx/crypto/Cipher;[BSS[BS)S;
			decrypt(Ljavacardx/crypto/Cipher;[BSS[BS)S;
			setPrivateExponent([BSS)V;
			setPublicExponent([BSS)V;
			setModulus([BSS)V;
			getPublicExponent([BS)S;
			getModulus([BS)S;
			generate()V;
		}

		.packageMethodTable 0 {
		}

		.method public <init>(BBBBB)V 0 {
			.stack 6;
			.locals 0;

				L0:	aload_0;
					sload_1;
					sload_2;
					sload_3;
					sload 4;
					sload 5;
					invokespecial 167;		// com/makina/security/OpenFIPS201/PIVKeyObject.<init>(BBBBB)V
					return;
		}

		.method public updateElement(B[BSS)V 17 {
			.stack 4;
			.locals 0;

				L0:	sload_1;
					slookupswitch L21 4 -127 L1 -126 L7 -125 L12 -1 L17;
				L1:	sload 4;
					aload_0;
					invokevirtual 144;		// getKeyLength()S
					if_scmpeq L3;
				L2:	sspush 26368;
					invokestatic 150;		// javacard/framework/ISOException.throwIt(S)V
				L3:	getfield_a_this 21;		// reference com/makina/security/OpenFIPS201/PIVKeyObjectPKI.publicKey
					ifnull L5;
				L4:	getfield_a_this 22;		// reference com/makina/security/OpenFIPS201/PIVKeyObjectPKI.privateKey
					ifnonnull L6;
				L5:	aload_0;
					invokespecial 170;		// com/makina/security/OpenFIPS201/PIVKeyObjectPKI.allocate()V
				L6:	getfield_a_this 21;		// reference com/makina/security/OpenFIPS201/PIVKeyObjectPKI.publicKey
					aload_2;
					sload_3;
					sload 4;
					invokeinterface 4 171 7;		// javacard/security/RSAPublicKey
					getfield_a_this 22;		// reference com/makina/security/OpenFIPS201/PIVKeyObjectPKI.privateKey
					aload_2;
					sload_3;
					sload 4;
					invokeinterface 4 172 7;		// javacard/security/RSAPrivateKey
					goto L22;
				L7:	sload 4;
					ifne L9;
				L8:	sspush 26368;
					invokestatic 150;		// javacard/framework/ISOException.throwIt(S)V
				L9:	getfield_a_this 21;		// reference com/makina/security/OpenFIPS201/PIVKeyObjectPKI.publicKey
					ifnonnull L11;
				L10:	aload_0;
					invokespecial 170;		// com/makina/security/OpenFIPS201/PIVKeyObjectPKI.allocate()V
				L11:	getfield_a_this 21;		// reference com/makina/security/OpenFIPS201/PIVKeyObjectPKI.publicKey
					aload_2;
					sload_3;
					sload 4;
					invokeinterface 4 171 6;		// javacard/security/RSAPublicKey
					goto L22;
				L12:	sload 4;
					aload_0;
					invokevirtual 144;		// getKeyLength()S
					if_scmpeq L14;
				L13:	sspush 26368;
					invokestatic 150;		// javacard/framework/ISOException.throwIt(S)V
				L14:	getfield_a_this 22;		// reference com/makina/security/OpenFIPS201/PIVKeyObjectPKI.privateKey
					ifnonnull L16;
				L15:	aload_0;
					invokespecial 170;		// com/makina/security/OpenFIPS201/PIVKeyObjectPKI.allocate()V
				L16:	getfield_a_this 22;		// reference com/makina/security/OpenFIPS201/PIVKeyObjectPKI.privateKey
					aload_2;
					sload_3;
					sload 4;
					invokeinterface 4 172 6;		// javacard/security/RSAPrivateKey
					goto L22;
				L17:	getfield_a_this 21;		// reference com/makina/security/OpenFIPS201/PIVKeyObjectPKI.publicKey
					ifnull L19;
				L18:	getfield_a_this 21;		// reference com/makina/security/OpenFIPS201/PIVKeyObjectPKI.publicKey
					invokeinterface 1 171 0;		// javacard/security/RSAPublicKey
				L19:	getfield_a_this 22;		// reference com/makina/security/OpenFIPS201/PIVKeyObjectPKI.privateKey
					ifnull L22;
				L20:	getfield_a_this 22;		// reference com/makina/security/OpenFIPS201/PIVKeyObjectPKI.privateKey
					invokeinterface 1 172 0;		// javacard/security/RSAPrivateKey
					goto L22;
				L21:	sspush 27264;
					invokestatic 150;		// javacard/framework/ISOException.throwIt(S)V
				L22:	return;
		}

		.method public setPrivateExponent([BSS)V 20 {
			.stack 4;
			.locals 0;

				L0:	getfield_a_this 22;		// reference com/makina/security/OpenFIPS201/PIVKeyObjectPKI.privateKey
					ifnonnull L2;
				L1:	aload_0;
					invokespecial 170;		// com/makina/security/OpenFIPS201/PIVKeyObjectPKI.allocate()V
				L2:	getfield_a_this 22;		// reference com/makina/security/OpenFIPS201/PIVKeyObjectPKI.privateKey
					aload_1;
					sload_2;
					sload_3;
					invokeinterface 4 172 6;		// javacard/security/RSAPrivateKey
					return;
		}

		.method public setPublicExponent([BSS)V 21 {
			.stack 4;
			.locals 0;

				L0:	getfield_a_this 21;		// reference com/makina/security/OpenFIPS201/PIVKeyObjectPKI.publicKey
					ifnonnull L2;
				L1:	aload_0;
					invokespecial 170;		// com/makina/security/OpenFIPS201/PIVKeyObjectPKI.allocate()V
				L2:	getfield_a_this 21;		// reference com/makina/security/OpenFIPS201/PIVKeyObjectPKI.publicKey
					aload_1;
					sload_2;
					sload_3;
					invokeinterface 4 171 6;		// javacard/security/RSAPublicKey
					return;
		}

		.method public setModulus([BSS)V 22 {
			.stack 4;
			.locals 0;

				L0:	getfield_a_this 22;		// reference com/makina/security/OpenFIPS201/PIVKeyObjectPKI.privateKey
					ifnull L2;
				L1:	getfield_a_this 21;		// reference com/makina/security/OpenFIPS201/PIVKeyObjectPKI.publicKey
					ifnonnull L3;
				L2:	aload_0;
					invokespecial 170;		// com/makina/security/OpenFIPS201/PIVKeyObjectPKI.allocate()V
				L3:	getfield_a_this 22;		// reference com/makina/security/OpenFIPS201/PIVKeyObjectPKI.privateKey
					aload_1;
					sload_2;
					sload_3;
					invokeinterface 4 172 7;		// javacard/security/RSAPrivateKey
					getfield_a_this 21;		// reference com/makina/security/OpenFIPS201/PIVKeyObjectPKI.publicKey
					aload_1;
					sload_2;
					sload_3;
					invokeinterface 4 171 7;		// javacard/security/RSAPublicKey
					return;
		}

		.method public getPublicExponent([BS)S 23 {
			.stack 3;
			.locals 0;

				L0:	getfield_a_this 21;		// reference com/makina/security/OpenFIPS201/PIVKeyObjectPKI.publicKey
					aload_1;
					sload_2;
					invokeinterface 3 171 4;		// javacard/security/RSAPublicKey
					sreturn;
		}

		.method public getModulus([BS)S 24 {
			.stack 3;
			.locals 0;

				L0:	getfield_a_this 21;		// reference com/makina/security/OpenFIPS201/PIVKeyObjectPKI.publicKey
					aload_1;
					sload_2;
					invokeinterface 3 171 5;		// javacard/security/RSAPublicKey
					sreturn;
		}

		.method private allocate()V {
			.stack 5;
			.locals 0;

				L0:	getfield_a_this 19;		// reference com/makina/security/OpenFIPS201/PIVObject.header
					sconst_3;
					baload;
					slookupswitch L3 2 6 L1 7 L2;
				L1:	aload_0;
					new 173;		// javacard/security/KeyPair
					dup;
					sconst_1;
					sspush 1024;
					invokespecial 174;		// javacard/security/KeyPair.<init>(BS)V
					putfield_a 23;		// reference com/makina/security/OpenFIPS201/PIVKeyObjectPKI.keyPair
					goto L4;
				L2:	aload_0;
					new 173;		// javacard/security/KeyPair
					dup;
					sconst_1;
					sspush 2048;
					invokespecial 174;		// javacard/security/KeyPair.<init>(BS)V
					putfield_a 23;		// reference com/makina/security/OpenFIPS201/PIVKeyObjectPKI.keyPair
					goto L4;
				L3:	sspush 27265;
					invokestatic 150;		// javacard/framework/ISOException.throwIt(S)V
				L4:	aload_0;
					getfield_a_this 23;		// reference com/makina/security/OpenFIPS201/PIVKeyObjectPKI.keyPair
					invokevirtual 176;		// getPrivate()Ljavacard/security/PrivateKey;
					checkcast 0 172;		// T_CLASSORINTERFACE javacard/security/RSAPrivateKey
					putfield_a 22;		// reference com/makina/security/OpenFIPS201/PIVKeyObjectPKI.privateKey
					aload_0;
					getfield_a_this 23;		// reference com/makina/security/OpenFIPS201/PIVKeyObjectPKI.keyPair
					invokevirtual 177;		// getPublic()Ljavacard/security/PublicKey;
					checkcast 0 171;		// T_CLASSORINTERFACE javacard/security/RSAPublicKey
					putfield_a 21;		// reference com/makina/security/OpenFIPS201/PIVKeyObjectPKI.publicKey
					return;
		}

		.method public clear()V 6 {
			.stack 1;
			.locals 0;

				L0:	getfield_a_this 22;		// reference com/makina/security/OpenFIPS201/PIVKeyObjectPKI.privateKey
					ifnull L2;
				L1:	getfield_a_this 22;		// reference com/makina/security/OpenFIPS201/PIVKeyObjectPKI.privateKey
					invokeinterface 1 172 0;		// javacard/security/RSAPrivateKey
				L2:	getfield_a_this 21;		// reference com/makina/security/OpenFIPS201/PIVKeyObjectPKI.publicKey
					ifnull L4;
				L3:	getfield_a_this 21;		// reference com/makina/security/OpenFIPS201/PIVKeyObjectPKI.publicKey
					invokeinterface 1 171 0;		// javacard/security/RSAPublicKey
				L4:	return;
		}

		.method public isInitialised()Z 5 {
			.stack 1;
			.locals 0;

				L0:	getfield_a_this 22;		// reference com/makina/security/OpenFIPS201/PIVKeyObjectPKI.privateKey
					ifnull L5;
				L1:	getfield_a_this 22;		// reference com/makina/security/OpenFIPS201/PIVKeyObjectPKI.privateKey
					invokeinterface 1 172 3;		// javacard/security/RSAPrivateKey
					ifeq L5;
				L2:	getfield_a_this 21;		// reference com/makina/security/OpenFIPS201/PIVKeyObjectPKI.publicKey
					ifnull L5;
				L3:	getfield_a_this 21;		// reference com/makina/security/OpenFIPS201/PIVKeyObjectPKI.publicKey
					invokeinterface 1 171 3;		// javacard/security/RSAPublicKey
					ifeq L5;
				L4:	sconst_1;
					goto L6;
				L5:	sconst_0;
				L6:	sreturn;
		}

		.method public generate()V 25 {
			.stack 1;
			.locals 0;

				L0:	getfield_a_this 22;		// reference com/makina/security/OpenFIPS201/PIVKeyObjectPKI.privateKey
					ifnull L2;
				L1:	getfield_a_this 21;		// reference com/makina/security/OpenFIPS201/PIVKeyObjectPKI.publicKey
					ifnonnull L3;
				L2:	aload_0;
					invokespecial 170;		// com/makina/security/OpenFIPS201/PIVKeyObjectPKI.allocate()V
				L3:	getfield_a_this 23;		// reference com/makina/security/OpenFIPS201/PIVKeyObjectPKI.keyPair
					invokevirtual 178;		// genKeyPair()V
					return;
		}

		.method public encrypt(Ljavacardx/crypto/Cipher;[BSS[BS)S 18 {
			.stack 6;
			.locals 0;

			.descriptor	Ljavacardx/crypto/Cipher;	3.1;

				L0:	aload_1;
					getfield_a_this 22;		// reference com/makina/security/OpenFIPS201/PIVKeyObjectPKI.privateKey
					sconst_2;
					invokevirtual 179;		// init(Ljavacard/security/Key;B)V
					aload_1;
					aload_2;
					sload_3;
					sload 4;
					aload 5;
					sload 6;
					invokevirtual 180;		// doFinal([BSS[BS)S
					sreturn;
		}

		.method public decrypt(Ljavacardx/crypto/Cipher;[BSS[BS)S 19 {
			.stack 6;
			.locals 0;

			.descriptor	Ljavacardx/crypto/Cipher;	3.1;

				L0:	aload_1;
					getfield_a_this 22;		// reference com/makina/security/OpenFIPS201/PIVKeyObjectPKI.privateKey
					sconst_1;
					invokevirtual 179;		// init(Ljavacard/security/Key;B)V
					aload_1;
					aload_2;
					sload_3;
					sload 4;
					aload 5;
					sload 6;
					invokevirtual 180;		// doFinal([BSS[BS)S
					sreturn;
		}

	}

	.class public final PIVKeyObjectSYM 8 extends PIVKeyObject {

		.fields {
			private 4.4 key 0;		// Ljavacard/security/SecretKey;
			public static final byte ELEMENT_KEY = -128;		// B
			public static final byte ELEMENT_KEY_CLEAR = -1;		// B
		}

		.publicMethodTable 5 {
			equals(Ljava/lang/Object;)Z;
			match(B)Z;
			getId()B;
			getModeContact()B;
			getModeContactless()B;
			isInitialised()Z;
			clear()V;
			getMechanism()B;
			getRoles()B;
			hasRole(B)Z;
			resetSecurityStatus()V;
			setSecurityStatus()V;
			getSecurityStatus()Z;
			match(BB)Z;
			getBlockLength()S;
			getKeyLength()S;
			isAsymmetric()Z;
			updateElement(B[BSS)V;
			encrypt(Ljavacardx/crypto/Cipher;[BSS[BS)S;
			decrypt(Ljavacardx/crypto/Cipher;[BSS[BS)S;
		}

		.packageMethodTable 0 {
		}

		.method public <init>(BBBBB)V 0 {
			.stack 6;
			.locals 0;

				L0:	aload_0;
					sload_1;
					sload_2;
					sload_3;
					sload 4;
					sload 5;
					invokespecial 167;		// com/makina/security/OpenFIPS201/PIVKeyObject.<init>(BBBBB)V
					return;
		}

		.method public updateElement(B[BSS)V 17 {
			.stack 3;
			.locals 1;

				L0:	sload 4;
					aload_0;
					invokevirtual 181;		// getKeyLength()S
					if_scmpeq L2;
				L1:	sspush 26368;
					invokestatic 150;		// javacard/framework/ISOException.throwIt(S)V
				L2:	sload_1;
					slookupswitch L18 2 -128 L3 -1 L17;
				L3:	getfield_a_this 24;		// reference com/makina/security/OpenFIPS201/PIVKeyObjectSYM.key
					ifnonnull L5;
				L4:	aload_0;
					invokespecial 183;		// com/makina/security/OpenFIPS201/PIVKeyObjectSYM.allocate()V
				L5:	getfield_a_this 24;		// reference com/makina/security/OpenFIPS201/PIVKeyObjectSYM.key
					invokeinterface 1 184 2;		// javacard/security/SecretKey
					slookupswitch L16 2 3 L6 15 L11;
				L6:	getfield_a_this 24;		// reference com/makina/security/OpenFIPS201/PIVKeyObjectSYM.key
					checkcast 0 185;		// T_CLASSORINTERFACE javacard/security/DESKey
					aload_2;
					sload_3;
					invokeinterface 3 185 5;		// javacard/security/DESKey
				L7:	goto L19;
				L8:	astore 5;
				L9:	aload_0;
					invokevirtual 186;		// clear()V
					sspush 27264;
					invokestatic 150;		// javacard/framework/ISOException.throwIt(S)V
				L10:	goto L19;
				L11:	getfield_a_this 24;		// reference com/makina/security/OpenFIPS201/PIVKeyObjectSYM.key
					checkcast 0 187;		// T_CLASSORINTERFACE javacard/security/AESKey
					aload_2;
					sload_3;
					invokeinterface 3 187 4;		// javacard/security/AESKey
				L12:	goto L19;
				L13:	astore 5;
				L14:	aload_0;
					invokevirtual 186;		// clear()V
					sspush 27264;
					invokestatic 150;		// javacard/framework/ISOException.throwIt(S)V
				L15:	goto L19;
				L16:	sspush 27012;
					invokestatic 150;		// javacard/framework/ISOException.throwIt(S)V
					goto L19;
				L17:	aload_0;
					invokevirtual 186;		// clear()V
					goto L19;
				L18:	sspush 27264;
					invokestatic 150;		// javacard/framework/ISOException.throwIt(S)V
				L19:	return;
			.exceptionTable {
				// start_block end_block handler_block catch_type_index
				L6 L7 L8 102;
				L11 L12 L13 102;
			}
		}

		.method private allocate()V {
			.stack 4;
			.locals 0;

				L0:	getfield_a_this 19;		// reference com/makina/security/OpenFIPS201/PIVObject.header
					sconst_3;
					baload;
					stableswitch L5 0 12 L1 L5 L5 L1 L5 L5 L5 L5 L2 L5 L3 L5 L4;
				L1:	aload_0;
					sconst_3;
					sspush 192;
					sconst_0;
					invokestatic 188;		// javacard/security/KeyBuilder.buildKey(BSZ)Ljavacard/security/Key;
					checkcast 0 184;		// T_CLASSORINTERFACE javacard/security/SecretKey
					putfield_a 24;		// reference com/makina/security/OpenFIPS201/PIVKeyObjectSYM.key
					goto L6;
				L2:	aload_0;
					bspush 15;
					sspush 128;
					sconst_0;
					invokestatic 188;		// javacard/security/KeyBuilder.buildKey(BSZ)Ljavacard/security/Key;
					checkcast 0 184;		// T_CLASSORINTERFACE javacard/security/SecretKey
					putfield_a 24;		// reference com/makina/security/OpenFIPS201/PIVKeyObjectSYM.key
					goto L6;
				L3:	aload_0;
					bspush 15;
					sspush 192;
					sconst_0;
					invokestatic 188;		// javacard/security/KeyBuilder.buildKey(BSZ)Ljavacard/security/Key;
					checkcast 0 184;		// T_CLASSORINTERFACE javacard/security/SecretKey
					putfield_a 24;		// reference com/makina/security/OpenFIPS201/PIVKeyObjectSYM.key
					goto L6;
				L4:	aload_0;
					bspush 15;
					sspush 256;
					sconst_0;
					invokestatic 188;		// javacard/security/KeyBuilder.buildKey(BSZ)Ljavacard/security/Key;
					checkcast 0 184;		// T_CLASSORINTERFACE javacard/security/SecretKey
					putfield_a 24;		// reference com/makina/security/OpenFIPS201/PIVKeyObjectSYM.key
					goto L6;
				L5:	sspush 27266;
					invokestatic 150;		// javacard/framework/ISOException.throwIt(S)V
				L6:	return;
		}

		.method public clear()V 6 {
			.stack 1;
			.locals 0;

				L0:	getfield_a_this 24;		// reference com/makina/security/OpenFIPS201/PIVKeyObjectSYM.key
					ifnull L2;
				L1:	getfield_a_this 24;		// reference com/makina/security/OpenFIPS201/PIVKeyObjectSYM.key
					invokeinterface 1 184 0;		// javacard/security/SecretKey
				L2:	return;
		}

		.method public isInitialised()Z 5 {
			.stack 1;
			.locals 0;

				L0:	getfield_a_this 24;		// reference com/makina/security/OpenFIPS201/PIVKeyObjectSYM.key
					ifnull L3;
				L1:	getfield_a_this 24;		// reference com/makina/security/OpenFIPS201/PIVKeyObjectSYM.key
					invokeinterface 1 184 3;		// javacard/security/SecretKey
					ifeq L3;
				L2:	sconst_1;
					goto L4;
				L3:	sconst_0;
				L4:	sreturn;
		}

		.method public encrypt(Ljavacardx/crypto/Cipher;[BSS[BS)S 18 {
			.stack 6;
			.locals 0;

			.descriptor	Ljavacardx/crypto/Cipher;	3.1;

				L0:	aload_1;
					getfield_a_this 24;		// reference com/makina/security/OpenFIPS201/PIVKeyObjectSYM.key
					sconst_2;
					invokevirtual 179;		// init(Ljavacard/security/Key;B)V
					aload_1;
					aload_2;
					sload_3;
					sload 4;
					aload 5;
					sload 6;
					invokevirtual 180;		// doFinal([BSS[BS)S
					sreturn;
		}

		.method public decrypt(Ljavacardx/crypto/Cipher;[BSS[BS)S 19 {
			.stack 6;
			.locals 0;

			.descriptor	Ljavacardx/crypto/Cipher;	3.1;

				L0:	aload_1;
					getfield_a_this 24;		// reference com/makina/security/OpenFIPS201/PIVKeyObjectSYM.key
					sconst_1;
					invokevirtual 179;		// init(Ljavacard/security/Key;B)V
					aload_1;
					aload_2;
					sload_3;
					sload 4;
					aload 5;
					sload 6;
					invokevirtual 180;		// doFinal([BSS[BS)S
					sreturn;
		}

	}

	.class public final PIVDataObject 9 extends PIVObject {

		.fields {
			public byte[] content 0;		// [B
			private short bytesAllocated 1;		// S
			private static final short HEADER_POPULATED = 3;		// S
		}

		.publicMethodTable 5 {
			equals(Ljava/lang/Object;)Z;
			match(B)Z;
			getId()B;
			getModeContact()B;
			getModeContactless()B;
			isInitialised()Z;
			clear()V;
			getLength()S;
			allocate(S)V;
		}

		.packageMethodTable 0 {
		}

		.method public getLength()S 7 {
			.stack 1;
			.locals 0;

				L0:	getfield_s_this 25;		// short com/makina/security/OpenFIPS201/PIVDataObject.bytesAllocated
					sreturn;
		}

		.method public <init>(BBB)V 0 {
			.stack 4;
			.locals 0;

				L0:	aload_0;
					sload_1;
					sload_2;
					sload_3;
					invokespecial 162;		// com/makina/security/OpenFIPS201/PIVObject.<init>(BBB)V
					return;
		}

		.method public allocate(S)V 8 {
			.stack 4;
			.locals 0;

				L0:	sload_1;
					ifge L2;
				L1:	sspush 27012;
					invokestatic 150;		// javacard/framework/ISOException.throwIt(S)V
					goto L12;
				L2:	sload_1;
					ifne L5;
				L3:	aload_0;
					aconst_null;
					putfield_a 14;		// reference com/makina/security/OpenFIPS201/PIVDataObject.content
					invokestatic 190;		// javacard/framework/JCSystem.isObjectDeletionSupported()Z
					ifeq L12;
				L4:	invokestatic 191;		// javacard/framework/JCSystem.requestObjectDeletion()V
					goto L12;
				L5:	getfield_a_this 14;		// reference com/makina/security/OpenFIPS201/PIVDataObject.content
					ifnonnull L7;
				L6:	aload_0;
					sload_1;
					newarray 11;
					putfield_a 14;		// reference com/makina/security/OpenFIPS201/PIVDataObject.content
					goto L12;
				L7:	sload_1;
					getfield_a_this 14;		// reference com/makina/security/OpenFIPS201/PIVDataObject.content
					arraylength;
					if_scmple L11;
				L8:	invokestatic 190;		// javacard/framework/JCSystem.isObjectDeletionSupported()Z
					ifne L10;
				L9:	sspush 27268;
					invokestatic 150;		// javacard/framework/ISOException.throwIt(S)V
				L10:	aload_0;
					aconst_null;
					putfield_a 14;		// reference com/makina/security/OpenFIPS201/PIVDataObject.content
					invokestatic 191;		// javacard/framework/JCSystem.requestObjectDeletion()V
					aload_0;
					sload_1;
					newarray 11;
					putfield_a 14;		// reference com/makina/security/OpenFIPS201/PIVDataObject.content
					goto L12;
				L11:	getfield_a_this 14;		// reference com/makina/security/OpenFIPS201/PIVDataObject.content
					sconst_0;
					getfield_a_this 14;		// reference com/makina/security/OpenFIPS201/PIVDataObject.content
					arraylength;
					sconst_0;
					invokestatic 85;		// javacard/framework/Util.arrayFillNonAtomic([BSSB)S
					pop;
				L12:	aload_0;
					sload_1;
					putfield_s 25;		// short com/makina/security/OpenFIPS201/PIVDataObject.bytesAllocated
					return;
		}

		.method public isInitialised()Z 5 {
			.stack 1;
			.locals 0;

				L0:	getfield_a_this 14;		// reference com/makina/security/OpenFIPS201/PIVDataObject.content
					ifnull L2;
				L1:	sconst_1;
					goto L3;
				L2:	sconst_0;
				L3:	sreturn;
		}

		.method public clear()V 6 {
			.stack 4;
			.locals 0;

				L0:	getfield_a_this 14;		// reference com/makina/security/OpenFIPS201/PIVDataObject.content
					ifnonnull L2;
				L1:	return;
				L2:	getfield_a_this 14;		// reference com/makina/security/OpenFIPS201/PIVDataObject.content
					sconst_0;
					getfield_a_this 14;		// reference com/makina/security/OpenFIPS201/PIVDataObject.content
					arraylength;
					sconst_0;
					invokestatic 85;		// javacard/framework/Util.arrayFillNonAtomic([BSSB)S
					pop;
					aload_0;
					sconst_0;
					putfield_s 25;		// short com/makina/security/OpenFIPS201/PIVDataObject.bytesAllocated
					return;
		}

	}

	.class public final PIVSecurityProvider 10 extends 2.0 {		// extends java/lang/Object

		.fields {
			public final 0.9 cardPIN 0;		// Ljavacard/framework/OwnerPIN;
			public final 0.9 cardPUK 1;		// Ljavacard/framework/OwnerPIN;
			public final CVMPIN globalPIN 2;		// Lcom/makina/security/OpenFIPS201/CVMPIN;
			private PIVKeyObject firstKey 3;		// Lcom/makina/security/OpenFIPS201/PIVKeyObject;
			private final 3.1 cspAES 4;		// Ljavacardx/crypto/Cipher;
			private final 3.1 cspRSA 5;		// Ljavacardx/crypto/Cipher;
			private final 3.1 cspTDEA 6;		// Ljavacardx/crypto/Cipher;
			private final 4.14 cspRNG 7;		// Ljavacard/security/RandomData;
			private final boolean[] securityFlags 8;		// [Z
			private static final short FLAG_CONTACTLESS = 0;		// S
			private static final short FLAG_SECURE_CHANNEL = 1;		// S
			private static final short FLAG_PIN_ALWAYS = 2;		// S
			private static final short LENGTH_FLAGS = 3;		// S
		}

		.publicMethodTable 1 {
			equals(Ljava/lang/Object;)Z;
			resetSecurityStatus()V;
			setPINAlways(Z)V;
			getPINAlways()Z;
			setIsContactless(Z)V;
			getIsContactless()Z;
			setIsSecureChannel(Z)V;
			getIsSecureChannel()Z;
			selectKey(BB)Lcom/makina/security/OpenFIPS201/PIVKeyObject;;
			keyExists(B)Z;
			createKey(BBBBB)V;
			checkAccessModeAdmin(Z)Z;
			checkAccessModeObject(Lcom/makina/security/OpenFIPS201/PIVObject;)Z;
			generateRandom([BSS)V;
			encrypt(Lcom/makina/security/OpenFIPS201/PIVKeyObject;[BSS[BS)S;
			zeroise([BSS)V;
		}

		.packageMethodTable 0 {
		}

		.method public <init>()V 0 {
			.stack 5;
			.locals 0;

				L0:	aload_0;
					invokespecial 202;		// java/lang/Object.<init>()V
					aload_0;
					bspush 14;
					sconst_0;
					invokestatic 192;		// javacardx/crypto/Cipher.getInstance(BZ)Ljavacardx/crypto/Cipher;
					putfield_a 26;		// reference com/makina/security/OpenFIPS201/PIVSecurityProvider.cspAES
					aload_0;
					bspush 12;
					sconst_0;
					invokestatic 192;		// javacardx/crypto/Cipher.getInstance(BZ)Ljavacardx/crypto/Cipher;
					putfield_a 27;		// reference com/makina/security/OpenFIPS201/PIVSecurityProvider.cspRSA
					aload_0;
					sconst_5;
					sconst_0;
					invokestatic 192;		// javacardx/crypto/Cipher.getInstance(BZ)Ljavacardx/crypto/Cipher;
					putfield_a 28;		// reference com/makina/security/OpenFIPS201/PIVSecurityProvider.cspTDEA
					aload_0;
					sconst_2;
					invokestatic 196;		// javacard/security/RandomData.getInstance(B)Ljavacard/security/RandomData;
					putfield_a 29;		// reference com/makina/security/OpenFIPS201/PIVSecurityProvider.cspRNG
					aload_0;
					sconst_3;
					sconst_2;
					invokestatic 163;		// javacard/framework/JCSystem.makeTransientBooleanArray(SB)[Z
					putfield_a 30;		// reference com/makina/security/OpenFIPS201/PIVSecurityProvider.securityFlags
					aload_0;
					new 199;		// javacard/framework/OwnerPIN
					dup;
					bspush 6;
					bspush 8;
					invokespecial 74;		// javacard/framework/OwnerPIN.<init>(BB)V
					putfield_a 12;		// reference com/makina/security/OpenFIPS201/PIVSecurityProvider.cardPIN
					aload_0;
					new 199;		// javacard/framework/OwnerPIN
					dup;
					bspush 6;
					bspush 8;
					invokespecial 74;		// javacard/framework/OwnerPIN.<init>(BB)V
					putfield_a 13;		// reference com/makina/security/OpenFIPS201/PIVSecurityProvider.cardPUK
					aload_0;
					new 200;		// com/makina/security/OpenFIPS201/CVMPIN
					dup;
					bspush 6;
					bspush 8;
					invokespecial 201;		// com/makina/security/OpenFIPS201/CVMPIN.<init>(BB)V
					putfield_a 15;		// reference com/makina/security/OpenFIPS201/PIVSecurityProvider.globalPIN
					return;
		}

		.method public resetSecurityStatus()V 1 {
			.stack 1;
			.locals 1;

				L0:	getfield_a_this 12;		// reference com/makina/security/OpenFIPS201/PIVSecurityProvider.cardPIN
					invokevirtual 108;		// isValidated()Z
					ifeq L2;
				L1:	getfield_a_this 12;		// reference com/makina/security/OpenFIPS201/PIVSecurityProvider.cardPIN
					invokevirtual 109;		// reset()V
				L2:	getfield_a_this 13;		// reference com/makina/security/OpenFIPS201/PIVSecurityProvider.cardPUK
					invokevirtual 108;		// isValidated()Z
					ifeq L4;
				L3:	getfield_a_this 13;		// reference com/makina/security/OpenFIPS201/PIVSecurityProvider.cardPUK
					invokevirtual 109;		// reset()V
				L4:	getfield_a_this 31;		// reference com/makina/security/OpenFIPS201/PIVSecurityProvider.firstKey
					astore_1;
				L5:	aload_1;
					ifnull L7;
				L6:	aload_1;
					invokevirtual 135;		// resetSecurityStatus()V
					aload_1;
					getfield_a 32;		// reference com/makina/security/OpenFIPS201/PIVObject.nextObject
					checkcast 0 204;		// T_CLASSORINTERFACE com/makina/security/OpenFIPS201/PIVKeyObject
					astore_1;
					goto L5;
				L7:	return;
		}

		.method public setPINAlways(Z)V 2 {
			.stack 3;
			.locals 0;

				L0:	getfield_a_this 30;		// reference com/makina/security/OpenFIPS201/PIVSecurityProvider.securityFlags
					sconst_2;
					sload_1;
					bastore;
					return;
		}

		.method public getPINAlways()Z 3 {
			.stack 2;
			.locals 0;

				L0:	getfield_a_this 30;		// reference com/makina/security/OpenFIPS201/PIVSecurityProvider.securityFlags
					sconst_2;
					baload;
					ifeq L4;
				L1:	getfield_a_this 12;		// reference com/makina/security/OpenFIPS201/PIVSecurityProvider.cardPIN
					invokevirtual 108;		// isValidated()Z
					ifne L3;
				L2:	getfield_a_this 15;		// reference com/makina/security/OpenFIPS201/PIVSecurityProvider.globalPIN
					invokevirtual 205;		// isValidated()Z
					ifeq L4;
				L3:	sconst_1;
					goto L5;
				L4:	sconst_0;
				L5:	sreturn;
		}

		.method public setIsContactless(Z)V 4 {
			.stack 3;
			.locals 0;

				L0:	getfield_a_this 30;		// reference com/makina/security/OpenFIPS201/PIVSecurityProvider.securityFlags
					sconst_0;
					sload_1;
					bastore;
					return;
		}

		.method public getIsContactless()Z 5 {
			.stack 2;
			.locals 0;

				L0:	getfield_a_this 30;		// reference com/makina/security/OpenFIPS201/PIVSecurityProvider.securityFlags
					sconst_0;
					baload;
					sreturn;
		}

		.method public setIsSecureChannel(Z)V 6 {
			.stack 3;
			.locals 0;

				L0:	getfield_a_this 30;		// reference com/makina/security/OpenFIPS201/PIVSecurityProvider.securityFlags
					sconst_1;
					sload_1;
					bastore;
					return;
		}

		.method public getIsSecureChannel()Z 7 {
			.stack 2;
			.locals 0;

				L0:	getfield_a_this 30;		// reference com/makina/security/OpenFIPS201/PIVSecurityProvider.securityFlags
					sconst_1;
					baload;
					sreturn;
		}

		.method public selectKey(BB)Lcom/makina/security/OpenFIPS201/PIVKeyObject; 8 {
			.stack 3;
			.locals 1;

				L0:	sload_2;
					ifne L2;
				L1:	sconst_3;
					sstore_2;
				L2:	getfield_a_this 31;		// reference com/makina/security/OpenFIPS201/PIVSecurityProvider.firstKey
					astore_3;
				L3:	aload_3;
					ifnull L7;
				L4:	aload_3;
					sload_1;
					sload_2;
					invokevirtual 206;		// match(BB)Z
					ifeq L6;
				L5:	aload_3;
					areturn;
				L6:	aload_3;
					getfield_a 32;		// reference com/makina/security/OpenFIPS201/PIVObject.nextObject
					checkcast 0 204;		// T_CLASSORINTERFACE com/makina/security/OpenFIPS201/PIVKeyObject
					astore_3;
					goto L3;
				L7:	aconst_null;
					areturn;
		}

		.method public keyExists(B)Z 9 {
			.stack 2;
			.locals 1;

				L0:	getfield_a_this 31;		// reference com/makina/security/OpenFIPS201/PIVSecurityProvider.firstKey
					astore_2;
				L1:	aload_2;
					ifnull L5;
				L2:	aload_2;
					sload_1;
					invokevirtual 207;		// match(B)Z
					ifeq L4;
				L3:	sconst_1;
					sreturn;
				L4:	aload_2;
					getfield_a 32;		// reference com/makina/security/OpenFIPS201/PIVObject.nextObject
					checkcast 0 204;		// T_CLASSORINTERFACE com/makina/security/OpenFIPS201/PIVKeyObject
					astore_2;
					goto L1;
				L5:	sconst_0;
					sreturn;
		}

		.method public createKey(BBBBB)V 10 {
			.stack 5;
			.locals 2;

				L0:	sload 4;
					ifne L2;
				L1:	sconst_3;
					sstore 4;
				L2:	sload_1;
					sload_2;
					sload_3;
					sload 4;
					sload 5;
					invokestatic 208;		// com/makina/security/OpenFIPS201/PIVKeyObject.create(BBBBB)Lcom/makina/security/OpenFIPS201/PIVKeyObject;
					astore 6;
				L3:	getfield_a_this 31;		// reference com/makina/security/OpenFIPS201/PIVSecurityProvider.firstKey
					ifnonnull L5;
				L4:	aload_0;
					aload 6;
					putfield_a 31;		// reference com/makina/security/OpenFIPS201/PIVSecurityProvider.firstKey
					return;
				L5:	getfield_a_this 31;		// reference com/makina/security/OpenFIPS201/PIVSecurityProvider.firstKey
					astore 7;
				L6:	aload 7;
					getfield_a 17;		// reference com/makina/security/OpenFIPS201/PIVObject.nextObject
					ifnull L8;
				L7:	aload 7;
					getfield_a 17;		// reference com/makina/security/OpenFIPS201/PIVObject.nextObject
					astore 7;
					goto L6;
				L8:	aload 7;
					aload 6;
					putfield_a 17;		// reference com/makina/security/OpenFIPS201/PIVObject.nextObject
					return;
		}

		.method public checkAccessModeAdmin(Z)Z 11 {
			.stack 3;
			.locals 2;

				L0:	sconst_0;
					sstore_2;
				L1:	sload_1;
					ifne L9;
				L2:	getfield_a_this 31;		// reference com/makina/security/OpenFIPS201/PIVSecurityProvider.firstKey
					astore_3;
				L3:	aload_3;
					ifnull L9;
				L4:	sload_2;
					ifne L9;
				L5:	aload_3;
					sconst_1;
					invokevirtual 125;		// hasRole(B)Z
					ifeq L8;
				L6:	aload_3;
					invokevirtual 209;		// getSecurityStatus()Z
					ifeq L8;
				L7:	sconst_1;
					sstore_2;
					goto L9;
				L8:	aload_3;
					getfield_a 32;		// reference com/makina/security/OpenFIPS201/PIVObject.nextObject
					checkcast 0 204;		// T_CLASSORINTERFACE com/makina/security/OpenFIPS201/PIVKeyObject
					astore_3;
					goto L3;
				L9:	sload_2;
					getfield_a_this 30;		// reference com/makina/security/OpenFIPS201/PIVSecurityProvider.securityFlags
					sconst_1;
					baload;
					sor;
					sstore_2;
					getfield_a_this 30;		// reference com/makina/security/OpenFIPS201/PIVSecurityProvider.securityFlags
					sconst_2;
					sconst_0;
					bastore;
					sload_2;
					sreturn;
		}

		.method public checkAccessModeObject(Lcom/makina/security/OpenFIPS201/PIVObject;)Z 12 {
			.stack 3;
			.locals 2;

				L0:	getfield_a_this 30;		// reference com/makina/security/OpenFIPS201/PIVSecurityProvider.securityFlags
					sconst_0;
					baload;
					ifeq L2;
				L1:	aload_1;
					invokevirtual 210;		// getModeContactless()B
					goto L3;
				L2:	aload_1;
					invokevirtual 211;		// getModeContact()B
				L3:	sstore_3;
				L4:	sload_3;
					ifne L7;
				L5:	sconst_0;
					sstore_2;
				L6:	goto L18;
				L7:	sload_3;
					bspush 127;
					if_scmpne L10;
				L8:	sconst_1;
					sstore_2;
				L9:	goto L18;
				L10:	sconst_1;
					sstore_2;
				L11:	sload_3;
					sconst_1;
					sand;
					sconst_1;
					if_scmpne L15;
				L12:	getfield_a_this 12;		// reference com/makina/security/OpenFIPS201/PIVSecurityProvider.cardPIN
					invokevirtual 108;		// isValidated()Z
					ifeq L14;
				L13:	goto L15;
				L14:	sconst_0;
					sstore_2;
				L15:	sload_3;
					sconst_2;
					sand;
					sconst_2;
					if_scmpne L18;
				L16:	getfield_a_this 30;		// reference com/makina/security/OpenFIPS201/PIVSecurityProvider.securityFlags
					sconst_2;
					baload;
					ifne L18;
				L17:	sconst_0;
					sstore_2;
				L18:	getfield_a_this 30;		// reference com/makina/security/OpenFIPS201/PIVSecurityProvider.securityFlags
					sconst_2;
					sconst_0;
					bastore;
					sload_2;
					sreturn;
		}

		.method public generateRandom([BSS)V 13 {
			.stack 4;
			.locals 0;

				L0:	getfield_a_this 29;		// reference com/makina/security/OpenFIPS201/PIVSecurityProvider.cspRNG
					aload_1;
					sload_2;
					sload_3;
					invokevirtual 212;		// generateData([BSS)V
					return;
		}

		.method public encrypt(Lcom/makina/security/OpenFIPS201/PIVKeyObject;[BSS[BS)S 14 {
			.stack 7;
			.locals 1;

				L0:	aload_1;
					invokevirtual 137;		// getMechanism()B
					stableswitch L7 0 12 L1 L7 L7 L1 L7 L7 L5 L5 L3 L7 L3 L7 L3;
				L1:	getfield_a_this 28;		// reference com/makina/security/OpenFIPS201/PIVSecurityProvider.cspTDEA
					astore 7;
				L2:	goto L8;
				L3:	getfield_a_this 26;		// reference com/makina/security/OpenFIPS201/PIVSecurityProvider.cspAES
					astore 7;
				L4:	goto L8;
				L5:	getfield_a_this 27;		// reference com/makina/security/OpenFIPS201/PIVSecurityProvider.cspRSA
					astore 7;
				L6:	goto L8;
				L7:	sspush 27012;
					invokestatic 150;		// javacard/framework/ISOException.throwIt(S)V
					sconst_0;
					sreturn;
				L8:	aload_1;
					aload 7;
					aload_2;
					sload_3;
					sload 4;
					aload 5;
					sload 6;
					invokevirtual 213;		// encrypt(Ljavacardx/crypto/Cipher;[BSS[BS)S
					sreturn;
		}

		.method public zeroise([BSS)V 15 {
			.stack 4;
			.locals 0;

				L0:	aload_1;
					sload_2;
					sload_3;
					sconst_0;
					invokestatic 85;		// javacard/framework/Util.arrayFillNonAtomic([BSSB)S
					pop;
					aload_1;
					sload_2;
					sload_3;
					sconst_m1;
					invokestatic 85;		// javacard/framework/Util.arrayFillNonAtomic([BSSB)S
					pop;
					aload_1;
					sload_2;
					sload_3;
					sconst_0;
					invokestatic 85;		// javacard/framework/Util.arrayFillNonAtomic([BSSB)S
					pop;
					return;
		}

	}

	.class public final TLVReader 11 extends 2.0 {		// extends java/lang/Object

		.fields {
			public 2.0[] dataPtr 0;		// [Ljava/lang/Object;
			public short[] context 1;		// [S
			public static final byte CLASS_UNIVERSAL = 0;		// B
			public static final byte CLASS_APPLICATION = 64;		// B
			public static final byte CLASS_CONTEXT = -128;		// B
			public static final byte CLASS_PRIVATE = -64;		// B
			public static final byte MASK_CONSTRUCTED = 32;		// B
			public static final byte MASK_LOW_TAG_NUMBER = 31;		// B
			public static final byte MASK_HIGH_TAG_NUMBER = 127;		// B
			public static final byte MASK_HIGH_TAG_MOREDATA = -128;		// B
			public static final byte MASK_LONG_LENGTH = -128;		// B
			public static final byte MASK_LENGTH = 127;		// B
			public static final byte ASN1_BOOLEAN = 1;		// B
			public static final byte ASN1_INTEGER = 2;		// B
			public static final byte ASN1_BIT_STRING = 3;		// B
			public static final byte ASN1_OCTET_STRING = 4;		// B
			public static final byte ASN1_NULL = 5;		// B
			public static final byte ASN1_OBJECT = 6;		// B
			public static final byte ASN1_ENUMERATED = 10;		// B
			public static final byte ASN1_SEQUENCE = 16;		// B
			public static final byte ASN1_SET = 17;		// B
			public static final byte ASN1_PRINT_STRING = 19;		// B
			public static final byte ASN1_T61_STRING = 20;		// B
			public static final byte ASN1_IA5_STRING = 22;		// B
			public static final byte ASN1_UTC_TIME = 23;		// B
			private static final short CONTEXT_LENGTH = 0;		// S
			private static final short CONTEXT_POSITION = 1;		// S
			private static final short CONTEXT_POSITION_RESET = 2;		// S
			private static final short LENGTH_CONTEXT = 4;		// S
		}

		.publicMethodTable 1 {
			equals(Ljava/lang/Object;)Z;
			init([BSS)V;
			clear()V;
			isInitialized()Z;
			resetPosition()V;
			find(B)Z;
			find(S)Z;
			findNext(B)Z;
			findNext(S)Z;
			moveNext()Z;
			moveInto()Z;
			match(B)Z;
			getTag()B;
			getTagShort()S;
			isConstructed()Z;
			getLength()S;
			isNull()Z;
			getOffset()S;
			setOffset(S)V;
			getDataOffset()S;
			toShort()S;
			toByte()B;
			toBytes([BS)V;
		}

		.packageMethodTable 0 {
		}

		.method public <init>()V 0 {
			.stack 3;
			.locals 0;

				L0:	aload_0;
					invokespecial 202;		// java/lang/Object.<init>()V
					aload_0;
					sconst_1;
					sconst_2;
					invokestatic 219;		// javacard/framework/JCSystem.makeTransientObjectArray(SB)[Ljava/lang/Object;
					putfield_a 33;		// reference com/makina/security/OpenFIPS201/TLVReader.dataPtr
					aload_0;
					sconst_4;
					sconst_2;
					invokestatic 73;		// javacard/framework/JCSystem.makeTransientShortArray(SB)[S
					putfield_a 34;		// reference com/makina/security/OpenFIPS201/TLVReader.context
					return;
		}

		.method public init([BSS)V 1 {
			.stack 3;
			.locals 0;

				L0:	getfield_a_this 33;		// reference com/makina/security/OpenFIPS201/TLVReader.dataPtr
					sconst_0;
					aload_1;
					aastore;
					getfield_a_this 34;		// reference com/makina/security/OpenFIPS201/TLVReader.context
					sconst_1;
					sload_2;
					sastore;
					getfield_a_this 34;		// reference com/makina/security/OpenFIPS201/TLVReader.context
					sconst_2;
					sload_2;
					sastore;
					getfield_a_this 34;		// reference com/makina/security/OpenFIPS201/TLVReader.context
					sconst_0;
					sload_3;
					sastore;
					return;
		}

		.method public clear()V 2 {
			.stack 3;
			.locals 0;

				L0:	getfield_a_this 33;		// reference com/makina/security/OpenFIPS201/TLVReader.dataPtr
					sconst_0;
					aconst_null;
					aastore;
					getfield_a_this 34;		// reference com/makina/security/OpenFIPS201/TLVReader.context
					sconst_1;
					sconst_0;
					sastore;
					getfield_a_this 34;		// reference com/makina/security/OpenFIPS201/TLVReader.context
					sconst_2;
					sconst_0;
					sastore;
					getfield_a_this 34;		// reference com/makina/security/OpenFIPS201/TLVReader.context
					sconst_0;
					sconst_0;
					sastore;
					return;
		}

		.method public isInitialized()Z 3 {
			.stack 2;
			.locals 0;

				L0:	getfield_a_this 33;		// reference com/makina/security/OpenFIPS201/TLVReader.dataPtr
					sconst_0;
					aaload;
					ifnull L2;
				L1:	sconst_1;
					goto L3;
				L2:	sconst_0;
				L3:	sreturn;
		}

		.method public resetPosition()V 4 {
			.stack 4;
			.locals 0;

				L0:	aload_0;
					invokevirtual 216;		// isInitialized()Z
					ifne L2;
				L1:	sspush 27012;
					invokestatic 150;		// javacard/framework/ISOException.throwIt(S)V
				L2:	getfield_a_this 34;		// reference com/makina/security/OpenFIPS201/TLVReader.context
					sconst_1;
					getfield_a_this 34;		// reference com/makina/security/OpenFIPS201/TLVReader.context
					sconst_2;
					saload;
					sastore;
					return;
		}

		.method public find(B)Z 5 {
			.stack 3;
			.locals 0;

				L0:	getfield_a_this 34;		// reference com/makina/security/OpenFIPS201/TLVReader.context
					sconst_1;
					saload;
					getfield_a_this 34;		// reference com/makina/security/OpenFIPS201/TLVReader.context
					sconst_2;
					saload;
					ssub;
					getfield_a_this 34;		// reference com/makina/security/OpenFIPS201/TLVReader.context
					sconst_0;
					saload;
					if_scmpge L5;
				L1:	sload_1;
					aload_0;
					invokevirtual 153;		// getTag()B
					if_scmpne L3;
				L2:	sconst_1;
					sreturn;
				L3:	aload_0;
					invokevirtual 121;		// moveNext()Z
					ifne L0;
				L4:	sconst_0;
					sreturn;
				L5:	sconst_0;
					sreturn;
		}

		.method public find(S)Z 6 {
			.stack 3;
			.locals 0;

				L0:	getfield_a_this 34;		// reference com/makina/security/OpenFIPS201/TLVReader.context
					sconst_1;
					saload;
					getfield_a_this 34;		// reference com/makina/security/OpenFIPS201/TLVReader.context
					sconst_2;
					saload;
					ssub;
					getfield_a_this 34;		// reference com/makina/security/OpenFIPS201/TLVReader.context
					sconst_0;
					saload;
					if_scmpge L5;
				L1:	sload_1;
					aload_0;
					invokevirtual 217;		// getTagShort()S
					if_scmpne L3;
				L2:	sconst_1;
					sreturn;
				L3:	aload_0;
					invokevirtual 121;		// moveNext()Z
					ifne L0;
				L4:	sconst_0;
					sreturn;
				L5:	sconst_0;
					sreturn;
		}

		.method public findNext(B)Z 7 {
			.stack 2;
			.locals 0;

				L0:	aload_0;
					invokevirtual 121;		// moveNext()Z
					ifne L2;
				L1:	sconst_0;
					sreturn;
				L2:	aload_0;
					sload_1;
					invokevirtual 116;		// find(B)Z
					sreturn;
		}

		.method public findNext(S)Z 8 {
			.stack 2;
			.locals 0;

				L0:	aload_0;
					invokevirtual 121;		// moveNext()Z
					ifne L2;
				L1:	sconst_0;
					sreturn;
				L2:	aload_0;
					sload_1;
					invokevirtual 218;		// find(S)Z
					sreturn;
		}

		.method public moveNext()Z 9 {
			.stack 4;
			.locals 1;

				L0:	aload_0;
					invokevirtual 126;		// getLength()S
					sstore_1;
				L1:	getfield_a_this 34;		// reference com/makina/security/OpenFIPS201/TLVReader.context
					sconst_1;
					aload_0;
					invokevirtual 127;		// getDataOffset()S
					sastore;
					getfield_a_this 34;		// reference com/makina/security/OpenFIPS201/TLVReader.context
					sconst_1;
					dup2;
					saload;
					sload_1;
					sadd;
					sastore;
					getfield_a_this 34;		// reference com/makina/security/OpenFIPS201/TLVReader.context
					sconst_1;
					saload;
					getfield_a_this 34;		// reference com/makina/security/OpenFIPS201/TLVReader.context
					sconst_2;
					saload;
					ssub;
					getfield_a_this 34;		// reference com/makina/security/OpenFIPS201/TLVReader.context
					sconst_0;
					saload;
					if_scmpge L3;
				L2:	sconst_1;
					goto L4;
				L3:	sconst_0;
				L4:	sreturn;
		}

		.method public moveInto()Z 10 {
			.stack 3;
			.locals 0;

				L0:	getfield_a_this 34;		// reference com/makina/security/OpenFIPS201/TLVReader.context
					sconst_1;
					aload_0;
					invokevirtual 127;		// getDataOffset()S
					sastore;
					getfield_a_this 34;		// reference com/makina/security/OpenFIPS201/TLVReader.context
					sconst_1;
					saload;
					getfield_a_this 34;		// reference com/makina/security/OpenFIPS201/TLVReader.context
					sconst_2;
					saload;
					ssub;
					getfield_a_this 34;		// reference com/makina/security/OpenFIPS201/TLVReader.context
					sconst_0;
					saload;
					if_scmpge L2;
				L1:	sconst_1;
					goto L3;
				L2:	sconst_0;
				L3:	sreturn;
		}

		.method public match(B)Z 11 {
			.stack 4;
			.locals 1;

				L0:	getfield_a_this 33;		// reference com/makina/security/OpenFIPS201/TLVReader.dataPtr
					sconst_0;
					aaload;
					checkcast 11 0;		// T_BYTE
					checkcast 11 0;		// T_BYTE
					astore_2;
				L1:	sload_1;
					aload_2;
					getfield_a_this 34;		// reference com/makina/security/OpenFIPS201/TLVReader.context
					sconst_1;
					saload;
					baload;
					if_scmpne L3;
				L2:	sconst_1;
					goto L4;
				L3:	sconst_0;
				L4:	sreturn;
		}

		.method private match(S)Z {
			.stack 4;
			.locals 0;

				L0:	sload_1;
					getfield_a_this 33;		// reference com/makina/security/OpenFIPS201/TLVReader.dataPtr
					sconst_0;
					aaload;
					checkcast 11 0;		// T_BYTE
					checkcast 11 0;		// T_BYTE
					getfield_a_this 34;		// reference com/makina/security/OpenFIPS201/TLVReader.context
					sconst_1;
					saload;
					invokestatic 95;		// javacard/framework/Util.getShort([BS)S
					if_scmpne L2;
				L1:	sconst_1;
					goto L3;
				L2:	sconst_0;
				L3:	sreturn;
		}

		.method public getTag()B 12 {
			.stack 3;
			.locals 1;

				L0:	getfield_a_this 33;		// reference com/makina/security/OpenFIPS201/TLVReader.dataPtr
					sconst_0;
					aaload;
					checkcast 11 0;		// T_BYTE
					checkcast 11 0;		// T_BYTE
					astore_1;
				L1:	aload_1;
					getfield_a_this 34;		// reference com/makina/security/OpenFIPS201/TLVReader.context
					sconst_1;
					saload;
					baload;
					sreturn;
		}

		.method public getTagShort()S 13 {
			.stack 3;
			.locals 0;

				L0:	getfield_a_this 33;		// reference com/makina/security/OpenFIPS201/TLVReader.dataPtr
					sconst_0;
					aaload;
					checkcast 11 0;		// T_BYTE
					checkcast 11 0;		// T_BYTE
					getfield_a_this 34;		// reference com/makina/security/OpenFIPS201/TLVReader.context
					sconst_1;
					saload;
					invokestatic 95;		// javacard/framework/Util.getShort([BS)S
					sreturn;
		}

		.method public isConstructed()Z 14 {
			.stack 2;
			.locals 0;

				L0:	aload_0;
					invokevirtual 153;		// getTag()B
					bspush 32;
					sand;
					bspush 32;
					if_scmpne L2;
				L1:	sconst_1;
					goto L3;
				L2:	sconst_0;
				L3:	sreturn;
		}

		.method public getLength()S 15 {
			.stack 3;
			.locals 0;

				L0:	getfield_a_this 33;		// reference com/makina/security/OpenFIPS201/TLVReader.dataPtr
					sconst_0;
					aaload;
					checkcast 11 0;		// T_BYTE
					checkcast 11 0;		// T_BYTE
					getfield_a_this 34;		// reference com/makina/security/OpenFIPS201/TLVReader.context
					sconst_1;
					saload;
					invokestatic 98;		// com/makina/security/OpenFIPS201/TLVReader.getLength([BS)S
					sreturn;
		}

		.method public static getLength([BS)S 1 {
			.stack 2;
			.locals 0;

				L0:	sinc 1 1;
					aload_0;
					sload_1;
					baload;
					bspush -128;
					sand;
					bspush -128;
					if_scmpeq L2;
				L1:	aload_0;
					sload_1;
					baload;
					sspush 255;
					sand;
					sreturn;
				L2:	aload_0;
					sload_1;
					baload;
					bspush 127;
					sand;
					sconst_1;
					if_scmpne L4;
				L3:	sinc 1 1;
					aload_0;
					sload_1;
					baload;
					sspush 255;
					sand;
					sreturn;
				L4:	aload_0;
					sload_1;
					baload;
					bspush 127;
					sand;
					sconst_2;
					if_scmpne L6;
				L5:	sinc 1 1;
					aload_0;
					sload_1;
					invokestatic 95;		// javacard/framework/Util.getShort([BS)S
					sreturn;
				L6:	sspush 27012;
					invokestatic 150;		// javacard/framework/ISOException.throwIt(S)V
					sconst_m1;
					sreturn;
		}

		.method public isNull()Z 16 {
			.stack 1;
			.locals 0;

				L0:	aload_0;
					invokevirtual 126;		// getLength()S
					ifne L2;
				L1:	sconst_1;
					goto L3;
				L2:	sconst_0;
				L3:	sreturn;
		}

		.method public getOffset()S 17 {
			.stack 2;
			.locals 0;

				L0:	getfield_a_this 34;		// reference com/makina/security/OpenFIPS201/TLVReader.context
					sconst_1;
					saload;
					sreturn;
		}

		.method public setOffset(S)V 18 {
			.stack 3;
			.locals 0;

				L0:	getfield_a_this 34;		// reference com/makina/security/OpenFIPS201/TLVReader.context
					sconst_1;
					sload_1;
					sastore;
					return;
		}

		.method public getDataOffset()S 19 {
			.stack 3;
			.locals 0;

				L0:	getfield_a_this 33;		// reference com/makina/security/OpenFIPS201/TLVReader.dataPtr
					sconst_0;
					aaload;
					checkcast 11 0;		// T_BYTE
					checkcast 11 0;		// T_BYTE
					getfield_a_this 34;		// reference com/makina/security/OpenFIPS201/TLVReader.context
					sconst_1;
					saload;
					invokestatic 99;		// com/makina/security/OpenFIPS201/TLVReader.getDataOffset([BS)S
					sreturn;
		}

		.method public static getDataOffset([BS)S 2 {
			.stack 3;
			.locals 0;

				L0:	sinc 1 1;
					aload_0;
					sload_1;
					baload;
					bspush -128;
					sand;
					bspush -128;
					if_scmpne L2;
				L1:	sload_1;
					aload_0;
					sload_1;
					baload;
					bspush 127;
					sand;
					sadd;
					sstore_1;
				L2:	sinc 1 1;
					sload_1;
					sreturn;
		}

		.method public toShort()S 20 {
			.stack 2;
			.locals 3;

				L0:	getfield_a_this 33;		// reference com/makina/security/OpenFIPS201/TLVReader.dataPtr
					sconst_0;
					aaload;
					checkcast 11 0;		// T_BYTE
					checkcast 11 0;		// T_BYTE
					astore_1;
				L1:	aload_0;
					invokevirtual 126;		// getLength()S
					sstore_2;
				L2:	aload_0;
					invokevirtual 127;		// getDataOffset()S
					sstore_3;
				L3:	sconst_1;
					sload_2;
					if_scmpne L5;
				L4:	aload_1;
					sload_3;
					baload;
					sspush 255;
					sand;
					sreturn;
				L5:	sconst_2;
					sload_2;
					if_scmpne L7;
				L6:	aload_1;
					sload_3;
					invokestatic 95;		// javacard/framework/Util.getShort([BS)S
					sreturn;
				L7:	sspush 27012;
					invokestatic 150;		// javacard/framework/ISOException.throwIt(S)V
					sconst_m1;
					sreturn;
		}

		.method public toByte()B 21 {
			.stack 2;
			.locals 2;

				L0:	getfield_a_this 33;		// reference com/makina/security/OpenFIPS201/TLVReader.dataPtr
					sconst_0;
					aaload;
					checkcast 11 0;		// T_BYTE
					checkcast 11 0;		// T_BYTE
					astore_1;
				L1:	aload_0;
					invokevirtual 126;		// getLength()S
					sstore_2;
				L2:	sconst_1;
					sload_2;
					if_scmpne L4;
				L3:	aload_1;
					aload_0;
					invokevirtual 127;		// getDataOffset()S
					baload;
					sreturn;
				L4:	sspush 27012;
					invokestatic 150;		// javacard/framework/ISOException.throwIt(S)V
					sconst_0;
					sreturn;
		}

		.method public toBytes([BS)V 22 {
			.stack 5;
			.locals 3;

				L0:	getfield_a_this 33;		// reference com/makina/security/OpenFIPS201/TLVReader.dataPtr
					sconst_0;
					aaload;
					checkcast 11 0;		// T_BYTE
					checkcast 11 0;		// T_BYTE
					astore_3;
				L1:	aload_0;
					invokevirtual 126;		// getLength()S
					sstore 4;
				L2:	aload_0;
					invokevirtual 127;		// getDataOffset()S
					sstore 5;
				L3:	aload_3;
					sload 5;
					aload_1;
					sload_2;
					sload 4;
					invokestatic 156;		// javacard/framework/Util.arrayCopyNonAtomic([BS[BSS)S
					pop;
					return;
		}

	}

	.class public final TLVWriter 12 extends 2.0 {		// extends java/lang/Object

		.fields {
			public 2.0[] dataPtr 0;		// [Ljava/lang/Object;
			public short[] context 1;		// [S
			public static final short LENGTH_1BYTE_MAX = 127;		// S
			public static final short LENGTH_2BYTE_MAX = 255;		// S
			public static final short LENGTH_3BYTE_MAX = 32767;		// S
			private static final short CONTEXT_LENGTH_MAX = 0;		// S
			private static final short CONTEXT_LENGTH_PTR = 1;		// S
			private static final short CONTEXT_OFFSET = 2;		// S
			private static final short CONTEXT_OFFSET_RESET = 3;		// S
			private static final short LENGTH_CONTEXT = 4;		// S
		}

		.publicMethodTable 1 {
			equals(Ljava/lang/Object;)Z;
			init([BSSS)V;
			finish()S;
			reset()V;
			isInitialized()Z;
			write(SB)V;
			write(SS)V;
			write(S[BSS)V;
			writeNull(S)V;
			writeTag(B)S;
			writeTag(S)S;
			writeLength(S)S;
			setOffset(S)V;
			getOffset()S;
		}

		.packageMethodTable 0 {
		}

		.method public <init>()V 0 {
			.stack 3;
			.locals 0;

				L0:	aload_0;
					invokespecial 202;		// java/lang/Object.<init>()V
					aload_0;
					sconst_1;
					sconst_2;
					invokestatic 219;		// javacard/framework/JCSystem.makeTransientObjectArray(SB)[Ljava/lang/Object;
					putfield_a 35;		// reference com/makina/security/OpenFIPS201/TLVWriter.dataPtr
					aload_0;
					sconst_4;
					sconst_2;
					invokestatic 73;		// javacard/framework/JCSystem.makeTransientShortArray(SB)[S
					putfield_a 36;		// reference com/makina/security/OpenFIPS201/TLVWriter.context
					return;
		}

		.method public init([BSSS)V 1 {
			.stack 7;
			.locals 0;

				L0:	sload_3;
					ifge L2;
				L1:	sspush 26368;
					invokestatic 150;		// javacard/framework/ISOException.throwIt(S)V
				L2:	getfield_a_this 35;		// reference com/makina/security/OpenFIPS201/TLVWriter.dataPtr
					sconst_0;
					aload_1;
					aastore;
					getfield_a_this 36;		// reference com/makina/security/OpenFIPS201/TLVWriter.context
					sconst_2;
					sload_2;
					sastore;
					getfield_a_this 36;		// reference com/makina/security/OpenFIPS201/TLVWriter.context
					sconst_3;
					sload_2;
					sastore;
					getfield_a_this 36;		// reference com/makina/security/OpenFIPS201/TLVWriter.context
					sconst_0;
					sload_3;
					sastore;
					aload_0;
					sload 4;
					invokevirtual 221;		// writeTag(S)S
					pop;
					sload_3;
					bspush 127;
					if_scmpgt L4;
				L3:	getfield_a_this 36;		// reference com/makina/security/OpenFIPS201/TLVWriter.context
					sconst_1;
					getfield_a_this 36;		// reference com/makina/security/OpenFIPS201/TLVWriter.context
					sconst_2;
					dup2;
					saload;
					dup_x 19;
					sconst_1;
					sadd;
					sastore;
					sastore;
					goto L7;
				L4:	sload_3;
					sspush 255;
					if_scmpgt L6;
				L5:	aload_1;
					getfield_a_this 36;		// reference com/makina/security/OpenFIPS201/TLVWriter.context
					sconst_2;
					dup2;
					saload;
					dup_x 19;
					sconst_1;
					sadd;
					sastore;
					bspush -127;
					bastore;
					getfield_a_this 36;		// reference com/makina/security/OpenFIPS201/TLVWriter.context
					sconst_1;
					getfield_a_this 36;		// reference com/makina/security/OpenFIPS201/TLVWriter.context
					sconst_2;
					dup2;
					saload;
					dup_x 19;
					sconst_1;
					sadd;
					sastore;
					sastore;
					getfield_a_this 36;		// reference com/makina/security/OpenFIPS201/TLVWriter.context
					sconst_2;
					dup2;
					saload;
					sconst_1;
					sadd;
					sastore;
					goto L7;
				L6:	aload_1;
					getfield_a_this 36;		// reference com/makina/security/OpenFIPS201/TLVWriter.context
					sconst_2;
					dup2;
					saload;
					dup_x 19;
					sconst_1;
					sadd;
					sastore;
					bspush -126;
					bastore;
					getfield_a_this 36;		// reference com/makina/security/OpenFIPS201/TLVWriter.context
					sconst_1;
					getfield_a_this 36;		// reference com/makina/security/OpenFIPS201/TLVWriter.context
					sconst_2;
					saload;
					sastore;
					getfield_a_this 36;		// reference com/makina/security/OpenFIPS201/TLVWriter.context
					sconst_2;
					dup2;
					saload;
					sconst_2;
					sadd;
					sastore;
				L7:	return;
		}

		.method public finish()S 2 {
			.stack 4;
			.locals 2;

				L0:	getfield_a_this 35;		// reference com/makina/security/OpenFIPS201/TLVWriter.dataPtr
					sconst_0;
					aaload;
					ifnonnull L2;
				L1:	sspush 27012;
					invokestatic 150;		// javacard/framework/ISOException.throwIt(S)V
				L2:	getfield_a_this 35;		// reference com/makina/security/OpenFIPS201/TLVWriter.dataPtr
					sconst_0;
					aaload;
					checkcast 11 0;		// T_BYTE
					checkcast 11 0;		// T_BYTE
					astore_1;
				L3:	getfield_a_this 36;		// reference com/makina/security/OpenFIPS201/TLVWriter.context
					sconst_0;
					saload;
					iflt L9;
				L4:	getfield_a_this 36;		// reference com/makina/security/OpenFIPS201/TLVWriter.context
					sconst_0;
					saload;
					bspush 127;
					if_scmpgt L9;
				L5:	getfield_a_this 36;		// reference com/makina/security/OpenFIPS201/TLVWriter.context
					sconst_2;
					saload;
					getfield_a_this 36;		// reference com/makina/security/OpenFIPS201/TLVWriter.context
					sconst_1;
					saload;
					ssub;
					sconst_1;
					ssub;
					sstore_2;
				L6:	sload_2;
					bspush 127;
					if_scmple L8;
				L7:	sspush 27012;
					invokestatic 150;		// javacard/framework/ISOException.throwIt(S)V
				L8:	aload_1;
					getfield_a_this 36;		// reference com/makina/security/OpenFIPS201/TLVWriter.context
					sconst_1;
					saload;
					sload_2;
					bspush 127;
					sand;
					s2b;
					bastore;
					goto L20;
				L9:	getfield_a_this 36;		// reference com/makina/security/OpenFIPS201/TLVWriter.context
					sconst_0;
					saload;
					iflt L15;
				L10:	getfield_a_this 36;		// reference com/makina/security/OpenFIPS201/TLVWriter.context
					sconst_0;
					saload;
					sspush 255;
					if_scmpgt L15;
				L11:	getfield_a_this 36;		// reference com/makina/security/OpenFIPS201/TLVWriter.context
					sconst_2;
					saload;
					getfield_a_this 36;		// reference com/makina/security/OpenFIPS201/TLVWriter.context
					sconst_1;
					saload;
					ssub;
					sconst_1;
					ssub;
					sstore_2;
				L12:	sload_2;
					sspush 255;
					if_scmple L14;
				L13:	sspush 27012;
					invokestatic 150;		// javacard/framework/ISOException.throwIt(S)V
				L14:	aload_1;
					getfield_a_this 36;		// reference com/makina/security/OpenFIPS201/TLVWriter.context
					sconst_1;
					saload;
					sload_2;
					sspush 255;
					sand;
					s2b;
					bastore;
					goto L20;
				L15:	getfield_a_this 36;		// reference com/makina/security/OpenFIPS201/TLVWriter.context
					sconst_0;
					saload;
					iflt L19;
				L16:	getfield_a_this 36;		// reference com/makina/security/OpenFIPS201/TLVWriter.context
					sconst_0;
					saload;
					sspush 32767;
					if_scmpgt L19;
				L17:	getfield_a_this 36;		// reference com/makina/security/OpenFIPS201/TLVWriter.context
					sconst_2;
					saload;
					getfield_a_this 36;		// reference com/makina/security/OpenFIPS201/TLVWriter.context
					sconst_1;
					saload;
					ssub;
					sconst_2;
					ssub;
					sstore_2;
				L18:	aload_1;
					getfield_a_this 36;		// reference com/makina/security/OpenFIPS201/TLVWriter.context
					sconst_1;
					saload;
					sload_2;
					invokestatic 222;		// javacard/framework/Util.setShort([BSS)S
					pop;
					goto L20;
				L19:	sspush 26368;
					invokestatic 150;		// javacard/framework/ISOException.throwIt(S)V
				L20:	getfield_a_this 36;		// reference com/makina/security/OpenFIPS201/TLVWriter.context
					sconst_2;
					saload;
					getfield_a_this 36;		// reference com/makina/security/OpenFIPS201/TLVWriter.context
					sconst_3;
					saload;
					ssub;
					sstore_2;
				L21:	aload_0;
					invokevirtual 223;		// reset()V
					sload_2;
					sreturn;
		}

		.method public reset()V 3 {
			.stack 3;
			.locals 0;

				L0:	getfield_a_this 35;		// reference com/makina/security/OpenFIPS201/TLVWriter.dataPtr
					sconst_0;
					aconst_null;
					aastore;
					getfield_a_this 36;		// reference com/makina/security/OpenFIPS201/TLVWriter.context
					sconst_3;
					sconst_0;
					sastore;
					getfield_a_this 36;		// reference com/makina/security/OpenFIPS201/TLVWriter.context
					sconst_2;
					sconst_0;
					sastore;
					getfield_a_this 36;		// reference com/makina/security/OpenFIPS201/TLVWriter.context
					sconst_1;
					sconst_0;
					sastore;
					return;
		}

		.method public isInitialized()Z 4 {
			.stack 2;
			.locals 0;

				L0:	getfield_a_this 35;		// reference com/makina/security/OpenFIPS201/TLVWriter.dataPtr
					sconst_0;
					aaload;
					ifnull L2;
				L1:	sconst_1;
					goto L3;
				L2:	sconst_0;
				L3:	sreturn;
		}

		.method public write(SB)V 5 {
			.stack 6;
			.locals 1;

				L0:	getfield_a_this 35;		// reference com/makina/security/OpenFIPS201/TLVWriter.dataPtr
					sconst_0;
					aaload;
					ifnonnull L2;
				L1:	sspush 27012;
					invokestatic 150;		// javacard/framework/ISOException.throwIt(S)V
				L2:	getfield_a_this 35;		// reference com/makina/security/OpenFIPS201/TLVWriter.dataPtr
					sconst_0;
					aaload;
					checkcast 11 0;		// T_BYTE
					checkcast 11 0;		// T_BYTE
					astore_3;
				L3:	aload_0;
					sload_1;
					invokevirtual 221;		// writeTag(S)S
					pop;
					aload_3;
					getfield_a_this 36;		// reference com/makina/security/OpenFIPS201/TLVWriter.context
					sconst_2;
					dup2;
					saload;
					dup_x 19;
					sconst_1;
					sadd;
					sastore;
					sconst_1;
					bastore;
					aload_3;
					getfield_a_this 36;		// reference com/makina/security/OpenFIPS201/TLVWriter.context
					sconst_2;
					dup2;
					saload;
					dup_x 19;
					sconst_1;
					sadd;
					sastore;
					sload_2;
					bastore;
					return;
		}

		.method public write(SS)V 6 {
			.stack 6;
			.locals 1;

				L0:	getfield_a_this 35;		// reference com/makina/security/OpenFIPS201/TLVWriter.dataPtr
					sconst_0;
					aaload;
					ifnonnull L2;
				L1:	sspush 27012;
					invokestatic 150;		// javacard/framework/ISOException.throwIt(S)V
				L2:	getfield_a_this 35;		// reference com/makina/security/OpenFIPS201/TLVWriter.dataPtr
					sconst_0;
					aaload;
					checkcast 11 0;		// T_BYTE
					checkcast 11 0;		// T_BYTE
					astore_3;
				L3:	aload_0;
					sload_1;
					invokevirtual 221;		// writeTag(S)S
					pop;
					aload_3;
					getfield_a_this 36;		// reference com/makina/security/OpenFIPS201/TLVWriter.context
					sconst_2;
					dup2;
					saload;
					dup_x 19;
					sconst_1;
					sadd;
					sastore;
					sconst_2;
					bastore;
					aload_3;
					getfield_a_this 36;		// reference com/makina/security/OpenFIPS201/TLVWriter.context
					sconst_2;
					saload;
					sload_2;
					invokestatic 222;		// javacard/framework/Util.setShort([BSS)S
					pop;
					getfield_a_this 36;		// reference com/makina/security/OpenFIPS201/TLVWriter.context
					sconst_2;
					dup2;
					saload;
					sconst_2;
					sadd;
					sastore;
					return;
		}

		.method public write(S[BSS)V 7 {
			.stack 5;
			.locals 1;

				L0:	getfield_a_this 35;		// reference com/makina/security/OpenFIPS201/TLVWriter.dataPtr
					sconst_0;
					aaload;
					ifnonnull L2;
				L1:	sspush 27012;
					invokestatic 150;		// javacard/framework/ISOException.throwIt(S)V
				L2:	getfield_a_this 35;		// reference com/makina/security/OpenFIPS201/TLVWriter.dataPtr
					sconst_0;
					aaload;
					checkcast 11 0;		// T_BYTE
					checkcast 11 0;		// T_BYTE
					astore 5;
				L3:	aload_0;
					sload_1;
					invokevirtual 221;		// writeTag(S)S
					pop;
					aload_0;
					sload 4;
					invokevirtual 131;		// writeLength(S)S
					pop;
					aload_2;
					sload_3;
					aload 5;
					getfield_a_this 36;		// reference com/makina/security/OpenFIPS201/TLVWriter.context
					sconst_2;
					saload;
					sload 4;
					invokestatic 160;		// javacard/framework/Util.arrayCopy([BS[BSS)S
					pop;
					getfield_a_this 36;		// reference com/makina/security/OpenFIPS201/TLVWriter.context
					sconst_2;
					dup2;
					saload;
					sload 4;
					sadd;
					sastore;
					return;
		}

		.method public writeNull(S)V 8 {
			.stack 6;
			.locals 1;

				L0:	getfield_a_this 35;		// reference com/makina/security/OpenFIPS201/TLVWriter.dataPtr
					sconst_0;
					aaload;
					ifnonnull L2;
				L1:	sspush 27012;
					invokestatic 150;		// javacard/framework/ISOException.throwIt(S)V
				L2:	getfield_a_this 35;		// reference com/makina/security/OpenFIPS201/TLVWriter.dataPtr
					sconst_0;
					aaload;
					checkcast 11 0;		// T_BYTE
					checkcast 11 0;		// T_BYTE
					astore_2;
				L3:	aload_0;
					sload_1;
					invokevirtual 221;		// writeTag(S)S
					pop;
					aload_2;
					getfield_a_this 36;		// reference com/makina/security/OpenFIPS201/TLVWriter.context
					sconst_2;
					dup2;
					saload;
					dup_x 19;
					sconst_1;
					sadd;
					sastore;
					sconst_0;
					bastore;
					return;
		}

		.method public writeTag(B)S 9 {
			.stack 3;
			.locals 0;

				L0:	aload_0;
					sload_1;
					sspush 255;
					sand;
					invokevirtual 221;		// writeTag(S)S
					sreturn;
		}

		.method public writeTag(S)S 10 {
			.stack 4;
			.locals 0;

				L0:	sload_1;
					iflt L3;
				L1:	sload_1;
					sspush 255;
					if_scmpgt L3;
				L2:	getfield_a_this 35;		// reference com/makina/security/OpenFIPS201/TLVWriter.dataPtr
					sconst_0;
					aaload;
					checkcast 11 0;		// T_BYTE
					checkcast 11 0;		// T_BYTE
					getfield_a_this 36;		// reference com/makina/security/OpenFIPS201/TLVWriter.context
					sconst_2;
					saload;
					sload_1;
					s2b;
					bastore;
					getfield_a_this 36;		// reference com/makina/security/OpenFIPS201/TLVWriter.context
					sconst_2;
					dup2;
					saload;
					sconst_1;
					sadd;
					sastore;
					sconst_1;
					sreturn;
				L3:	getfield_a_this 35;		// reference com/makina/security/OpenFIPS201/TLVWriter.dataPtr
					sconst_0;
					aaload;
					checkcast 11 0;		// T_BYTE
					checkcast 11 0;		// T_BYTE
					getfield_a_this 36;		// reference com/makina/security/OpenFIPS201/TLVWriter.context
					sconst_2;
					saload;
					sload_1;
					invokestatic 222;		// javacard/framework/Util.setShort([BSS)S
					pop;
					getfield_a_this 36;		// reference com/makina/security/OpenFIPS201/TLVWriter.context
					sconst_2;
					dup2;
					saload;
					sconst_2;
					sadd;
					sastore;
					sconst_2;
					sreturn;
		}

		.method public writeLength(S)S 11 {
			.stack 6;
			.locals 1;

				L0:	getfield_a_this 35;		// reference com/makina/security/OpenFIPS201/TLVWriter.dataPtr
					sconst_0;
					aaload;
					checkcast 11 0;		// T_BYTE
					checkcast 11 0;		// T_BYTE
					astore_2;
				L1:	sload_1;
					iflt L4;
				L2:	sload_1;
					bspush 127;
					if_scmpgt L4;
				L3:	aload_2;
					getfield_a_this 36;		// reference com/makina/security/OpenFIPS201/TLVWriter.context
					sconst_2;
					dup2;
					saload;
					dup_x 19;
					sconst_1;
					sadd;
					sastore;
					sload_1;
					s2b;
					bastore;
					sconst_1;
					sreturn;
				L4:	sload_1;
					bspush 127;
					if_scmple L7;
				L5:	sload_1;
					sspush 255;
					if_scmpgt L7;
				L6:	aload_2;
					getfield_a_this 36;		// reference com/makina/security/OpenFIPS201/TLVWriter.context
					sconst_2;
					dup2;
					saload;
					dup_x 19;
					sconst_1;
					sadd;
					sastore;
					bspush -127;
					bastore;
					aload_2;
					getfield_a_this 36;		// reference com/makina/security/OpenFIPS201/TLVWriter.context
					sconst_2;
					dup2;
					saload;
					dup_x 19;
					sconst_1;
					sadd;
					sastore;
					sload_1;
					s2b;
					bastore;
					sconst_2;
					sreturn;
				L7:	aload_2;
					getfield_a_this 36;		// reference com/makina/security/OpenFIPS201/TLVWriter.context
					sconst_2;
					dup2;
					saload;
					dup_x 19;
					sconst_1;
					sadd;
					sastore;
					bspush -126;
					bastore;
					aload_2;
					getfield_a_this 36;		// reference com/makina/security/OpenFIPS201/TLVWriter.context
					sconst_2;
					saload;
					sload_1;
					invokestatic 222;		// javacard/framework/Util.setShort([BSS)S
					pop;
					getfield_a_this 36;		// reference com/makina/security/OpenFIPS201/TLVWriter.context
					sconst_2;
					dup2;
					saload;
					sconst_2;
					sadd;
					sastore;
					sconst_3;
					sreturn;
		}

		.method public setOffset(S)V 12 {
			.stack 3;
			.locals 0;

				L0:	getfield_a_this 36;		// reference com/makina/security/OpenFIPS201/TLVWriter.context
					sconst_2;
					sload_1;
					sastore;
					return;
		}

		.method public getOffset()S 13 {
			.stack 2;
			.locals 0;

				L0:	getfield_a_this 36;		// reference com/makina/security/OpenFIPS201/TLVWriter.context
					sconst_2;
					saload;
					sreturn;
		}

	}

}
